Workbook

Sheet README
A1: Property Visualisation SaaS — 36-month financial model
A2: Purpose | B2: Test whether a UK-first AI property visualisation SaaS (floor plans / CAD / IFC → geometry-true 3D, renders, tours, video, white-label viewers and configurators) can become a viable business. Built to be conservative: the aim is to find out whether the idea deserves to exist, not to flatter it.
A3: Date / currency | B3: Built 20 Oct 2026. Model currency GBP (£); vendor prices in USD converted at the FX rate below. Prices ex VAT. No corporation tax, VAT timing, R&D credits, capex or working-capital effects (annual prepayments ignored).
A4: FX rate | B4: £0.755 per US$1 (≈ $1.324 per £) — X-Rates October 2026 monthly average (0.755183, 20 days). Editable at Assumptions!D6.
A5: How to use | B5: 1) Change blue cells on Assumptions (and the target-GM row on Pricing, milestone thresholds on Milestones). 2) Everything else recalculates. 3) Read Summary first, then Milestones, Pricing, Unit_Costs. Scenario sheets (Model_Bear / Model_Base / Model_Bull) use Assumptions columns C / D / E respectively. Unit-cost Low/Base/High also use columns C / D / E; each scenario picks a cost case via 'Unit-cost case used'.
A6: Colour legend | B6: Blue text = hard-coded input you can change. Black text = formula. Green text = direct link to another sheet. Yellow-shaded label = ASSUMPTION (modeller's judgement, no source in notes). Light-yellow rows in model sheets = key outputs.
A7: Source labels | B7: VERIFIED = quoted from a vendor or primary page cited in the research notes. ESTIMATE = researcher estimate built from cited prices. ASSUMPTION = modeller's judgement where the notes have no figure (replace with pilot data).
A8: Sheets | B8: Assumptions · Unit_Costs (cost per successful deliverable, Low/Base/High, retry/failure table) · Pricing (tiers, allowances, overage, setup, per-development; GM at included usage; price for 60/70/80/85% GM) · Model_Bear / Model_Base / Model_Bull (monthly, 36m) · Milestones · Summary.
A9: Key modelling choices | B9: MRR milestone metric = subscription MRR only (overage, setup and per-development fees are revenue but not MRR). Customers are expected values (fractional). Hires are step functions triggered by the previous month's customers or MRR. Human QA is costed at contractor rates in COGS even when the founder does it (conservative). Enterprise wins cannot start before month 12 (Base), 18 (Bear), 10 (Bull). Self-serve launch month 6 (Base), 9 (Bear), 4 (Bull).
A10: Research notes | B10: /home/user/widgetme-legal/research_notes/AI property visualisation SaaS audit/ : pricing_inputs.md, market_segments.md, gtm_benchmarks.md, competitors.md, technical_feasibility.md, legal_compliance.md
A12: Sources (from notes)
A13: Claude API pricing (LLM tokens) | B13: https://platform.claude.com/docs/en/about-claude/pricing
A14: Gemini API pricing (Nano Banana images, Veo video) | B14: https://ai.google.dev/gemini-api/docs/pricing
A15: Kling API video pricing | B15: https://kling.ai/document-api/pricing/base/video.md
A16: RunPod GPU pricing | B16: https://www.runpod.io/pricing
A17: AWS g6e.xlarge (Vantage) | B17: https://instances.vantage.sh/aws/ec2/g6e.xlarge
A18: AWS GameLift Streams pricing | B18: https://aws.amazon.com/gamelift/streams/pricing/
A19: Vagon Streams pricing | B19: https://vagon.io/streams/pricing
A20: Cloudflare R2 pricing | B20: https://developers.cloudflare.com/r2/pricing/
A21: Bunny CDN pricing | B21: https://bunny.net/pricing/
A22: Autodesk Flex tokens (APS) | B22: https://www.autodesk.com/buying/flex
A23: APS business model change | B23: https://aps.autodesk.com/blog/aps-business-model-evolution
A24: Upwork rendering freelancer rates | B24: https://www.upwork.com/hire/architectural-rendering-freelancers/cost/
... A47: UK stand sample budget | B47: https://boothexhibits.com/?p=19816

Sheet Assumptions
A1: Assumptions — all model inputs (blue = editable input; black = formula)
A2: Columns C/D/E: for unit-cost inputs = Low / Base / High cost case; for growth inputs = Bear / Base / Bull scenario. Single-value inputs sit in column D. Labels: VERIFIED = quoted from a vendor/primary page in the research notes; ESTIMATE = researcher estimate built from cited prices; ASSUMPTION = modeller's judgement where the notes have no figure.
A4: 1. General
A5: Parameter | B5: Unit | C5: Low / Bear | D5: Base | E5: High / Bull | F5: Label | G5: Source / reasoning
A6: FX rate: GBP per 1 USD | B6: £ per $ | D6: 0.755 | F6: VERIFIED | G6: X-Rates Oct-2026 monthly average 0.755183 (20 days) — https://www.x-rates.com/average/?from=USD&to=GBP&amount=1&year=2026
A7: Starting cash (founder-funded) | B7: £ | D7: 50000 | F7: ASSUMPTION | G7: Brief example: £50k founder-funded. No external funding modelled.
A8: Model horizon | B8: months | D8: 36 | F8: ASSUMPTION | G8: 36 monthly periods; month 1 = first month of company operation (pre-launch build included)
A10: 2. Unit-cost component prices (USD unless stated) — Low / Base / High cost case
A11: Parameter | B11: Unit | C11: Low / Bear | D11: Base | E11: High / Bull | F11: Label | G11: Source / reasoning
A12: LLM floor-plan parse (one high-res plan, structured JSON) | B12: $ / plan | C12: 0.026 | D12: 0.052 | E12: 0.1 | F12: ESTIMATE | G12: pricing_inputs §1: Sonnet 5.5 ≈ $0.052; Batch ≈ $0.026; Opus 5.5 ≈ $0.10 — https://platform.claude.com/docs/en/about-claude/pricing
A13: LLM orchestration + vision QA per generated image | B13: $ / image | C13: 0.02 | D13: 0.03 | E13: 0.05 | F13: ESTIMATE | G13: pricing_inputs §1: $0.02–0.05 per room image on Sonnet 5.5 — https://platform.claude.com/docs/en/about-claude/pricing
A14: LLM shot planning / prompting per video | B14: $ / video | C14: 0.05 | D14: 0.1 | E14: 0.2 | F14: ASSUMPTION | G14: Not in notes; scaled from per-image orchestration cost (a video = ~6 shots).
A15: Image generation per attempt (4K photoreal) | B15: $ / attempt | C15: 0.113 | D15: 0.24 | E15: 0.24 | F15: VERIFIED | G15: Gemini Nano Banana 2.1 4K $0.113 (low); Nano Banana Pro 4K $0.24 (base/high) — https://ai.google.dev/gemini-api/docs/pricing
A16: Generation attempts per accepted image | B16: x | C16: 2 | D16: 3 | E16: 4 | F16: ESTIMATE | G16: pricing_inputs §12: 3 attempts per accepted 4K image (gap: replace with pilot data)
A17: Standard walkthrough video generation | B17: $ / second | C17: 0.07 | D17: 0.12 | E17: 0.168 | F17: VERIFIED | G17: Kling 2.6 1080p $0.07/s; Veo 3.1 Fast 1080p $0.12/s; Kling 3.0 with audio 1080p $0.168/s — https://ai.google.dev/gemini-api/docs/pricing ; https://kling.ai/document-api/pricing/base/video.md
A18: Cinematic video generation | B18: $ / second | C18: 0.12 | D18: 0.4 | E18: 0.6 | F18: VERIFIED | G18: Veo 3.1 Fast $0.12/s (low); Veo 3.1 Std 1080p $0.40/s (base); Veo Std 4K $0.60/s (high) — https://ai.google.dev/gemini-api/docs/pricing
A19: Video retake multiplier (seconds billed / seconds delivered) | B19: x | C19: 1.5 | D19: 2 | E19: 3 | F19: ESTIMATE | G19: pricing_inputs §12: 2x retakes assumed; range is modeller's
A20: Length of standard walkthrough video | B20: seconds | D20: 30 | F20: ASSUMPTION | G20: Deliverable definition (30s walkthrough)
A21: Length of cinematic video | B21: seconds | D21: 60 | F21: ASSUMPTION | G21: Deliverable definition (60s cinematic)
A22: GPU rental for scene build / base render (Blender headless) | B22: $ / GPU-hour | C22: 0.59 | D22: 1.09 | E22: 1.86 | F22: VERIFIED | G22: RunPod L4 $0.59/h; RunPod L40S $1.09/h; AWS g6e.xlarge L40S $1.861/h — https://www.runpod.io/pricing ; https://instances.vantage.sh/aws/ec2/g6e.xlarge
A23: GPU-hours multiplier vs base quantities | B23: x | C23: 0.5 | D23: 1 | E23: 2 | F23: ESTIMATE | G23: pricing_inputs §5: 4K Cycles still 2–10 min on RTX 4090; scene build ~1h L40S. Modelling/asset setup can dominate.
A24: Interactive viewer: pixel-streaming hours per hosted property per month | B24: hours | C24: 0 | D24: 2 | E24: 6.65 | F24: ESTIMATE | G24: pricing_inputs §6: 100 sessions x 8 min = 13.3 h if fully pixel-streamed; high = 50% of sessions streamed (6.65 h). Low = WebGL/three.js only (≈$0). Base = WebGL default + occasional streaming (ASSUMPTION).
A25: Pixel-streaming capacity price | B25: $ / user-hour | C25: 1.82 | D25: 1.82 | E25: 2.82 | F25: VERIFIED | G25: AWS GameLift Streams gen6n_ultra L4 $1.82/h; Vagon L4 Pro G3 $2.82/h — https://aws.amazon.com/gamelift/streams/pricing/ ; https://vagon.io/streams/pricing
A26: Object storage (Cloudflare R2 Standard) | B26: $ / GB-month | D26: 0.015 | F26: VERIFIED | G26: https://developers.cloudflare.com/r2/pricing/
A27: Storage retention charged per deliverable | B27: months | D27: 12 | F27: ASSUMPTION | G27: Assets kept 12 months in hot storage
A28: CDN delivery (Bunny) | B28: $ / GB | C28: 0.005 | D28: 0.01 | E28: 0.01 | F28: VERIFIED | G28: Bunny $0.01/GB EU/NA; $0.005 volume network — https://bunny.net/pricing/
A29: CDN GB per hosted interactive property per month | B29: GB | D29: 10 | F29: ESTIMATE | G29: ~100 WebGL sessions x ~100 MB (modeller's estimate based on pricing_inputs §6 session count)
A30: CAD translation fee (Autodesk APS Flex) per DWG/RVT file | B30: $ / file | C30: 0 | D30: 1.5 | E30: 3 | F30: ESTIMATE | G30: pricing_inputs §8: budget $1.50–$3/file (UNVERIFIED after Dec-2025 APS price change); low = IFC/DXF via open-source parsers — https://www.autodesk.com/buying/flex
A31: Share of plans needing paid CAD translation | B31: % | D31: 0.3 | F31: ASSUMPTION | G31: Most inputs are PDF/raster or IFC/DXF (free parsers); ODA SDK licence covers DWG in-house
A32: Human QA / 2D-confirm operator rate (fully loaded) | B32: $ / hour | C32: 15 | D32: 25 | E32: 35 | F32: ESTIMATE | G32: pricing_inputs §11: offshore $15–25/h (Upwork median $20–30/h; 3D artists $25–40/h); high = $35/h — https://www.upwork.com/hire/architectural-rendering-freelancers/cost/
A33: Human 2D vector/scale confirm-edit per plan | B33: minutes / plan | C33: 3 | D33: 10 | E33: 15 | F33: ESTIMATE | G33: technical_feasibility §7: target 3–5 min clean CAD, 10–15 min scans; pricing_inputs §11: 10–20 min per plan. Mandatory HITL step for raster input — https://tool.planner5d.com/b2b-floor-plan-recognition
A34: Human review per delivered image attempt | B34: minutes / image | C34: 0.5 | D34: 1 | E34: 1.5 | F34: ASSUMPTION | G34: Not measured in notes. Automated drift QA + human spot-check of every customer-facing image (DMCC 2024 misdescription risk).
A35: Human review per video attempt | B35: minutes / video | C35: 5 | D35: 10 | E35: 15 | F35: ASSUMPTION | G35: Watch-through + shot check; not in notes
A36: Human check per development unit (finish swaps / availability data) | B36: minutes / unit | C36: 1 | D36: 1.5 | E36: 2.5 | F36: ASSUMPTION | G36: Not in notes
A37: Customer support handling rate (allocated to COGS) | B37: $ / hour | C37: 25 | D37: 30 | E37: 35 | F37: ASSUMPTION | G37: UK part-time/outsourced support; no UK support salary in notes (gtm_benchmarks gaps)
A38: Support minutes multiplier vs base quantities | B38: x | C38: 0.5 | D38: 1 | E38: 1.5 | F38: ASSUMPTION | G38: Tickets, revision requests, re-uploads
A39: Deliverable-level QA rejection / redo rate used for COGS | B39: % | C39: 0.05 | D39: 0.15 | E39: 0.25 | F39: ASSUMPTION | G39: On top of per-image attempts. Applied as cost per success = fixed + repeatable/(1-f). Replace with pilot data.
A40: Failure-table rate 1 | B40: % | D40: 0.05 | F40: ASSUMPTION | G40: Retry/failure sensitivity table
A41: Failure-table rate 2 | B41: % | D41: 0.15 | F41: ASSUMPTION | G41: Retry/failure sensitivity table
A42: Failure-table rate 3 | B42: % | D42: 0.3 | F42: ASSUMPTION | G42: Retry/failure sensitivity table
A43: Failure-table rate 4 | B43: % | D43: 0.5 | F43: ASSUMPTION | G43: Retry/failure sensitivity table
A44: Storage per hosted interactive property | B44: GB | D44: 2 | F44: ESTIMATE | G44: pricing_inputs §7: ~2 GB source scenes per property
A46: 3. Development deliverable definitions
A47: Parameter | B47: Unit | C47: Low / Bear | D47: Base | E47: High / Bull | F47: Label | G47: Source / reasoning
A48: 50-unit development: distinct plan (house) types | B48: types | D48: 6 | F48: ESTIMATE | G48: pricing_inputs §12 example: 6 floor-plan types
A49: 50-unit development: units | B49: units | D49: 50 | F49: ESTIMATE | G49: pricing_inputs §12
A50: 200-unit development: distinct plan types | B50: types | D50: 15 | F50: ESTIMATE | G50: pricing_inputs §12 example: 15 types (repeated plan types)
A51: 200-unit development: units | B51: units | D51: 200 | F51: ESTIMATE | G51: pricing_inputs §12
A52: Images per unit (1 plan render + 2 finish swaps) | B52: images / unit | D52: 3 | F52: ESTIMATE | G52: pricing_inputs §12: 50 x (1 plan render + 2 finish swaps)
A53: Site-plan / availability setup QA per development | B53: minutes | D53: 60 | F53: ASSUMPTION | G53: Not in notes
A54: Site-plan / aerial GPU hours per development | B54: GPU-hours | D54: 2 | F54: ASSUMPTION | G54: Not in notes
A55: Credits charged per development unit | B55: credits / unit | D55: 3 | F55: ASSUMPTION | G55: Credit design choice
A57: 4. Deliverable quantity drivers (base quantities; cost case changes prices/minutes, not quantities)
A58: Deliverable | B58: Plans (2D confirm) | C58: Accepted images | D58: 30s videos | E58: 60s videos | F58: GPU-hours | G58: Interactive props | H58: Storage GB | I58: CDN GB | J58: Dev units | K58: Extra QA min | L58: Support min | M58: Credits charged
A59: Single room image | B59: 1 | C59: 1 | D59: 0 | E59: 0 | F59: 0.05 | G59: 0 | H59: 0.1 | I59: 0.5 | J59: 0 | K59: 0 | L59: 2 | M59: 5
A60: 5 room images | B60: 1 | C60: 5 | D60: 0 | E60: 0 | F60: 0.2 | G60: 0 | H60: 0.5 | I60: 2 | J60: 0 | K60: 2 | L60: 3 | M60: 10
A61: 2-bed flat (8 images + plan) | B61: 1 | C61: 8 | D61: 0 | E61: 0 | F61: 0.5 | G61: 0 | H61: 1 | I61: 5 | J61: 0 | K61: 5 | L61: 5 | M61: 15
A62: 4-bed house (19 images, 2 floors) | B62: 2 | C62: 19 | D62: 0 | E62: 0 | F62: 1 | G62: 0 | H62: 2 | I62: 10 | J62: 0 | K62: 10 | L62: 8 | M62: 32
A63: Interactive 3D property (WebGL tour, 1st month hosting) | B63: 1 | C63: 0 | D63: 0 | E63: 0 | F63: 1 | G63: 1 | H63: 2 | I63: 10 | J63: 0 | K63: 15 | L63: 10 | M63: 20
A64: 30s walkthrough video | B64: 1 | C64: 0 | D64: 1 | E64: 0 | F64: 0.5 | G64: 0 | H64: 0.5 | I64: 5 | J64: 0 | K64: 0 | L64: 5 | M64: 20
A65: 60s cinematic video | B65: 1 | C65: 0 | D65: 0 | E65: 1 | F65: 1 | G65: 0 | H65: 1 | I65: 10 | J65: 0 | K65: 0 | L65: 8 | M65: 60
A66: Developer marketing package (per house type) | B66: 2 | C66: 22 | D66: 1 | E66: 1 | F66: 2 | G66: 1 | H66: 3 | I66: 20 | J66: 0 | K66: 30 | L66: 30 | M66: 160
A67: 50-unit development (6 plan types) | B67: =Assumptions!$D$48*B$66 -> 12 | C67: =Assumptions!$D$48*C$66+Assumptions!$D$49*Assumptions!$D$52 -> 282 | D67: =Assumptions!$D$48*D$66 -> 6 | E67: =Assumptions!$D$48*E$66 -> 6 | F67: =Assumptions!$D$48*F$66+Assumptions!$D$54 -> 14 | G67: =Assumptions!$D$48*G$66 -> 6 | H67: =Assumptions!$D$48*H$66+Assumptions!$D$49*0.1 -> 23 | I67: =Assumptions!$D$48*I$66+Assumptions!$D$49*1 -> 170 | J67: =Assumptions!$D$49 -> 50 | K67: =Assumptions!$D$48*K$66+Assumptions!$D$53 -> 240 | L67: =120 -> 120 | M67: =Assumptions!$D$48*M$66+Assumptions!$D$49*Assumptions!$D$55 -> 1110
A68: 200-unit development (15 plan types) | B68: =Assumptions!$D$50*B$66 -> 30 | C68: =Assumptions!$D$50*C$66+Assumptions!$D$51*Assumptions!$D$52 -> 930 | D68: =Assumptions!$D$50*D$66 -> 15 | E68: =Assumptions!$D$50*E$66 -> 15 | F68: =Assumptions!$D$50*F$66+Assumptions!$D$54 -> 32 | G68: =Assumptions!$D$50*G$66 -> 15 | H68: =Assumptions!$D$50*H$66+Assumptions!$D$51*0.1 -> 65 | I68: =Assumptions!$D$50*I$66+Assumptions!$D$51*1 -> 500 | J68: =Assumptions!$D$51 -> 200 | K68: =Assumptions!$D$50*K$66+Assumptions!$D$53 -> 510 | L68: =240 -> 240 | M68: =Assumptions!$D$50*M$66+Assumptions!$D$51*Assumptions!$D$55 -> 3000
A69: Rows 1–8 quantities: ESTIMATE from pricing_inputs §12 (image counts per flat/house/package) and §5–7 (GPU, storage, CDN); support minutes and credits are ASSUMPTIONS. Rows 9–10 are formulas: plan types x house-type package + units x per-unit images (cost scales with plan types, not units). Development support minutes (120/240) are ASSUMPTIONS.
A71: 5. Pricing inputs (recommended structure; prices are hypotheses — none observed for this product)
A72: Parameter | B72: Unit | C72: Low / Bear | D72: Base | E72: High / Bull | F72: Label | G72: Source / reasoning
A73: Studio list price | B73: £ / month | D73: 149 | F73: ASSUMPTION | G73: Brief hypothesis. Anchors: Metropix £44.90–£59.75/office/mo; agent WTP £50–£150/branch/mo (market_segments Q4) — https://www.landmark.co.uk/products/metropix/pricing/
A74: Agency list price (white-label viewer) | B74: £ / month | D74: 499 | F74: ASSUMPTION | G74: Brief hypothesis. Anchors: prime agents £400–£1,000/office/mo; marketing agencies £3k–£10k/yr seats (market_segments Q4/Q6)
A75: Developer Pro list price (1 live development hosted) | B75: £ / month | D75: 1499 | F75: ASSUMPTION | G75: Brief hypothesis. Anchors: developers £5k–£25k/scheme/yr; Rightmove New Homes £2,135/dev/mo; ProPlan configurator $499/mo — https://www.londonstockexchange.com/news-article/RMV/annual-financial-report/17479517
A76: Enterprise price used in model (range £3k–£10k+) | B76: £ / month | D76: 5000 | F76: ASSUMPTION | G76: Brief range £3k–£10k+. Nationals WTP £50k–£250k/yr enterprise licence (market_segments Q4 [HYP])
A77: Enterprise hypothesis — low point | B77: £ / month | D77: 3000 | F77: ASSUMPTION | G77: Brief range
A78: Enterprise hypothesis — high point | B78: £ / month | D78: 10000 | F78: ASSUMPTION | G78: Brief range
A79: Studio overage price | B79: £ / credit | D79: 4 | F79: ASSUMPTION | G79: Set above included-credit value to protect margin
A80: Agency overage price | B80: £ / credit | D80: 3.5 | F80: ASSUMPTION
A81: Developer Pro overage price | B81: £ / credit | D81: 3 | F81: ASSUMPTION
A82: Enterprise overage price | B82: £ / credit | D82: 2.5 | F82: ASSUMPTION
A83: Studio setup fee | B83: £ one-off | D83: 0 | F83: ASSUMPTION | G83: Self-serve
A84: Agency setup fee (white-label branding) | B84: £ one-off | D84: 500 | F84: ASSUMPTION
A85: Developer Pro setup fee | B85: £ one-off | D85: 1500 | F85: ASSUMPTION | G85: Anchors: ProPlan $1,000 per-model setup; Realitiq €2,000 setup — https://www.proplanstudio.com/ ; https://www.realitiq.com/en/prices-for-projects/
A86: Enterprise setup / integration fee | B86: £ one-off | D86: 7500 | F86: ASSUMPTION | G86: realtySTUDIO launch packages $12.5k–$59.5k (competitors Q3)
A87: Per-development fee: price per plan (house) type, additional developments | B87: £ / plan type | D87: 350 | F87: ASSUMPTION | G87: competitors Q3 inference: UK entrant could anchor £300–£600 per plot type + platform fee; Realitiq €400–600/unit
A88: Studio: hosted interactive properties (avg) | B88: properties | D88: 1 | F88: ASSUMPTION
A89: Agency: hosted interactive properties (avg) | B89: properties | D89: 5 | F89: ASSUMPTION
A90: Developer Pro: hosted interactive properties / plots (avg) | B90: properties | D90: 15 | F90: ASSUMPTION
A91: Enterprise: hosted interactive properties / plots (avg) | B91: properties | D91: 50 | F91: ASSUMPTION
A92: Studio: SSO connections | B92: connections | D92: 0 | F92: ASSUMPTION
A93: Agency: SSO connections | B93: connections | D93: 0 | F93: ASSUMPTION
A94: Developer Pro: SSO connections | B94: connections | D94: 0 | F94: ASSUMPTION
A95: Enterprise: SSO connections | B95: connections | D95: 1 | F95: ASSUMPTION | G95: Enterprise requires SAML SSO (legal_compliance: procurement norms UNVERIFIED)
A96: WorkOS SSO price per connection (1–15) | B96: $ / month | D96: 125 | F96: VERIFIED | G96: https://workos.com/pricing
A97: Studio payment fees (% of billing) | B97: % | D97: 0.022 | F97: VERIFIED | G97: Stripe UK card 1.5% + Billing 0.7% — https://stripe.com/gb/pricing
A98: Agency payment fees (% of billing) | B98: % | D98: 0.022 | F98: VERIFIED | G98: Stripe UK card 1.5% + Billing 0.7%
A99: Developer Pro payment fees (% of billing) | B99: % | D99: 0.011 | F99: VERIFIED | G99: Invoice 0.4% + Billing 0.7% + Bacs (capped £4, below) — https://stripe.com/gb/pricing
A100: Enterprise payment fees (% of billing) | B100: % | D100: 0.011 | F100: VERIFIED | G100: Invoice 0.4% + Billing 0.7% + Bacs cap £4
A101: Studio payment fixed fee | B101: £ / invoice | D101: 0.2 | F101: VERIFIED | G101: Stripe 20p per card transaction
A102: Agency payment fixed fee | B102: £ / invoice | D102: 0.2 | F102: VERIFIED | G102: Stripe 20p
A103: Developer Pro payment fixed fee | B103: £ / invoice | D103: 4 | F103: VERIFIED | G103: Bacs Direct Debit 1% capped at £4
A104: Enterprise payment fixed fee | B104: £ / invoice | D104: 4 | F104: VERIFIED | G104: Bacs cap £4
A105: Studio onboarding labour | B105: hours / new customer | D105: 0.5 | F105: ASSUMPTION
...

Sheet Unit_Costs
A1: Unit costs — cost per SUCCESSFUL deliverable, built from components (USD unless stated)
A2: Repeatable components (LLM, image gen, video gen, GPU, output-review QA) are re-incurred when a deliverable is rejected; fixed components (2D confirm, hosting, storage, CDN, CAD fees, support) are incurred once. Cost per success = fixed + repeatable / (1 − failure rate). Human labour (2D confirm + QA + support) is shown explicitly.
A4: LOW cost case
A5: Deliverable | B5: LLM tokens | C5: Image gen | D5: Video gen | E5: GPU render | F5: 3D streaming (1st mo) | G5: Storage | H5: CDN | I5: 3rd-party fees (CAD) | J5: Human 2D confirm | K5: Human output QA | L5: Support alloc. | M5: Attempt cost (USD) | N5: of which repeatable | O5: Failure rate | P5: Cost / success (USD) | Q5: Cost / success (GBP) | R5: Human labour share | S5: Human minutes / success
A6: Single room image | B6: =Assumptions!$B$59*Assumptions!$C$12+Assumptions!$C$59*Assumptions!$C$13+(Assumptions!$D$59+Assumptions!$E$59)*Assumptions!$C$14 -> 0.046 | C6: =Assumptions!$C$59*Assumptions!$C$16*Assumptions!$C$15 -> 0.226 | D6: =(Assumptions!$D$59*Assumptions!$D$20*Assumptions!$C$17+Assumptions!$E$59*Assumptions!$D$21*Assumptions!$C$18)*Assumptions!$C$19 -> 0 | E6: =Assumptions!$F$59*Assumptions!$C$23*Assumptions!$C$22 -> 0.01475 | F6: =Assumptions!$G$59*Assumptions!$C$24*Assumptions!$C$25 -> 0 | G6: =Assumptions!$H$59*Assumptions!$D$26*Assumptions!$D$27 -> 0.018 | H6: =Assumptions!$I$59*Assumptions!$C$28 -> 0.0025 | I6: =Assumptions!$B$59*Assumptions!$D$31*Assumptions!$C$30 -> 0 | J6: =Assumptions!$B$59*Assumptions!$C$33/60*Assumptions!$C$32 -> 0.75 | K6: =(Assumptions!$C$59*Assumptions!$C$34+(Assumptions!$D$59+Assumptions!$E$59)*Assumptions!$C$35+Assumptions!$J$59*Assumptions!$C$36+Assumptions!$K$59)/60*Assumptions!$C$32 -> 0.125 | L6: =Assumptions!$L$59*Assumptions!$C$38/60*Assumptions!$C$37 -> 0.41666667 | M6: =SUM(B6:L6) -> 1.5989167 | N6: =B6+C6+D6+E6+K6 -> 0.41175 | O6: =Assumptions!$C$39 -> 0.05 | P6: =(M6-N6)+N6/(1-O6) -> 1.6205877 | Q6: =P6*Assumptions!$D$6 -> 1.2235437 | R6: =IF(P6=0,0,(J6+K6/(1-O6)+L6)/P6) -> 0.80109555 | S6: =Assumptions!$B$59*Assumptions!$C$33+(Assumptions!$C$59*Assumptions!$C$34+(Assumptions!$D$59+Assumptions!$E$59)*Assumptions!$C$35+Assumptions!$J$59*Assumptions!$C$36+Assumptions!$K$59)/(1-O6)+Assumptions!$L$59*Assumptions!$C$38 -> 4.5263158
A7: 5 room images | B7: =Assumptions!$B$60*Assumptions!$C$12+Assumptions!$C$60*Assumptions!$C$13+(Assumptions!$D$60+Assumptions!$E$60)*Assumptions!$C$14 -> 0.126 | C7: =Assumptions!$C$60*Assumptions!$C$16*Assumptions!$C$15 -> 1.13 | D7: =(Assumptions!$D$60*Assumptions!$D$20*Assumptions!$C$17+Assumptions!$E$60*Assumptions!$D$21*Assumptions!$C$18)*Assumptions!$C$19 -> 0 | E7: =Assumptions!$F$60*Assumptions!$C$23*Assumptions!$C$22 -> 0.059 | F7: =Assumptions!$G$60*Assumptions!$C$24*Assumptions!$C$25 -> 0 | G7: =Assumptions!$H$60*Assumptions!$D$26*Assumptions!$D$27 -> 0.09 | H7: =Assumptions!$I$60*Assumptions!$C$28 -> 0.01 | I7: =Assumptions!$B$60*Assumptions!$D$31*Assumptions!$C$30 -> 0 | J7: =Assumptions!$B$60*Assumptions!$C$33/60*Assumptions!$C$32 -> 0.75 | K7: =(Assumptions!$C$60*Assumptions!$C$34+(Assumptions!$D$60+Assumptions!$E$60)*Assumptions!$C$35+Assumptions!$J$60*Assumptions!$C$36+Assumptions!$K$60)/60*Assumptions!$C$32 -> 1.125 | L7: =Assumptions!$L$60*Assumptions!$C$38/60*Assumptions!$C$37 -> 0.625 | M7: =SUM(B7:L7) -> 3.915 | N7: =B7+C7+D7+E7+K7 -> 2.44 | O7: =Assumptions!$C$39 -> 0.05 | P7: =(M7-N7)+N7/(1-O7) -> 4.0434211 | Q7: =P7*Assumptions!$D$6 -> 3.0527829 | R7: =IF(P7=0,0,(J7+K7/(1-O7)+L7)/P7) -> 0.63293199 | S7: =Assumptions!$B$60*Assumptions!$C$33+(Assumptions!$C$60*Assumptions!$C$34+(Assumptions!$D$60+Assumptions!$E$60)*Assumptions!$C$35+Assumptions!$J$60*Assumptions!$C$36+Assumptions!$K$60)/(1-O7)+Assumptions!$L$60*Assumptions!$C$38 -> 9.2368421
A8: 2-bed flat (8 images + plan) | B8: =Assumptions!$B$61*Assumptions!$C$12+Assumptions!$C$61*Assumptions!$C$13+(Assumptions!$D$61+Assumptions!$E$61)*Assumptions!$C$14 -> 0.186 | C8: =Assumptions!$C$61*Assumptions!$C$16*Assumptions!$C$15 -> 1.808 | D8: =(Assumptions!$D$61*Assumptions!$D$20*Assumptions!$C$17+Assumptions!$E$61*Assumptions!$D$21*Assumptions!$C$18)*Assumptions!$C$19 -> 0 | E8: =Assumptions!$F$61*Assumptions!$C$23*Assumptions!$C$22 -> 0.1475 | F8: =Assumptions!$G$61*Assumptions!$C$24*Assumptions!$C$25 -> 0 | G8: =Assumptions!$H$61*Assumptions!$D$26*Assumptions!$D$27 -> 0.18 | H8: =Assumptions!$I$61*Assumptions!$C$28 -> 0.025 | I8: =Assumptions!$B$61*Assumptions!$D$31*Assumptions!$C$30 -> 0 | J8: =Assumptions!$B$61*Assumptions!$C$33/60*Assumptions!$C$32 -> 0.75 | K8: =(Assumptions!$C$61*Assumptions!$C$34+(Assumptions!$D$61+Assumptions!$E$61)*Assumptions!$C$35+Assumptions!$J$61*Assumptions!$C$36+Assumptions!$K$61)/60*Assumptions!$C$32 -> 2.25 | L8: =Assumptions!$L$61*Assumptions!$C$38/60*Assumptions!$C$37 -> 1.0416667 | M8: =SUM(B8:L8) -> 6.3881667 | N8: =B8+C8+D8+E8+K8 -> 4.3915 | O8: =Assumptions!$C$39 -> 0.05 | P8: =(M8-N8)+N8/(1-O8) -> 6.6192982 | Q8: =P8*Assumptions!$D$6 -> 4.9975702 | R8: =IF(P8=0,0,(J8+K8/(1-O8)+L8)/P8) -> 0.62847866 | S8: =Assumptions!$B$61*Assumptions!$C$33+(Assumptions!$C$61*Assumptions!$C$34+(Assumptions!$D$61+Assumptions!$E$61)*Assumptions!$C$35+Assumptions!$J$61*Assumptions!$C$36+Assumptions!$K$61)/(1-O8)+Assumptions!$L$61*Assumptions!$C$38 -> 14.973684
A9: 4-bed house (19 images, 2 floors) | B9: =Assumptions!$B$62*Assumptions!$C$12+Assumptions!$C$62*Assumptions!$C$13+(Assumptions!$D$62+Assumptions!$E$62)*Assumptions!$C$14 -> 0.432 | C9: =Assumptions!$C$62*Assumptions!$C$16*Assumptions!$C$15 -> 4.294 | D9: =(Assumptions!$D$62*Assumptions!$D$20*Assumptions!$C$17+Assumptions!$E$62*Assumptions!$D$21*Assumptions!$C$18)*Assumptions!$C$19 -> 0 | E9: =Assumptions!$F$62*Assumptions!$C$23*Assumptions!$C$22 -> 0.295 | F9: =Assumptions!$G$62*Assumptions!$C$24*Assumptions!$C$25 -> 0 | G9: =Assumptions!$H$62*Assumptions!$D$26*Assumptions!$D$27 -> 0.36 | H9: =Assumptions!$I$62*Assumptions!$C$28 -> 0.05 | I9: =Assumptions!$B$62*Assumptions!$D$31*Assumptions!$C$30 -> 0 | J9: =Assumptions!$B$62*Assumptions!$C$33/60*Assumptions!$C$32 -> 1.5 | K9: =(Assumptions!$C$62*Assumptions!$C$34+(Assumptions!$D$62+Assumptions!$E$62)*Assumptions!$C$35+Assumptions!$J$62*Assumptions!$C$36+Assumptions!$K$62)/60*Assumptions!$C$32 -> 4.875 | L9: =Assumptions!$L$62*Assumptions!$C$38/60*Assumptions!$C$37 -> 1.6666667 | M9: =SUM(B9:L9) -> 13.472667 | N9: =B9+C9+D9+E9+K9 -> 9.896 | O9: =Assumptions!$C$39 -> 0.05 | P9: =(M9-N9)+N9/(1-O9) -> 13.993509 | Q9: =P9*Assumptions!$D$6 -> 10.565099 | R9: =IF(P9=0,0,(J9+K9/(1-O9)+L9)/P9) -> 0.59300678 | S9: =Assumptions!$B$62*Assumptions!$C$33+(Assumptions!$C$62*Assumptions!$C$34+(Assumptions!$D$62+Assumptions!$E$62)*Assumptions!$C$35+Assumptions!$J$62*Assumptions!$C$36+Assumptions!$K$62)/(1-O9)+Assumptions!$L$62*Assumptions!$C$38 -> 30.526316
A10: Interactive 3D property (WebGL tour, 1st month hosting) | B10: =Assumptions!$B$63*Assumptions!$C$12+Assumptions!$C$63*Assumptions!$C$13+(Assumptions!$D$63+Assumptions!$E$63)*Assumptions!$C$14 -> 0.026 | C10: =Assumptions!$C$63*Assumptions!$C$16*Assumptions!$C$15 -> 0 | D10: =(Assumptions!$D$63*Assumptions!$D$20*Assumptions!$C$17+Assumptions!$E$63*Assumptions!$D$21*Assumptions!$C$18)*Assumptions!$C$19 -> 0 | E10: =Assumptions!$F$63*Assumptions!$C$23*Assumptions!$C$22 -> 0.295 | F10: =Assumptions!$G$63*Assumptions!$C$24*Assumptions!$C$25 -> 0 | G10: =Assumptions!$H$63*Assumptions!$D$26*Assumptions!$D$27 -> 0.36 | H10: =Assumptions!$I$63*Assumptions!$C$28 -> 0.05 | I10: =Assumptions!$B$63*Assumptions!$D$31*Assumptions!$C$30 -> 0 | J10: =Assumptions!$B$63*Assumptions!$C$33/60*Assumptions!$C$32 -> 0.75 | K10: =(Assumptions!$C$63*Assumptions!$C$34+(Assumptions!$D$63+Assumptions!$E$63)*Assumptions!$C$35+Assumptions!$J$63*Assumptions!$C$36+Assumptions!$K$63)/60*Assumptions!$C$32 -> 3.75 | L10: =Assumptions!$L$63*Assumptions!$C$38/60*Assumptions!$C$37 -> 2.0833333 | M10: =SUM(B10:L10) -> 7.3143333 | N10: =B10+C10+D10+E10+K10 -> 4.071 | O10: =Assumptions!$C$39 -> 0.05 | P10: =(M10-N10)+N10/(1-O10) -> 7.5285965 | Q10: =P10*Assumptions!$D$6 -> 5.6840904 | R10: =IF(P10=0,0,(J10+K10/(1-O10)+L10)/P10) -> 0.90065947 | S10: =Assumptions!$B$63*Assumptions!$C$33+(Assumptions!$C$63*Assumptions!$C$34+(Assumptions!$D$63+Assumptions!$E$63)*Assumptions!$C$35+Assumptions!$J$63*Assumptions!$C$36+Assumptions!$K$63)/(1-O10)+Assumptions!$L$63*Assumptions!$C$38 -> 23.789474
A11: 30s walkthrough video | B11: =Assumptions!$B$64*Assumptions!$C$12+Assumptions!$C$64*Assumptions!$C$13+(Assumptions!$D$64+Assumptions!$E$64)*Assumptions!$C$14 -> 0.076 | C11: =Assumptions!$C$64*Assumptions!$C$16*Assumptions!$C$15 -> 0 | D11: =(Assumptions!$D$64*Assumptions!$D$20*Assumptions!$C$17+Assumptions!$E$64*Assumptions!$D$21*Assumptions!$C$18)*Assumptions!$C$19 -> 3.15 | E11: =Assumptions!$F$64*Assumptions!$C$23*Assumptions!$C$22 -> 0.1475 | F11: =Assumptions!$G$64*Assumptions!$C$24*Assumptions!$C$25 -> 0 | G11: =Assumptions!$H$64*Assumptions!$D$26*Assumptions!$D$27 -> 0.09 | H11: =Assumptions!$I$64*Assumptions!$C$28 -> 0.025 | I11: =Assumptions!$B$64*Assumptions!$D$31*Assumptions!$C$30 -> 0 | J11: =Assumptions!$B$64*Assumptions!$C$33/60*Assumptions!$C$32 -> 0.75 | K11: =(Assumptions!$C$64*Assumptions!$C$34+(Assumptions!$D$64+Assumptions!$E$64)*Assumptions!$C$35+Assumptions!$J$64*Assumptions!$C$36+Assumptions!$K$64)/60*Assumptions!$C$32 -> 1.25 | L11: =Assumptions!$L$64*Assumptions!$C$38/60*Assumptions!$C$37 -> 1.0416667 | M11: =SUM(B11:L11) -> 6.5301667 | N11: =B11+C11+D11+E11+K11 -> 4.6235 | O11: =Assumptions!$C$39 -> 0.05 | P11: =(M11-N11)+N11/(1-O11) -> 6.7735088 | Q11: =P11*Assumptions!$D$6 -> 5.1139991 | R11: =IF(P11=0,0,(J11+K11/(1-O11)+L11)/P11) -> 0.45876609 | S11: =Assumptions!$B$64*Assumptions!$C$33+(Assumptions!$C$64*Assumptions!$C$34+(Assumptions!$D$64+Assumptions!$E$64)*Assumptions!$C$35+Assumptions!$J$64*Assumptions!$C$36+Assumptions!$K$64)/(1-O11)+Assumptions!$L$64*Assumptions!$C$38 -> 10.763158
A12: 60s cinematic video | B12: =Assumptions!$B$65*Assumptions!$C$12+Assumptions!$C$65*Assumptions!$C$13+(Assumptions!$D$65+Assumptions!$E$65)*Assumptions!$C$14 -> 0.076 | C12: =Assumptions!$C$65*Assumptions!$C$16*Assumptions!$C$15 -> 0 | D12: =(Assumptions!$D$65*Assumptions!$D$20*Assumptions!$C$17+Assumptions!$E$65*Assumptions!$D$21*Assumptions!$C$18)*Assumptions!$C$19 -> 10.8 | E12: =Assumptions!$F$65*Assumptions!$C$23*Assumptions!$C$22 -> 0.295 | F12: =Assumptions!$G$65*Assumptions!$C$24*Assumptions!$C$25 -> 0 | G12: =Assumptions!$H$65*Assumptions!$D$26*Assumptions!$D$27 -> 0.18 | H12: =Assumptions!$I$65*Assumptions!$C$28 -> 0.05 | I12: =Assumptions!$B$65*Assumptions!$D$31*Assumptions!$C$30 -> 0 | J12: =Assumptions!$B$65*Assumptions!$C$33/60*Assumptions!$C$32 -> 0.75 | K12: =(Assumptions!$C$65*Assumptions!$C$34+(Assumptions!$D$65+Assumptions!$E$65)*Assumptions!$C$35+Assumptions!$J$65*Assumptions!$C$36+Assumptions!$K$65)/60*Assumptions!$C$32 -> 1.25 | L12: =Assumptions!$L$65*Assumptions!$C$38/60*Assumptions!$C$37 -> 1.6666667 | M12: =SUM(B12:L12) -> 15.067667 | N12: =B12+C12+D12+E12+K12 -> 12.421 | O12: =Assumptions!$C$39 -> 0.05 | P12: =(M12-N12)+N12/(1-O12) -> 15.721404 | Q12: =P12*Assumptions!$D$6 -> 11.86966 | R12: =IF(P12=0,0,(J12+K12/(1-O12)+L12)/P12) -> 0.2374124 | S12: =Assumptions!$B$65*Assumptions!$C$33+(Assumptions!$C$65*Assumptions!$C$34+(Assumptions!$D$65+Assumptions!$E$65)*Assumptions!$C$35+Assumptions!$J$65*Assumptions!$C$36+Assumptions!$K$65)/(1-O12)+Assumptions!$L$65*Assumptions!$C$38 -> 12.263158
A13: Developer marketing package (per house type) | B13: =Assumptions!$B$66*Assumptions!$C$12+Assumptions!$C$66*Assumptions!$C$13+(Assumptions!$D$66+Assumptions!$E$66)*Assumptions!$C$14 -> 0.592 | C13: =Assumptions!$C$66*Assumptions!$C$16*Assumptions!$C$15 -> 4.972 | D13: =(Assumptions!$D$66*Assumptions!$D$20*Assumptions!$C$17+Assumptions!$E$66*Assumptions!$D$21*Assumptions!$C$18)*Assumptions!$C$19 -> 13.95 | E13: =Assumptions!$F$66*Assumptions!$C$23*Assumptions!$C$22 -> 0.59 | F13: =Assumptions!$G$66*Assumptions!$C$24*Assumptions!$C$25 -> 0 | G13: =Assumptions!$H$66*Assumptions!$D$26*Assumptions!$D$27 -> 0.54 | H13: =Assumptions!$I$66*Assumptions!$C$28 -> 0.1 | I13: =Assumptions!$B$66*Assumptions!$D$31*Assumptions!$C$30 -> 0 | J13: =Assumptions!$B$66*Assumptions!$C$33/60*Assumptions!$C$32 -> 1.5 | K13: =(Assumptions!$C$66*Assumptions!$C$34+(Assumptions!$D$66+Assumptions!$E$66)*Assumptions!$C$35+Assumptions!$J$66*Assumptions!$C$36+Assumptions!$K$66)/60*Assumptions!$C$32 -> 12.75 | L13: =Assumptions!$L$66*Assumptions!$C$38/60*Assumptions!$C$37 -> 6.25 | M13: =SUM(B13:L13) -> 41.244 | N13: =B13+C13+D13+E13+K13 -> 32.854 | O13: =Assumptions!$C$39 -> 0.05 | P13: =(M13-N13)+N13/(1-O13) -> 42.973158 | Q13: =P13*Assumptions!$D$6 -> 32.444734 | R13: =IF(P13=0,0,(J13+K13/(1-O13)+L13)/P13) -> 0.4926576 | S13: =Assumptions!$B$66*Assumptions!$C$33+(Assumptions!$C$66*Assumptions!$C$34+(Assumptions!$D$66+Assumptions!$E$66)*Assumptions!$C$35+Assumptions!$J$66*Assumptions!$C$36+Assumptions!$K$66)/(1-O13)+Assumptions!$L$66*Assumptions!$C$38 -> 74.684211
A14: 50-unit development (6 plan types) | B14: =Assumptions!$B$67*Assumptions!$C$12+Assumptions!$C$67*Assumptions!$C$13+(Assumptions!$D$67+Assumptions!$E$67)*Assumptions!$C$14 -> 6.552 | C14: =Assumptions!$C$67*Assumptions!$C$16*Assumptions!$C$15 -> 63.732 | D14: =(Assumptions!$D$67*Assumptions!$D$20*Assumptions!$C$17+Assumptions!$E$67*Assumptions!$D$21*Assumptions!$C$18)*Assumptions!$C$19 -> 83.7 | E14: =Assumptions!$F$67*Assumptions!$C$23*Assumptions!$C$22 -> 4.13 | F14: =Assumptions!$G$67*Assumptions!$C$24*Assumptions!$C$25 -> 0 | G14: =Assumptions!$H$67*Assumptions!$D$26*Assumptions!$D$27 -> 4.14 | H14: =Assumptions!$I$67*Assumptions!$C$28 -> 0.85 | I14: =Assumptions!$B$67*Assumptions!$D$31*Assumptions!$C$30 -> 0 | J14: =Assumptions!$B$67*Assumptions!$C$33/60*Assumptions!$C$32 -> 9 | K14: =(Assumptions!$C$67*Assumptions!$C$34+(Assumptions!$D$67+Assumptions!$E$67)*Assumptions!$C$35+Assumptions!$J$67*Assumptions!$C$36+Assumptions!$K$67)/60*Assumptions!$C$32 -> 122.75 | L14: =Assumptions!$L$67*Assumptions!$C$38/60*Assumptions!$C$37 -> 25 | M14: =SUM(B14:L14) -> 319.854 | N14: =B14+C14+D14+E14+K14 -> 280.864 | O14: =Assumptions!$C$39 -> 0.05 | P14: =(M14-N14)+N14/(1-O14) -> 334.63632 | Q14: =P14*Assumptions!$D$6 -> 252.65042 | R14: =IF(P14=0,0,(J14+K14/(1-O14)+L14)/P14) -> 0.48772509 | S14: =Assumptions!$B$67*Assumptions!$C$33+(Assumptions!$C$67*Assumptions!$C$34+(Assumptions!$D$67+Assumptions!$E$67)*Assumptions!$C$35+Assumptions!$J$67*Assumptions!$C$36+Assumptions!$K$67)/(1-O14)+Assumptions!$L$67*Assumptions!$C$38 -> 612.84211
A15: 200-unit development (15 plan types) | B15: =Assumptions!$B$68*Assumptions!$C$12+Assumptions!$C$68*Assumptions!$C$13+(Assumptions!$D$68+Assumptions!$E$68)*Assumptions!$C$14 -> 20.88 | C15: =Assumptions!$C$68*Assumptions!$C$16*Assumptions!$C$15 -> 210.18 | D15: =(Assumptions!$D$68*Assumptions!$D$20*Assumptions!$C$17+Assumptions!$E$68*Assumptions!$D$21*Assumptions!$C$18)*Assumptions!$C$19 -> 209.25 | E15: =Assumptions!$F$68*Assumptions!$C$23*Assumptions!$C$22 -> 9.44 | F15: =Assumptions!$G$68*Assumptions!$C$24*Assumptions!$C$25 -> 0 | G15: =Assumptions!$H$68*Assumptions!$D$26*Assumptions!$D$27 -> 11.7 | H15: =Assumptions!$I$68*Assumptions!$C$28 -> 2.5 | I15: =Assumptions!$B$68*Assumptions!$D$31*Assumptions!$C$30 -> 0 | J15: =Assumptions!$B$68*Assumptions!$C$33/60*Assumptions!$C$32 -> 22.5 | K15: =(Assumptions!$C$68*Assumptions!$C$34+(Assumptions!$D$68+Assumptions!$E$68)*Assumptions!$C$35+Assumptions!$J$68*Assumptions!$C$36+Assumptions!$K$68)/60*Assumptions!$C$32 -> 331.25 | L15: =Assumptions!$L$68*Assumptions!$C$38/60*Assumptions!$C$37 -> 50 | M15: =SUM(B15:L15) -> 867.7 | N15: =B15+C15+D15+E15+K15 -> 781 | O15: =Assumptions!$C$39 -> 0.05 | P15: =(M15-N15)+N15/(1-O15) -> 908.80526 | Q15: =P15*Assumptions!$D$6 -> 686.14797 | R15: =IF(P15=0,0,(J15+K15/(1-O15)+L15)/P15) -> 0.46344825 | S15: =Assumptions!$B$68*Assumptions!$C$33+(Assumptions!$C$68*Assumptions!$C$34+(Assumptions!$D$68+Assumptions!$E$68)*Assumptions!$C$35+Assumptions!$J$68*Assumptions!$C$36+Assumptions!$K$68)/(1-O15)+Assumptions!$L$68*Assumptions!$C$38 -> 1604.7368
A16: Ongoing hosting per interactive property per month (streaming + CDN + storage) | M16: =Assumptions!$C$24*Assumptions!$C$25+Assumptions!$D$29*Assumptions!$C$28+Assumptions!$D$44*Assumptions!$D$26 -> 0.08 | Q16: =M16*Assumptions!$D$6 -> 0.0604
A18: BASE cost case
A19: Deliverable | B19: LLM tokens | C19: Image gen | D19: Video gen | E19: GPU render | F19: 3D streaming (1st mo) | G19: Storage | H19: CDN | I19: 3rd-party fees (CAD) | J19: Human 2D confirm | K19: Human output QA | L19: Support alloc. | M19: Attempt cost (USD) | N19: of which repeatable | O19: Failure rate | P19: Cost / success (USD) | Q19: Cost / success (GBP) | R19: Human labour share | S19: Human minutes / success
A20: Single room image | B20: =Assumptions!$B$59*Assumptions!$D$12+Assumptions!$C$59*Assumptions!$D$13+(Assumptions!$D$59+Assumptions!$E$59)*Assumptions!$D$14 -> 0.082 | C20: =Assumptions!$C$59*Assumptions!$D$16*Assumptions!$D$15 -> 0.72 | D20: =(Assumptions!$D$59*Assumptions!$D$20*Assumptions!$D$17+Assumptions!$E$59*Assumptions!$D$21*Assumptions!$D$18)*Assumptions!$D$19 -> 0 | E20: =Assumptions!$F$59*Assumptions!$D$23*Assumptions!$D$22 -> 0.0545 | F20: =Assumptions!$G$59*Assumptions!$D$24*Assumptions!$D$25 -> 0 | G20: =Assumptions!$H$59*Assumptions!$D$26*Assumptions!$D$27 -> 0.018 | H20: =Assumptions!$I$59*Assumptions!$D$28 -> 0.005 | I20: =Assumptions!$B$59*Assumptions!$D$31*Assumptions!$D$30 -> 0.45 | J20: =Assumptions!$B$59*Assumptions!$D$33/60*Assumptions!$D$32 -> 4.1666667 | K20: =(Assumptions!$C$59*Assumptions!$D$34+(Assumptions!$D$59+Assumptions!$E$59)*Assumptions!$D$35+Assumptions!$J$59*Assumptions!$D$36+Assumptions!$K$59)/60*Assumptions!$D$32 -> 0.41666667 | L20: =Assumptions!$L$59*Assumptions!$D$38/60*Assumptions!$D$37 -> 1 | M20: =SUM(B20:L20) -> 6.9128333 | N20: =B20+C20+D20+E20+K20 -> 1.2731667 | O20: =Assumptions!$D$39 -> 0.15 | P20: =(M20-N20)+N20/(1-O20) -> 7.1375098 | Q20: =P20*Assumptions!$D$6 -> 5.3888199 | R20: =IF(P20=0,0,(J20+K20/(1-O20)+L20)/P20) -> 0.79255411 | S20: =Assumptions!$B$59*Assumptions!$D$33+(Assumptions!$C$59*Assumptions!$D$34+(Assumptions!$D$59+Assumptions!$E$59)*Assumptions!$D$35+Assumptions!$J$59*Assumptions!$D$36+Assumptions!$K$59)/(1-O20)+Assumptions!$L$59*Assumptions!$D$38 -> 13.176471
A21: 5 room images | B21: =Assumptions!$B$60*Assumptions!$D$12+Assumptions!$C$60*Assumptions!$D$13+(Assumptions!$D$60+Assumptions!$E$60)*Assumptions!$D$14 -> 0.202 | C21: =Assumptions!$C$60*Assumptions!$D$16*Assumptions!$D$15 -> 3.6 | D21: =(Assumptions!$D$60*Assumptions!$D$20*Assumptions!$D$17+Assumptions!$E$60*Assumptions!$D$21*Assumptions!$D$18)*Assumptions!$D$19 -> 0 | E21: =Assumptions!$F$60*Assumptions!$D$23*Assumptions!$D$22 -> 0.218 | F21: =Assumptions!$G$60*Assumptions!$D$24*Assumptions!$D$25 -> 0 | G21: =Assumptions!$H$60*Assumptions!$D$26*Assumptions!$D$27 -> 0.09 | H21: =Assumptions!$I$60*Assumptions!$D$28 -> 0.02 | I21: =Assumptions!$B$60*Assumptions!$D$31*Assumptions!$D$30 -> 0.45 | J21: =Assumptions!$B$60*Assumptions!$D$33/60*Assumptions!$D$32 -> 4.1666667 | K21: =(Assumptions!$C$60*Assumptions!$D$34+(Assumptions!$D$60+Assumptions!$E$60)*Assumptions!$D$35+Assumptions!$J$60*Assumptions!$D$36+Assumptions!$K$60)/60*Assumptions!$D$32 -> 2.9166667 | L21: =Assumptions!$L$60*Assumptions!$D$38/60*Assumptions!$D$37 -> 1.5 | M21: =SUM(B21:L21) -> 13.163333 | N21: =B21+C21+D21+E21+K21 -> 6.9366667 | O21: =Assumptions!$D$39 -> 0.15 | P21: =(M21-N21)+N21/(1-O21) -> 14.387451 | Q21: =P21*Assumptions!$D$6 -> 10.862525 | R21: =IF(P21=0,0,(J21+K21/(1-O21)+L21)/P21) -> 0.63235935 | S21: =Assumptions!$B$60*Assumptions!$D$33+(Assumptions!$C$60*Assumptions!$D$34+(Assumptions!$D$60+Assumptions!$E$60)*Assumptions!$D$35+Assumptions!$J$60*Assumptions!$D$36+Assumptions!$K$60)/(1-O21)+Assumptions!$L$60*Assumptions!$D$38 -> 21.235294
A22: 2-bed flat (8 images + plan) | B22: =Assumptions!$B$61*Assumptions!$D$12+Assumptions!$C$61*Assumptions!$D$13+(Assumptions!$D$61+Assumptions!$E$61)*Assumptions!$D$14 -> 0.292 | C22: =Assumptions!$C$61*Assumptions!$D$16*Assumptions!$D$15 -> 5.76 | D22: =(Assumptions!$D$61*Assumptions!$D$20*Assumptions!$D$17+Assumptions!$E$61*Assumptions!$D$21*Assumptions!$D$18)*Assumptions!$D$19 -> 0 | E22: =Assumptions!$F$61*Assumptions!$D$23*Assumptions!$D$22 -> 0.545 | F22: =Assumptions!$G$61*Assumptions!$D$24*Assumptions!$D$25 -> 0 | G22: =Assumptions!$H$61*Assumptions!$D$26*Assumptions!$D$27 -> 0.18 | H22: =Assumptions!$I$61*Assumptions!$D$28 -> 0.05 | I22: =Assumptions!$B$61*Assumptions!$D$31*Assumptions!$D$30 -> 0.45 | J22: =Assumptions!$B$61*Assumptions!$D$33/60*Assumptions!$D$32 -> 4.1666667 | K22: =(Assumptions!$C$61*Assumptions!$D$34+(Assumptions!$D$61+Assumptions!$E$61)*Assumptions!$D$35+Assumptions!$J$61*Assumptions!$D$36+Assumptions!$K$61)/60*Assumptions!$D$32 -> 5.4166667 | L22: =Assumptions!$L$61*Assumptions!$D$38/60*Assumptions!$D$37 -> 2.5 | M22: =SUM(B22:L22) -> 19.360333 | N22: =B22+C22+D22+E22+K22 -> 12.013667 | O22: =Assumptions!$D$39 -> 0.15 | P22: =(M22-N22)+N22/(1-O22) -> 21.480392 | Q22: =P22*Assumptions!$D$6 -> 16.217696 | R22: =IF(P22=0,0,(J22+K22/(1-O22)+L22)/P22) -> 0.60702875 | S22: =Assumptions!$B$61*Assumptions!$D$33+(Assumptions!$C$61*Assumptions!$D$34+(Assumptions!$D$61+Assumptions!$E$61)*Assumptions!$D$35+Assumptions!$J$61*Assumptions!$D$36+Assumptions!$K$61)/(1-O22)+Assumptions!$L$61*Assumptions!$D$38 -> 30.294118
A23: 4-bed house (19 images, 2 floors) | B23: =Assumptions!$B$62*Assumptions!$D$12+Assumptions!$C$62*Assumptions!$D$13+(Assumptions!$D$62+Assumptions!$E$62)*Assumptions!$D$14 -> 0.674 | C23: =Assumptions!$C$62*Assumptions!$D$16*Assumptions!$D$15 -> 13.68 | D23: =(Assumptions!$D$62*Assumptions!$D$20*Assumptions!$D$17+Assumptions!$E$62*Assumptions!$D$21*Assumptions!$D$18)*Assumptions!$D$19 -> 0 | E23: =Assumptions!$F$62*Assumptions!$D$23*Assumptions!$D$22 -> 1.09 | F23: =Assumptions!$G$62*Assumptions!$D$24*Assumptions!$D$25 -> 0 | G23: =Assumptions!$H$62*Assumptions!$D$26*Assumptions!$D$27 -> 0.36 | H23: =Assumptions!$I$62*Assumptions!$D$28 -> 0.1 | I23: =Assumptions!$B$62*Assumptions!$D$31*Assumptions!$D$30 -> 0.9 | J23: =Assumptions!$B$62*Assumptions!$D$33/60*Assumptions!$D$32 -> 8.3333333 | K23: =(Assumptions!$C$62*Assumptions!$D$34+(Assumptions!$D$62+Assumptions!$E$62)*Assumptions!$D$35+Assumptions!$J$62*Assumptions!$D$36+Assumptions!$K$62)/60*Assumptions!$D$32 -> 12.083333 | L23: =Assumptions!$L$62*Assumptions!$D$38/60*Assumptions!$D$37 -> 4 | M23: =SUM(B23:L23) -> 41.220667 | N23: =B23+C23+D23+E23+K23 -> 27.527333 | O23: =Assumptions!$D$39 -> 0.15 | P23: =(M23-N23)+N23/(1-O23) -> 46.078431 | Q23: =P23*Assumptions!$D$6 -> 34.789216 | R23: =IF(P23=0,0,(J23+K23/(1-O23)+L23)/P23) -> 0.57617021 | S23: =Assumptions!$B$62*Assumptions!$D$33+(Assumptions!$C$62*Assumptions!$D$34+(Assumptions!$D$62+Assumptions!$E$62)*Assumptions!$D$35+Assumptions!$J$62*Assumptions!$D$36+Assumptions!$K$62)/(1-O23)+Assumptions!$L$62*Assumptions!$D$38 -> 62.117647
A24: Interactive 3D property (WebGL tour, 1st month hosting) | B24: =Assumptions!$B$63*Assumptions!$D$12+Assumptions!$C$63*Assumptions!$D$13+(Assumptions!$D$63+Assumptions!$E$63)*Assumptions!$D$14 -> 0.052 | C24: =Assumptions!$C$63*Assumptions!$D$16*Assumptions!$D$15 -> 0 | D24: =(Assumptions!$D$63*Assumptions!$D$20*Assumptions!$D$17+Assumptions!$E$63*Assumptions!$D$21*Assumptions!$D$18)*Assumptions!$D$19 -> 0 | E24: =Assumptions!$F$63*Assumptions!$D$23*Assumptions!$D$22 -> 1.09 | F24: =Assumptions!$G$63*Assumptions!$D$24*Assumptions!$D$25 -> 3.64 | G24: =Assumptions!$H$63*Assumptions!$D$26*Assumptions!$D$27 -> 0.36 | H24: =Assumptions!$I$63*Assumptions!$D$28 -> 0.1 | I24: =Assumptions!$B$63*Assumptions!$D$31*Assumptions!$D$30 -> 0.45 | J24: =Assumptions!$B$63*Assumptions!$D$33/60*Assumptions!$D$32 -> 4.1666667 | K24: =(Assumptions!$C$63*Assumptions!$D$34+(Assumptions!$D$63+Assumptions!$E$63)*Assumptions!$D$35+Assumptions!$J$63*Assumptions!$D$36+Assumptions!$K$63)/60*Assumptions!$D$32 -> 6.25 | L24: =Assumptions!$L$63*Assumptions!$D$38/60*Assumptions!$D$37 -> 5 | M24: =SUM(B24:L24) -> 21.108667 | N24: =B24+C24+D24+E24+K24 -> 7.392 | O24: =Assumptions!$D$39 -> 0.15 | P24: =(M24-N24)+N24/(1-O24) -> 22.413137 | Q24: =P24*Assumptions!$D$6 -> 16.921919 | R24: =IF(P24=0,0,(J24+K24/(1-O24)+L24)/P24) -> 0.73705022 | S24: =Assumptions!$B$63*Assumptions!$D$33+(Assumptions!$C$63*Assumptions!$D$34+(Assumptions!$D$63+Assumptions!$E$63)*Assumptions!$D$35+Assumptions!$J$63*Assumptions!$D$36+Assumptions!$K$63)/(1-O24)+Assumptions!$L$63*Assumptions!$D$38 -> 37.647059
A25: 30s walkthrough video | B25: =Assumptions!$B$64*Assumptions!$D$12+Assumptions!$C$64*Assumptions!$D$13+(Assumptions!$D$64+Assumptions!$E$64)*Assumptions!$D$14 -> 0.152 | C25: =Assumptions!$C$64*Assumptions!$D$16*Assumptions!$D$15 -> 0 | D25: =(Assumptions!$D$64*Assumptions!$D$20*Assumptions!$D$17+Assumptions!$E$64*Assumptions!$D$21*Assumptions!$D$18)*Assumptions!$D$19 -> 7.2 | E25: =Assumptions!$F$64*Assumptions!$D$23*Assumptions!$D$22 -> 0.545 | F25: =Assumptions!$G$64*Assumptions!$D$24*Assumptions!$D$25 -> 0 | G25: =Assumptions!$H$64*Assumptions!$D$26*Assumptions!$D$27 -> 0.09 | H25: =Assumptions!$I$64*Assumptions!$D$28 -> 0.05 | I25: =Assumptions!$B$64*Assumptions!$D$31*Assumptions!$D$30 -> 0.45 | J25: =Assumptions!$B$64*Assumptions!$D$33/60*Assumptions!$D$32 -> 4.1666667 | K25: =(Assumptions!$C$64*Assumptions!$D$34+(Assumptions!$D$64+Assumptions!$E$64)*Assumptions!$D$35+Assumptions!$J$64*Assumptions!$D$36+Assumptions!$K$64)/60*Assumptions!$D$32 -> 4.1666667 | L25: =Assumptions!$L$64*Assumptions!$D$38/60*Assumptions!$D$37 -> 2.5 | M25: =SUM(B25:L25) -> 19.320333 | N25: =B25+C25+D25+E25+K25 -> 12.063667 | O25: =Assumptions!$D$39 -> 0.15 | P25: =(M25-N25)+N25/(1-O25) -> 21.449216 | Q25: =P25*Assumptions!$D$6 -> 16.194158 | R25: =IF(P25=0,0,(J25+K25/(1-O25)+L25)/P25) -> 0.53934967 | S25: =Assumptions!$B$64*Assumptions!$D$33+(Assumptions!$C$64*Assumptions!$D$34+(Assumptions!$D$64+Assumptions!$E$64)*Assumptions!$D$35+Assumptions!$J$64*Assumptions!$D$36+Assumptions!$K$64)/(1-O25)+Assumptions!$L$64*Assumptions!$D$38 -> 26.764706
A26: 60s cinematic video | B26: =Assumptions!$B$65*Assumptions!$D$12+Assumptions!$C$65*Assumptions!$D$13+(Assumptions!$D$65+Assumptions!$E$65)*Assumptions!$D$14 -> 0.152 | C26: =Assumptions!$C$65*Assumptions!$D$16*Assumptions!$D$15 -> 0 | D26: =(Assumptions!$D$65*Assumptions!$D$20*Assumptions!$D$17+Assumptions!$E$65*Assumptions!$D$21*Assumptions!$D$18)*Assumptions!$D$19 -> 48 | E26: =Assumptions!$F$65*Assumptions!$D$23*Assumptions!$D$22 -> 1.09 | F26: =Assumptions!$G$65*Assumptions!$D$24*Assumptions!$D$25 -> 0 | G26: =Assumptions!$H$65*Assumptions!$D$26*Assumptions!$D$27 -> 0.18 | H26: =Assumptions!$I$65*Assumptions!$D$28 -> 0.1 | I26: =Assumptions!$B$65*Assumptions!$D$31*Assumptions!$D$30 -> 0.45 | J26: =Assumptions!$B$65*Assumptions!$D$33/60*Assumptions!$D$32 -> 4.1666667 | K26: =(Assumptions!$C$65*Assumptions!$D$34+(Assumptions!$D$65+Assumptions!$E$65)*Assumptions!$D$35+Assumptions!$J$65*Assumptions!$D$36+Assumptions!$K$65)/60*Assumptions!$D$32 -> 4.1666667 | L26: =Assumptions!$L$65*Assumptions!$D$38/60*Assumptions!$D$37 -> 4 | M26: =SUM(B26:L26) -> 62.305333 | N26: =B26+C26+D26+E26+K26 -> 53.408667 | O26: =Assumptions!$D$39 -> 0.15 | P26: =(M26-N26)+N26/(1-O26) -> 71.730392 | Q26: =P26*Assumptions!$D$6 -> 54.156446 | R26: =IF(P26=0,0,(J26+K26/(1-O26)+L26)/P26) -> 0.18219094 | S26: =Assumptions!$B$65*Assumptions!$D$33+(Assumptions!$C$65*Assumptions!$D$34+(Assumptions!$D$65+Assumptions!$E$65)*Assumptions!$D$35+Assumptions!$J$65*Assumptions!$D$36+Assumptions!$K$65)/(1-O26)+Assumptions!$L$65*Assumptions!$D$38 -> 29.764706
A27: Developer marketing package (per house type) | B27: =Assumptions!$B$66*Assumptions!$D$12+Assumptions!$C$66*Assumptions!$D$13+(Assumptions!$D$66+Assumptions!$E$66)*Assumptions!$D$14 -> 0.964 | C27: =Assumptions!$C$66*Assumptions!$D$16*Assumptions!$D$15 -> 15.84 | D27: =(Assumptions!$D$66*Assumptions!$D$20*Assumptions!$D$17+Assumptions!$E$66*Assumptions!$D$21*Assumptions!$D$18)*Assumptions!$D$19 -> 55.2 | E27: =Assumptions!$F$66*Assumptions!$D$23*Assumptions!$D$22 -> 2.18 | F27: =Assumptions!$G$66*Assumptions!$D$24*Assumptions!$D$25 -> 3.64 | G27: =Assumptions!$H$66*Assumptions!$D$26*Assumptions!$D$27 -> 0.54 | H27: =Assumptions!$I$66*Assumptions!$D$28 -> 0.2 | I27: =Assumptions!$B$66*Assumptions!$D$31*Assumptions!$D$30 -> 0.9 | J27: =Assumptions!$B$66*Assumptions!$D$33/60*Assumptions!$D$32 -> 8.3333333 | K27: =(Assumptions!$C$66*Assumptions!$D$34+(Assumptions!$D$66+Assumptions!$E$66)*Assumptions!$D$35+Assumptions!$J$66*Assumptions!$D$36+Assumptions!$K$66)/60*Assumptions!$D$32 -> 30 | L27: =Assumptions!$L$66*Assumptions!$D$38/60*Assumptions!$D$37 -> 15 | M27: =SUM(B27:L27) -> 132.79733 | N27: =B27+C27+D27+E27+K27 -> 104.184 | O27: =Assumptions!$D$39 -> 0.15 | P27: =(M27-N27)+N27/(1-O27) -> 151.18275 | Q27: =P27*Assumptions!$D$6 -> 114.14297 | R27: =IF(P27=0,0,(J27+K27/(1-O27)+L27)/P27) -> 0.38779195 | S27: =Assumptions!$B$66*Assumptions!$D$33+(Assumptions!$C$66*Assumptions!$D$34+(Assumptions!$D$66+Assumptions!$E$66)*Assumptions!$D$35+Assumptions!$J$66*Assumptions!$D$36+Assumptions!$K$66)/(1-O27)+Assumptions!$L$66*Assumptions!$D$38 -> 134.70588
A28: 50-unit development (6 plan types) | B28: =Assumptions!$B$67*Assumptions!$D$12+Assumptions!$C$67*Assumptions!$D$13+(Assumptions!$D$67+Assumptions!$E$67)*Assumptions!$D$14 -> 10.284 | C28: =Assumptions!$C$67*Assumptions!$D$16*Assumptions!$D$15 -> 203.04 | D28: =(Assumptions!$D$67*Assumptions!$D$20*Assumptions!$D$17+Assumptions!$E$67*Assumptions!$D$21*Assumptions!$D$18)*Assumptions!$D$19 -> 331.2 | E28: =Assumptions!$F$67*Assumptions!$D$23*Assumptions!$D$22 -> 15.26 | F28: =Assumptions!$G$67*Assumptions!$D$24*Assumptions!$D$25 -> 21.84 | G28: =Assumptions!$H$67*Assumptions!$D$26*Assumptions!$D$27 -> 4.14 | H28: =Assumptions!$I$67*Assumptions!$D$28 -> 1.7 | I28: =Assumptions!$B$67*Assumptions!$D$31*Assumptions!$D$30 -> 5.4 | J28: =Assumptions!$B$67*Assumptions!$D$33/60*Assumptions!$D$32 -> 50 | K28: =(Assumptions!$C$67*Assumptions!$D$34+(Assumptions!$D$67+Assumptions!$E$67)*Assumptions!$D$35+Assumptions!$J$67*Assumptions!$D$36+Assumptions!$K$67)/60*Assumptions!$D$32 -> 298.75 | L28: =Assumptions!$L$67*Assumptions!$D$38/60*Assumptions!$D$37 -> 60 | M28: =SUM(B28:L28) -> 1001.614 | N28: =B28+C28+D28+E28+K28 -> 858.534 | O28: =Assumptions!$D$39 -> 0.15 | P28: =(M28-N28)+N28/(1-O28) -> 1153.12 | Q28: =P28*Assumptions!$D$6 -> 870.6056 | R28: =IF(P28=0,0,(J28+K28/(1-O28)+L28)/P28) -> 0.40019303 | S28: =Assumptions!$B$67*Assumptions!$D$33+(Assumptions!$C$67*Assumptions!$D$34+(Assumptions!$D$67+Assumptions!$E$67)*Assumptions!$D$35+Assumptions!$J$67*Assumptions!$D$36+Assumptions!$K$67)/(1-O28)+Assumptions!$L$67*Assumptions!$D$38 -> 1083.5294
A29: 200-unit development (15 plan types) | B29: =Assumptions!$B$68*Assumptions!$D$12+Assumptions!$C$68*Assumptions!$D$13+(Assumptions!$D$68+Assumptions!$E$68)*Assumptions!$D$14 -> 32.46 | C29: =Assumptions!$C$68*Assumptions!$D$16*Assumptions!$D$15 -> 669.6 | D29: =(Assumptions!$D$68*Assumptions!$D$20*Assumptions!$D$17+Assumptions!$E$68*Assumptions!$D$21*Assumptions!$D$18)*Assumptions!$D$19 -> 828 | E29: =Assumptions!$F$68*Assumptions!$D$23*Assumptions!$D$22 -> 34.88 | F29: =Assumptions!$G$68*Assumptions!$D$24*Assumptions!$D$25 -> 54.6 | G29: =Assumptions!$H$68*Assumptions!$D$26*Assumptions!$D$27 -> 11.7 | H29: =Assumptions!$I$68*Assumptions!$D$28 -> 5 | I29: =Assumptions!$B$68*Assumptions!$D$31*Assumptions!$D$30 -> 13.5 | J29: =Assumptions!$B$68*Assumptions!$D$33/60*Assumptions!$D$32 -> 125 | K29: =(Assumptions!$C$68*Assumptions!$D$34+(Assumptions!$D$68+Assumptions!$E$68)*Assumptions!$D$35+Assumptions!$J$68*Assumptions!$D$36+Assumptions!$K$68)/60*Assumptions!$D$32 -> 850 | L29: =Assumptions!$L$68*Assumptions!$D$38/60*Assumptions!$D$37 -> 120 | M29: =SUM(B29:L29) -> 2744.74 | N29: =B29+C29+D29+E29+K29 -> 2414.94 | O29: =Assumptions!$D$39 -> 0.15 | P29: =(M29-N29)+N29/(1-O29) -> 3170.9059 | Q29: =P29*Assumptions!$D$6 -> 2394.0339 | R29: =IF(P29=0,0,(J29+K29/(1-O29)+L29)/P29) -> 0.39263228 | S29: =Assumptions!$B$68*Assumptions!$D$33+(Assumptions!$C$68*Assumptions!$D$34+(Assumptions!$D$68+Assumptions!$E$68)*Assumptions!$D$35+Assumptions!$J$68*Assumptions!$D$36+Assumptions!$K$68)/(1-O29)+Assumptions!$L$68*Assumptions!$D$38 -> 2940
A30: Ongoing hosting per interactive property per month (streaming + CDN + storage) | M30: =Assumptions!$D$24*Assumptions!$D$25+Assumptions!$D$29*Assumptions!$D$28+Assumptions!$D$44*Assumptions!$D$26 -> 3.77 | Q30: =M30*Assumptions!$D$6 -> 2.84635
A32: HIGH cost case
A33: Deliverable | B33: LLM tokens | C33: Image gen | D33: Video gen | E33: GPU render | F33: 3D streaming (1st mo) | G33: Storage | H33: CDN | I33: 3rd-party fees (CAD) | J33: Human 2D confirm | K33: Human output QA | L33: Support alloc. | M33: Attempt cost (USD) | N33: of which repeatable | O33: Failure rate | P33: Cost / success (USD) | Q33: Cost / success (GBP) | R33: Human labour share | S33: Human minutes / success
A34: Single room image | B34: =Assumptions!$B$59*Assumptions!$E$12+Assumptions!$C$59*Assumptions!$E$13+(Assumptions!$D$59+Assumptions!$E$59)*Assumptions!$E$14 -> 0.15 | C34: =Assumptions!$C$59*Assumptions!$E$16*Assumptions!$E$15 -> 0.96 | D34: =(Assumptions!$D$59*Assumptions!$D$20*Assumptions!$E$17+Assumptions!$E$59*Assumptions!$D$21*Assumptions!$E$18)*Assumptions!$E$19 -> 0 | E34: =Assumptions!$F$59*Assumptions!$E$23*Assumptions!$E$22 -> 0.186 | F34: =Assumptions!$G$59*Assumptions!$E$24*Assumptions!$E$25 -> 0 | G34: =Assumptions!$H$59*Assumptions!$D$26*Assumptions!$D$27 -> 0.018 | H34: =Assumptions!$I$59*Assumptions!$E$28 -> 0.005 | I34: =Assumptions!$B$59*Assumptions!$D$31*Assumptions!$E$30 -> 0.9 | J34: =Assumptions!$B$59*Assumptions!$E$33/60*Assumptions!$E$32 -> 8.75 | K34: =(Assumptions!$C$59*Assumptions!$E$34+(Assumptions!$D$59+Assumptions!$E$59)*Assumptions!$E$35+Assumptions!$J$59*Assumptions!$E$36+Assumptions!$K$59)/60*Assumptions!$E$32 -> 0.875 | L34: =Assumptions!$L$59*Assumptions!$E$38/60*Assumptions!$E$37 -> 1.75 | M34: =SUM(B34:L34) -> 13.594 | N34: =B34+C34+D34+E34+K34 -> 2.171 | O34: =Assumptions!$E$39 -> 0.25 | P34: =(M34-N34)+N34/(1-O34) -> 14.317667 | Q34: =P34*Assumptions!$D$6 -> 10.809838 | R34: =IF(P34=0,0,(J34+K34/(1-O34)+L34)/P34) -> 0.81484413 | S34: =Assumptions!$B$59*Assumptions!$E$33+(Assumptions!$C$59*Assumptions!$E$34+(Assumptions!$D$59+Assumptions!$E$59)*Assumptions!$E$35+Assumptions!$J$59*Assumptions!$E$36+Assumptions!$K$59)/(1-O34)+Assumptions!$L$59*Assumptions!$E$38 -> 20
A35: 5 room images | B35: =Assumptions!$B$60*Assumptions!$E$12+Assumptions!$C$60*Assumptions!$E$13+(Assumptions!$D$60+Assumptions!$E$60)*Assumptions!$E$14 -> 0.35 | C35: =Assumptions!$C$60*Assumptions!$E$16*Assumptions!$E$15 -> 4.8 | D35: =(Assumptions!$D$60*Assumptions!$D$20*Assumptions!$E$17+Assumptions!$E$60*Assumptions!$D$21*Assumptions!$E$18)*Assumptions!$E$19 -> 0 | E35: =Assumptions!$F$60*Assumptions!$E$23*Assumptions!$E$22 -> 0.744 | F35: =Assumptions!$G$60*Assumptions!$E$24*Assumptions!$E$25 -> 0 | G35: =Assumptions!$H$60*Assumptions!$D$26*Assumptions!$D$27 -> 0.09 | H35: =Assumptions!$I$60*Assumptions!$E$28 -> 0.02 | I35: =Assumptions!$B$60*Assumptions!$D$31*Assumptions!$E$30 -> 0.9 | J35: =Assumptions!$B$60*Assumptions!$E$33/60*Assumptions!$E$32 -> 8.75 | K35: =(Assumptions!$C$60*Assumptions!$E$34+(Assumptions!$D$60+Assumptions!$E$60)*Assumptions!$E$35+Assumptions!$J$60*Assumptions!$E$36+Assumptions!$K$60)/60*Assumptions!$E$32 -> 5.5416667 | L35: =Assumptions!$L$60*Assumptions!$E$38/60*Assumptions!$E$37 -> 2.625 | M35: =SUM(B35:L35) -> 23.820667 | N35: =B35+C35+D35+E35+K35 -> 11.435667 | O35: =Assumptions!$E$39 -> 0.25 | P35: =(M35-N35)+N35/(1-O35) -> 27.632556 | Q35: =P35*Assumptions!$D$6 -> 20.862579 | R35: =IF(P35=0,0,(J35+K35/(1-O35)+L35)/P35) -> 0.67905007 | S35: =Assumptions!$B$60*Assumptions!$E$33+(Assumptions!$C$60*Assumptions!$E$34+(Assumptions!$D$60+Assumptions!$E$60)*Assumptions!$E$35+Assumptions!$J$60*Assumptions!$E$36+Assumptions!$K$60)/(1-O35)+Assumptions!$L$60*Assumptions!$E$38 -> 32.166667
A36: 2-bed flat (8 images + plan) | B36: =Assumptions!$B$61*Assumptions!$E$12+Assumptions!$C$61*Assumptions!$E$13+(Assumptions!$D$61+Assumptions!$E$61)*Assumptions!$E$14 -> 0.5 | C36: =Assumptions!$C$61*Assumptions!$E$16*Assumptions!$E$15 -> 7.68 | D36: =(Assumptions!$D$61*Assumptions!$D$20*Assumptions!$E$17+Assumptions!$E$61*Assumptions!$D$21*Assumptions!$E$18)*Assumptions!$E$19 -> 0 | E36: =Assumptions!$F$61*Assumptions!$E$23*Assumptions!$E$22 -> 1.86 | F36: =Assumptions!$G$61*Assumptions!$E$24*Assumptions!$E$25 -> 0 | G36: =Assumptions!$H$61*Assumptions!$D$26*Assumptions!$D$27 -> 0.18 | H36: =Assumptions!$I$61*Assumptions!$E$28 -> 0.05 | I36: =Assumptions!$B$61*Assumptions!$D$31*Assumptions!$E$30 -> 0.9 | J36: =Assumptions!$B$61*Assumptions!$E$33/60*Assumptions!$E$32 -> 8.75 | K36: =(Assumptions!$C$61*Assumptions!$E$34+(Assumptions!$D$61+Assumptions!$E$61)*Assumptions!$E$35+Assumptions!$J$61*Assumptions!$E$36+Assumptions!$K$61)/60*Assumptions!$E$32 -> 9.9166667 | L36: =Assumptions!$L$61*Assumptions!$E$38/60*Assumptions!$E$37 -> 4.375 | M36: =SUM(B36:L36) -> 34.211667 | N36: =B36+C36+D36+E36+K36 -> 19.956667 | O36: =Assumptions!$E$39 -> 0.25 | P36: =(M36-N36)+N36/(1-O36) -> 40.863889 | Q36: =P36*Assumptions!$D$6 -> 30.852236 | R36: =IF(P36=0,0,(J36+K36/(1-O36)+L36)/P36) -> 0.64475563 | S36: =Assumptions!$B$61*Assumptions!$E$33+(Assumptions!$C$61*Assumptions!$E$34+(Assumptions!$D$61+Assumptions!$E$61)*Assumptions!$E$35+Assumptions!$J$61*Assumptions!$E$36+Assumptions!$K$61)/(1-O36)+Assumptions!$L$61*Assumptions!$E$38 -> 45.166667
A37: 4-bed house (19 images, 2 floors) | B37: =Assumptions!$B$62*Assumptions!$E$12+Assumptions!$C$62*Assumptions!$E$13+(Assumptions!$D$62+Assumptions!$E$62)*Assumptions!$E$14 -> 1.15 | C37: =Assumptions!$C$62*Assumptions!$E$16*Assumptions!$E$15 -> 18.24 | D37: =(Assumptions!$D$62*Assumptions!$D$20*Assumptions!$E$17+Assumptions!$E$62*Assumptions!$D$21*Assumptions!$E$18)*Assumptions!$E$19 -> 0 | E37: =Assumptions!$F$62*Assumptions!$E$23*Assumptions!$E$22 -> 3.72 | F37: =Assumptions!$G$62*Assumptions!$E$24*Assumptions!$E$25 -> 0 | G37: =Assumptions!$H$62*Assumptions!$D$26*Assumptions!$D$27 -> 0.36 | H37: =Assumptions!$I$62*Assumptions!$E$28 -> 0.1 | I37: =Assumptions!$B$62*Assumptions!$D$31*Assumptions!$E$30 -> 1.8 | J37: =Assumptions!$B$62*Assumptions!$E$33/60*Assumptions!$E$32 -> 17.5 | K37: =(Assumptions!$C$62*Assumptions!$E$34+(Assumptions!$D$62+Assumptions!$E$62)*Assumptions!$E$35+Assumptions!$J$62*Assumptions!$E$36+Assumptions!$K$62)/60*Assumptions!$E$32 -> 22.458333 | L37: =Assumptions!$L$62*Assumptions!$E$38/60*Assumptions!$E$37 -> 7 | M37: =SUM(B37:L37) -> 72.328333 | N37: =B37+C37+D37+E37+K37 -> 45.568333 | O37: =Assumptions!$E$39 -> 0.25 | P37: =(M37-N37)+N37/(1-O37) -> 87.517778 | Q37: =P37*Assumptions!$D$6 -> 66.075922 | R37: =IF(P37=0,0,(J37+K37/(1-O37)+L37)/P37) -> 0.62209583 | S37: =Assumptions!$B$62*Assumptions!$E$33+(Assumptions!$C$62*Assumptions!$E$34+(Assumptions!$D$62+Assumptions!$E$62)*Assumptions!$E$35+Assumptions!$J$62*Assumptions!$E$36+Assumptions!$K$62)/(1-O37)+Assumptions!$L$62*Assumptions!$E$38 -> 93.333333
A38: Interactive 3D property (WebGL tour, 1st month hosting) | B38: =Assumptions!$B$63*Assumptions!$E$12+Assumptions!$C$63*Assumptions!$E$13+(Assumptions!$D$63+Assumptions!$E$63)*Assumptions!$E$14 -> 0.1 | C38: =Assumptions!$C$63*Assumptions!$E$16*Assumptions!$E$15 -> 0 | D38: =(Assumptions!$D$63*Assumptions!$D$20*Assumptions!$E$17+Assumptions!$E$63*Assumptions!$D$21*Assumptions!$E$18)*Assumptions!$E$19 -> 0 | E38: =Assumptions!$F$63*Assumptions!$E$23*Assumptions!$E$22 -> 3.72 | F38: =Assumptions!$G$63*Assumptions!$E$24*Assumptions!$E$25 -> 18.753 | G38: =Assumptions!$H$63*Assumptions!$D$26*Assumptions!$D$27 -> 0.36 | H38: =Assumptions!$I$63*Assumptions!$E$28 -> 0.1 | I38: =Assumptions!$B$63*Assumptions!$D$31*Assumptions!$E$30 -> 0.9 | J38: =Assumptions!$B$63*Assumptions!$E$33/60*Assumptions!$E$32 -> 8.75 | K38: =(Assumptions!$C$63*Assumptions!$E$34+(Assumptions!$D$63+Assumptions!$E$63)*Assumptions!$E$35+Assumptions!$J$63*Assumptions!$E$36+Assumptions!$K$63)/60*Assumptions!$E$32 -> 8.75 | L38: =Assumptions!$L$63*Assumptions!$E$38/60*Assumptions!$E$37 -> 8.75 | M38: =SUM(B38:L38) -> 50.183 | N38: =B38+C38+D38+E38+K38 -> 12.57 | O38: =Assumptions!$E$39 -> 0.25 | P38: =(M38-N38)+N38/(1-O38) -> 54.373 | Q38: =P38*Assumptions!$D$6 -> 41.051615 | R38: =IF(P38=0,0,(J38+K38/(1-O38)+L38)/P38) -> 0.5364182 | S38: =Assumptions!$B$63*Assumptions!$E$33+(Assumptions!$C$63*Assumptions!$E$34+(Assumptions!$D$63+Assumptions!$E$63)*Assumptions!$E$35+Assumptions!$J$63*Assumptions!$E$36+Assumptions!$K$63)/(1-O38)+Assumptions!$L$63*Assumptions!$E$38 -> 50
A39: 30s walkthrough video | B39: =Assumptions!$B$64*Assumptions!$E$12+Assumptions!$C$64*Assumptions!$E$13+(Assumptions!$D$64+Assumptions!$E$64)*Assumptions!$E$14 -> 0.3 | C39: =Assumptions!$C$64*Assumptions!$E$16*Assumptions!$E$15 -> 0 | D39: =(Assumptions!$D$64*Assumptions!$D$20*Assumptions!$E$17+Assumptions!$E$64*Assumptions!$D$21*Assumptions!$E$18)*Assumptions!$E$19 -> 15.12 | E39: =Assumptions!$F$64*Assumptions!$E$23*Assumptions!$E$22 -> 1.86 | F39: =Assumptions!$G$64*Assumptions!$E$24*Assumptions!$E$25 -> 0 | G39: =Assumptions!$H$64*Assumptions!$D$26*Assumptions!$D$27 -> 0.09 | H39: =Assumptions!$I$64*Assumptions!$E$28 -> 0.05 | I39: =Assumptions!$B$64*Assumptions!$D$31*Assumptions!$E$30 -> 0.9 | J39: =Assumptions!$B$64*Assumptions!$E$33/60*Assumptions!$E$32 -> 8.75 | K39: =(Assumptions!$C$64*Assumptions!$E$34+(Assumptions!$D$64+Assumptions!$E$64)*Assumptions!$E$35+Assumptions!$J$64*Assumptions!$E$36+Assumptions!$K$64)/60*Assumptions!$E$32 -> 8.75 | L39: =Assumptions!$L$64*Assumptions!$E$38/60*Assumptions!$E$37 -> 4.375 | M39: =SUM(B39:L39) -> 40.195 | N39: =B39+C39+D39+E39+K39 -> 26.03 | O39: =Assumptions!$E$39 -> 0.25 | P39: =(M39-N39)+N39/(1-O39) -> 48.871667 | Q39: =P39*Assumptions!$D$6 -> 36.898108 | R39: =IF(P39=0,0,(J39+K39/(1-O39)+L39)/P39) -> 0.50728097 | S39: =Assumptions!$B$64*Assumptions!$E$33+(Assumptions!$C$64*Assumptions!$E$34+(Assumptions!$D$64+Assumptions!$E$64)*Assumptions!$E$35+Assumptions!$J$64*Assumptions!$E$36+Assumptions!$K$64)/(1-O39)+Assumptions!$L$64*Assumptions!$E$38 -> 42.5
A40: 60s cinematic video | B40: =Assumptions!$B$65*Assumptions!$E$12+Assumptions!$C$65*Assumptions!$E$13+(Assumptions!$D$65+Assumptions!$E$65)*Assumptions!$E$14 -> 0.3 | C40: =Assumptions!$C$65*Assumptions!$E$16*Assumptions!$E$15 -> 0 | D40: =(Assumptions!$D$65*Assumptions!$D$20*Assumptions!$E$17+Assumptions!$E$65*Assumptions!$D$21*Assumptions!$E$18)*Assumptions!$E$19 -> 108 | E40: =Assumptions!$F$65*Assumptions!$E$23*Assumptions!$E$22 -> 3.72 | F40: =Assumptions!$G$65*Assumptions!$E$24*Assumptions!$E$25 -> 0 | G40: =Assumptions!$H$65*Assumptions!$D$26*Assumptions!$D$27 -> 0.18 | H40: =Assumptions!$I$65*Assumptions!$E$28 -> 0.1 | I40: =Assumptions!$B$65*Assumptions!$D$31*Assumptions!$E$30 -> 0.9 | J40: =Assumptions!$B$65*Assumptions!$E$33/60*Assumptions!$E$32 -> 8.75 | K40: =(Assumptions!$C$65*Assumptions!$E$34+(Assumptions!$D$65+Assumptions!$E$65)*Assumptions!$E$35+Assumptions!$J$65*Assumptions!$E$36+Assumptions!$K$65)/60*Assumptions!$E$32 -> 8.75 | L40: =Assumptions!$L$65*Assumptions!$E$38/60*Assumptions!$E$37 -> 7 | M40: =SUM(B40:L40) -> 137.7 | N40: =B40+C40+D40+E40+K40 -> 120.77 | O40: =Assumptions!$E$39 -> 0.25 | P40: =(M40-N40)+N40/(1-O40) -> 177.95667 | Q40: =P40*Assumptions!$D$6 -> 134.35728 | R40: =IF(P40=0,0,(J40+K40/(1-O40)+L40)/P40) -> 0.15406372 | S40: =Assumptions!$B$65*Assumptions!$E$33+(Assumptions!$C$65*Assumptions!$E$34+(Assumptions!$D$65+Assumptions!$E$65)*Assumptions!$E$35+Assumptions!$J$65*Assumptions!$E$36+Assumptions!$K$65)/(1-O40)+Assumptions!$L$65*Assumptions!$E$38 -> 47
A41: Developer marketing package (per house type) | B41: =Assumptions!$B$66*Assumptions!$E$12+Assumptions!$C$66*Assumptions!$E$13+(Assumptions!$D$66+Assumptions!$E$66)*Assumptions!$E$14 -> 1.7 | C41: =Assumptions!$C$66*Assumptions!$E$16*Assumptions!$E$15 -> 21.12 | D41: =(Assumptions!$D$66*Assumptions!$D$20*Assumptions!$E$17+Assumptions!$E$66*Assumptions!$D$21*Assumptions!$E$18)*Assumptions!$E$19 -> 123.12 | E41: =Assumptions!$F$66*Assumptions!$E$23*Assumptions!$E$22 -> 7.44 | F41: =Assumptions!$G$66*Assumptions!$E$24*Assumptions!$E$25 -> 18.753 | G41: =Assumptions!$H$66*Assumptions!$D$26*Assumptions!$D$27 -> 0.54 | H41: =Assumptions!$I$66*Assumptions!$E$28 -> 0.2 | I41: =Assumptions!$B$66*Assumptions!$D$31*Assumptions!$E$30 -> 1.8 | J41: =Assumptions!$B$66*Assumptions!$E$33/60*Assumptions!$E$32 -> 17.5 | K41: =(Assumptions!$C$66*Assumptions!$E$34+(Assumptions!$D$66+Assumptions!$E$66)*Assumptions!$E$35+Assumptions!$J$66*Assumptions!$E$36+Assumptions!$K$66)/60*Assumptions!$E$32 -> 54.25 | L41: =Assumptions!$L$66*Assumptions!$E$38/60*Assumptions!$E$37 -> 26.25 | M41: =SUM(B41:L41) -> 272.673 | N41: =B41+C41+D41+E41+K41 -> 207.63 | O41: =Assumptions!$E$39 -> 0.25 | P41: =(M41-N41)+N41/(1-O41) -> 341.883 | Q41: =P41*Assumptions!$D$6 -> 258.12167 | R41: =IF(P41=0,0,(J41+K41/(1-O41)+L41)/P41) -> 0.33954111 | S41: =Assumptions!$B$66*Assumptions!$E$33+(Assumptions!$C$66*Assumptions!$E$34+(Assumptions!$D$66+Assumptions!$E$66)*Assumptions!$E$35+Assumptions!$J$66*Assumptions!$E$36+Assumptions!$K$66)/(1-O41)+Assumptions!$L$66*Assumptions!$E$38 -> 199
A42: 50-unit development (6 plan types) | B42: =Assumptions!$B$67*Assumptions!$E$12+Assumptions!$C$67*Assumptions!$E$13+(Assumptions!$D$67+Assumptions!$E$67)*Assumptions!$E$14 -> 17.7 | C42: =Assumptions!$C$67*Assumptions!$E$16*Assumptions!$E$15 -> 270.72 | D42: =(Assumptions!$D$67*Assumptions!$D$20*Assumptions!$E$17+Assumptions!$E$67*Assumptions!$D$21*Assumptions!$E$18)*Assumptions!$E$19 -> 738.72 | E42: =Assumptions!$F$67*Assumptions!$E$23*Assumptions!$E$22 -> 52.08 | F42: =Assumptions!$G$67*Assumptions!$E$24*Assumptions!$E$25 -> 112.518 | G42: =Assumptions!$H$67*Assumptions!$D$26*Assumptions!$D$27 -> 4.14 | H42: =Assumptions!$I$67*Assumptions!$E$28 -> 1.7 | I42: =Assumptions!$B$67*Assumptions!$D$31*Assumptions!$E$30 -> 10.8 | J42: =Assumptions!$B$67*Assumptions!$E$33/60*Assumptions!$E$32 -> 105 | K42: =(Assumptions!$C$67*Assumptions!$E$34+(Assumptions!$D$67+Assumptions!$E$67)*Assumptions!$E$35+Assumptions!$J$67*Assumptions!$E$36+Assumptions!$K$67)/60*Assumptions!$E$32 -> 564.66667 | L42: =Assumptions!$L$67*Assumptions!$E$38/60*Assumptions!$E$37 -> 105 | M42: =SUM(B42:L42) -> 1983.0447 | N42: =B42+C42+D42+E42+K42 -> 1643.8867 | O42: =Assumptions!$E$39 -> 0.25 | P42: =(M42-N42)+N42/(1-O42) -> 2531.0069 | Q42: =P42*Assumptions!$D$6 -> 1910.9102 | R42: =IF(P42=0,0,(J42+K42/(1-O42)+L42)/P42) -> 0.38043709 | S42: =Assumptions!$B$67*Assumptions!$E$33+(Assumptions!$C$67*Assumptions!$E$34+(Assumptions!$D$67+Assumptions!$E$67)*Assumptions!$E$35+Assumptions!$J$67*Assumptions!$E$36+Assumptions!$K$67)/(1-O42)+Assumptions!$L$67*Assumptions!$E$38 -> 1650.6667
A43: 200-unit development (15 plan types) | B43: =Assumptions!$B$68*Assumptions!$E$12+Assumptions!$C$68*Assumptions!$E$13+(Assumptions!$D$68+Assumptions!$E$68)*Assumptions!$E$14 -> 55.5 | C43: =Assumptions!$C$68*Assumptions!$E$16*Assumptions!$E$15 -> 892.8 | D43: =(Assumptions!$D$68*Assumptions!$D$20*Assumptions!$E$17+Assumptions!$E$68*Assumptions!$D$21*Assumptions!$E$18)*Assumptions!$E$19 -> 1846.8 | E43: =Assumptions!$F$68*Assumptions!$E$23*Assumptions!$E$22 -> 119.04 | F43: =Assumptions!$G$68*Assumptions!$E$24*Assumptions!$E$25 -> 281.295 | G43: =Assumptions!$H$68*Assumptions!$D$26*Assumptions!$D$27 -> 11.7 | H43: =Assumptions!$I$68*Assumptions!$E$28 -> 5 | I43: =Assumptions!$B$68*Assumptions!$D$31*Assumptions!$E$30 -> 27 | J43: =Assumptions!$B$68*Assumptions!$E$33/60*Assumptions!$E$32 -> 262.5 | K43: =(Assumptions!$C$68*Assumptions!$E$34+(Assumptions!$D$68+Assumptions!$E$68)*Assumptions!$E$35+Assumptions!$J$68*Assumptions!$E$36+Assumptions!$K$68)/60*Assumptions!$E$32 -> 1665.4167 | L43: =Assumptions!$L$68*Assumptions!$E$38/60*Assumptions!$E$37 -> 210 | M43: =SUM(B43:L43) -> 5377.0517 | N43: =B43+C43+D43+E43+K43 -> 4579.5567 | O43: =Assumptions!$E$39 -> 0.25 | P43: =(M43-N43)+N43/(1-O43) -> 6903.5706 | Q43: =P43*Assumptions!$D$6 -> 5212.1958 | R43: =IF(P43=0,0,(J43+K43/(1-O43)+L43)/P43) -> 0.39009604 | S43: =Assumptions!$B$68*Assumptions!$E$33+(Assumptions!$C$68*Assumptions!$E$34+(Assumptions!$D$68+Assumptions!$E$68)*Assumptions!$E$35+Assumptions!$J$68*Assumptions!$E$36+Assumptions!$K$68)/(1-O43)+Assumptions!$L$68*Assumptions!$E$38 -> 4616.6667
A44: Ongoing hosting per interactive property per month (streaming + CDN + storage) | M44: =Assumptions!$E$24*Assumptions!$E$25+Assumptions!$D$29*Assumptions!$E$28+Assumptions!$D$44*Assumptions!$D$26 -> 18.883 | Q44: =M44*Assumptions!$D$6 -> 14.256665
A46: Cost per successful deliverable — summary
A47: Deliverable | B47: Low (USD) | C47: Base (USD) | D47: High (USD) | E47: Low (GBP) | F47: Base (GBP) | G47: High (GBP) | H47: Base human labour share
A48: Single room image | B48: =P6 -> 1.6205877 | C48: =P20 -> 7.1375098 | D48: =P34 -> 14.317667 | E48: =Q6 -> 1.2235437 | F48: =Q20 -> 5.3888199 | G48: =Q34 -> 10.809838 | H48: =R20 -> 0.79255411
A49: 5 room images | B49: =P7 -> 4.0434211 | C49: =P21 -> 14.387451 | D49: =P35 -> 27.632556 | E49: =Q7 -> 3.0527829 | F49: =Q21 -> 10.862525 | G49: =Q35 -> 20.862579 | H49: =R21 -> 0.63235935
A50: 2-bed flat (8 images + plan) | B50: =P8 -> 6.6192982 | C50: =P22 -> 21.480392 | D50: =P36 -> 40.863889 | E50: =Q8 -> 4.9975702 | F50: =Q22 -> 16.217696 | G50: =Q36 -> 30.852236 | H50: =R22 -> 0.60702875
A51: 4-bed house (19 images, 2 floors) | B51: =P9 -> 13.993509 | C51: =P23 -> 46.078431 | D51: =P37 -> 87.517778 | E51: =Q9 -> 10.565099 | F51: =Q23 -> 34.789216 | G51: =Q37 -> 66.075922 | H51: =R23 -> 0.57617021
A52: Interactive 3D property (WebGL tour, 1st month hosting) | B52: =P10 -> 7.5285965 | C52: =P24 -> 22.413137 | D52: =P38 -> 54.373 | E52: =Q10 -> 5.6840904 | F52: =Q24 -> 16.921919 | G52: =Q38 -> 41.051615 | H52: =R24 -> 0.73705022
A53: 30s walkthrough video | B53: =P11 -> 6.7735088 | C53: =P25 -> 21.449216 | D53: =P39 -> 48.871667 | E53: =Q11 -> 5.1139991 | F53: =Q25 -> 16.194158 | G53: =Q39 -> 36.898108 | H53: =R25 -> 0.53934967
A54: 60s cinematic video | B54: =P12 -> 15.721404 | C54: =P26 -> 71.730392 | D54: =P40 -> 177.95667 | E54: =Q12 -> 11.86966 | F54: =Q26 -> 54.156446 | G54: =Q40 -> 134.35728 | H54: =R26 -> 0.18219094
A55: Developer marketing package (per house type) | B55: =P13 -> 42.973158 | C55: =P27 -> 151.18275 | D55: =P41 -> 341.883 | E55: =Q13 -> 32.444734 | F55: =Q27 -> 114.14297 | G55: =Q41 -> 258.12167 | H55: =R27 -> 0.38779195
A56: 50-unit development (6 plan types) | B56: =P14 -> 334.63632 | C56: =P28 -> 1153.12 | D56: =P42 -> 2531.0069 | E56: =Q14 -> 252.65042 | F56: =Q28 -> 870.6056 | G56: =Q42 -> 1910.9102 | H56: =R28 -> 0.40019303
A57: 200-unit development (15 plan types) | B57: =P15 -> 908.80526 | C57: =P29 -> 3170.9059 | D57: =P43 -> 6903.5706 | E57: =Q15 -> 686.14797 | F57: =Q29 -> 2394.0339 | G57: =Q43 -> 5212.1958 | H57: =R29 -> 0.39263228
A58: Ongoing hosting per interactive property-month | B58: =M16 -> 0.08 | C58: =M30 -> 3.77 | D58: =M44 -> 18.883 | E58: =Q16 -> 0.0604 | F58: =Q30 -> 2.84635 | G58: =Q44 -> 14.256665
A60: Retry / failure sensitivity — BASE cost case: cost per success at deliverable-level rejection rates (QA on rejects included)
A61: Deliverable | B61: ="USD @ "&TEXT(Assumptions!$D$40,"0%") -> USD @ 5% | C61: ="USD @ "&TEXT(Assumptions!$D$41,"0%") -> USD @ 15% | D61: ="USD @ "&TEXT(Assumptions!$D$42,"0%") -> USD @ 30% | E61: ="USD @ "&TEXT(Assumptions!$D$43,"0%") -> USD @ 50% | F61: ="GBP @ "&TEXT(Assumptions!$D$40,"0%") -> GBP @ 5% | G61: ="GBP @ "&TEXT(Assumptions!$D$41,"0%") -> GBP @ 15% | H61: ="GBP @ "&TEXT(Assumptions!$D$42,"0%") -> GBP @ 30% | I61: ="GBP @ "&TEXT(Assumptions!$D$43,"0%") -> GBP @ 50%
A62: Single room image | B62: =(M20-N20)+N20/(1-Assumptions!$D$40) -> 6.9798421 | C62: =(M20-N20)+N20/(1-Assumptions!$D$41) -> 7.1375098 | D62: =(M20-N20)+N20/(1-Assumptions!$D$42) -> 7.4584762 | E62: =(M20-N20)+N20/(1-Assumptions!$D$43) -> 8.186 | F62: =B62*Assumptions!$D$6 -> 5.2697808 | G62: =C62*Assumptions!$D$6 -> 5.3888199 | H62: =D62*Assumptions!$D$6 -> 5.6311495 | I62: =E62*Assumptions!$D$6 -> 6.18043
A63: 5 room images | B63: =(M21-N21)+N21/(1-Assumptions!$D$40) -> 13.528421 | C63: =(M21-N21)+N21/(1-Assumptions!$D$41) -> 14.387451 | D63: =(M21-N21)+N21/(1-Assumptions!$D$42) -> 16.13619 | E63: =(M21-N21)+N21/(1-Assumptions!$D$43) -> 20.1 | F63: =B63*Assumptions!$D$6 -> 10.213958 | G63: =C63*Assumptions!$D$6 -> 10.862525 | H63: =D63*Assumptions!$D$6 -> 12.182824 | I63: =E63*Assumptions!$D$6 -> 15.1755
A64: 2-bed flat (8 images + plan) | B64: =(M22-N22)+N22/(1-Assumptions!$D$40) -> 19.992632 | C64: =(M22-N22)+N22/(1-Assumptions!$D$41) -> 21.480392 | D64: =(M22-N22)+N22/(1-Assumptions!$D$42) -> 24.509048 | E64: =(M22-N22)+N22/(1-Assumptions!$D$43) -> 31.374 | F64: =B64*Assumptions!$D$6 -> 15.094437 | G64: =C64*Assumptions!$D$6 -> 16.217696 | H64: =D64*Assumptions!$D$6 -> 18.504331 | I64: =E64*Assumptions!$D$6 -> 23.68737
A65: 4-bed house (19 images, 2 floors) | B65: =(M23-N23)+N23/(1-Assumptions!$D$40) -> 42.669474 | C65: =(M23-N23)+N23/(1-Assumptions!$D$41) -> 46.078431 | D65: =(M23-N23)+N23/(1-Assumptions!$D$42) -> 53.018095 | E65: =(M23-N23)+N23/(1-Assumptions!$D$43) -> 68.748 | F65: =B65*Assumptions!$D$6 -> 32.215453 | G65: =C65*Assumptions!$D$6 -> 34.789216 | H65: =D65*Assumptions!$D$6 -> 40.028662 | I65: =E65*Assumptions!$D$6 -> 51.90474
A66: Interactive 3D property (WebGL tour, 1st month hosting) | B66: =(M24-N24)+N24/(1-Assumptions!$D$40) -> 21.497719 | C66: =(M24-N24)+N24/(1-Assumptions!$D$41) -> 22.413137 | D66: =(M24-N24)+N24/(1-Assumptions!$D$42) -> 24.276667 | E66: =(M24-N24)+N24/(1-Assumptions!$D$43) -> 28.500667 | F66: =B66*Assumptions!$D$6 -> 16.230778 | G66: =C66*Assumptions!$D$6 -> 16.921919 | H66: =D66*Assumptions!$D$6 -> 18.328883 | I66: =E66*Assumptions!$D$6 -> 21.518003
A67: 30s walkthrough video | B67: =(M25-N25)+N25/(1-Assumptions!$D$40) -> 19.955263 | C67: =(M25-N25)+N25/(1-Assumptions!$D$41) -> 21.449216 | D67: =(M25-N25)+N25/(1-Assumptions!$D$42) -> 24.490476 | E67: =(M25-N25)+N25/(1-Assumptions!$D$43) -> 31.384 | F67: =B67*Assumptions!$D$6 -> 15.066224 | G67: =C67*Assumptions!$D$6 -> 16.194158 | H67: =D67*Assumptions!$D$6 -> 18.49031 | I67: =E67*Assumptions!$D$6 -> 23.69492
A68: 60s cinematic video | B68: =(M26-N26)+N26/(1-Assumptions!$D$40) -> 65.116316 | C68: =(M26-N26)+N26/(1-Assumptions!$D$41) -> 71.730392 | D68: =(M26-N26)+N26/(1-Assumptions!$D$42) -> 85.194762 | E68: =(M26-N26)+N26/(1-Assumptions!$D$43) -> 115.714 | F68: =B68*Assumptions!$D$6 -> 49.162818 | G68: =C68*Assumptions!$D$6 -> 54.156446 | H68: =D68*Assumptions!$D$6 -> 64.322045 | I68: =E68*Assumptions!$D$6 -> 87.36407
A69: Developer marketing package (per house type) | B69: =(M27-N27)+N27/(1-Assumptions!$D$40) -> 138.2807 | C69: =(M27-N27)+N27/(1-Assumptions!$D$41) -> 151.18275 | D69: =(M27-N27)+N27/(1-Assumptions!$D$42) -> 177.44762 | E69: =(M27-N27)+N27/(1-Assumptions!$D$43) -> 236.98133 | F69: =B69*Assumptions!$D$6 -> 104.40193 | G69: =C69*Assumptions!$D$6 -> 114.14297 | H69: =D69*Assumptions!$D$6 -> 133.97295 | I69: =E69*Assumptions!$D$6 -> 178.92091
A70: 50-unit development (6 plan types) | B70: =(M28-N28)+N28/(1-Assumptions!$D$40) -> 1046.8 | C70: =(M28-N28)+N28/(1-Assumptions!$D$41) -> 1153.12 | D70: =(M28-N28)+N28/(1-Assumptions!$D$42) -> 1369.5571 | E70: =(M28-N28)+N28/(1-Assumptions!$D$43) -> 1860.148 | F70: =B70*Assumptions!$D$6 -> 790.334 | G70: =C70*Assumptions!$D$6 -> 870.6056 | H70: =D70*Assumptions!$D$6 -> 1034.0156 | I70: =E70*Assumptions!$D$6 -> 1404.4117
A71: 200-unit development (15 plan types) | B71: =(M29-N29)+N29/(1-Assumptions!$D$40) -> 2871.8421 | C71: =(M29-N29)+N29/(1-Assumptions!$D$41) -> 3170.9059 | D71: =(M29-N29)+N29/(1-Assumptions!$D$42) -> 3779.7143 | E71: =(M29-N29)+N29/(1-Assumptions!$D$43) -> 5159.68 | F71: =B71*Assumptions!$D$6 -> 2168.2408 | G71: =C71*Assumptions!$D$6 -> 2394.0339 | H71: =D71*Assumptions!$D$6 -> 2853.6843 | I71: =E71*Assumptions!$D$6 -> 3895.5584
A72: Note: the base case already assumes 3 generation attempts per accepted image and 2x video retakes; this table adds deliverable-level rejection (whole set redone after QA/customer rejection). Rejected attempts re-incur generation AND human output-review minutes; 2D confirm, storage and support are not repeated.

Sheet Pricing
A1: Pricing — tiers, allowances, overages, setup & per-development fees; gross margin at included usage
A3: A. Recommended structure: subscription + included credits + overage + setup fee + per-development fee
A4: Metric | B4: Studio | C4: Agency | D4: Developer Pro | E4: Enterprise
A5: List price (£ / month) | B5: =Assumptions!$D$73 -> 149 | C5: =Assumptions!$D$74 -> 499 | D5: =Assumptions!$D$75 -> 1499 | E5: =Assumptions!$D$76 -> 5000
A6: Included credits / month (= tier usage mix) | B6: =Assumptions!$B$113*Assumptions!$M$59+Assumptions!$C$113*Assumptions!$M$60+Assumptions!$D$113*Assumptions!$M$61+Assumptions!$E$113*Assumptions!$M$62+Assumptions!$F$113*Assumptions!$M$63+Assumptions!$G$113*Assumptions!$M$64+Assumptions!$H$113*Assumptions!$M$65+Assumptions!$I$113*Assumptions!$M$66+Assumptions!$J$113*Assumptions!$M$67+Assumptions!$K$113*Assumptions!$M$68 -> 52 | C6: =Assumptions!$B$114*Assumptions!$M$59+Assumptions!$C$114*Assumptions!$M$60+Assumptions!$D$114*Assumptions!$M$61+Assumptions!$E$114*Assumptions!$M$62+Assumptions!$F$114*Assumptions!$M$63+Assumptions!$G$114*Assumptions!$M$64+Assumptions!$H$114*Assumptions!$M$65+Assumptions!$I$114*Assumptions!$M$66+Assumptions!$J$114*Assumptions!$M$67+Assumptions!$K$114*Assumptions!$M$68 -> 204 | D6: =Assumptions!$B$115*Assumptions!$M$59+Assumptions!$C$115*Assumptions!$M$60+Assumptions!$D$115*Assumptions!$M$61+Assumptions!$E$115*Assumptions!$M$62+Assumptions!$F$115*Assumptions!$M$63+Assumptions!$G$115*Assumptions!$M$64+Assumptions!$H$115*Assumptions!$M$65+Assumptions!$I$115*Assumptions!$M$66+Assumptions!$J$115*Assumptions!$M$67+Assumptions!$K$115*Assumptions!$M$68 -> 444 | E6: =Assumptions!$B$116*Assumptions!$M$59+Assumptions!$C$116*Assumptions!$M$60+Assumptions!$D$116*Assumptions!$M$61+Assumptions!$E$116*Assumptions!$M$62+Assumptions!$F$116*Assumptions!$M$63+Assumptions!$G$116*Assumptions!$M$64+Assumptions!$H$116*Assumptions!$M$65+Assumptions!$I$116*Assumptions!$M$66+Assumptions!$J$116*Assumptions!$M$67+Assumptions!$K$116*Assumptions!$M$68 -> 1874
A7: Effective price per included credit (£) | B7: =IF(B6=0,0,B5/B6) -> 2.8653846 | C7: =IF(C6=0,0,C5/C6) -> 2.4460784 | D7: =IF(D6=0,0,D5/D6) -> 3.3761261 | E7: =IF(E6=0,0,E5/E6) -> 2.6680896
A8: Overage price (£ / credit) | B8: =Assumptions!$D$79 -> 4 | C8: =Assumptions!$D$80 -> 3.5 | D8: =Assumptions!$D$81 -> 3 | E8: =Assumptions!$D$82 -> 2.5
A9: Setup fee (£ one-off) | B9: =Assumptions!$D$83 -> 0 | C9: =Assumptions!$D$84 -> 500 | D9: =Assumptions!$D$85 -> 1500 | E9: =Assumptions!$D$86 -> 7500
A10: Per-development fee, extra developments (£ per plan type; Developer Pro/Enterprise) | B10: 0 | C10: 0 | D10: =Assumptions!$D$87 -> 350 | E10: =Assumptions!$D$87 -> 350
A11: Hosted interactive properties included | B11: =Assumptions!$D$88 -> 1 | C11: =Assumptions!$D$89 -> 5 | D11: =Assumptions!$D$90 -> 15 | E11: =Assumptions!$D$91 -> 50
A12: SSO connections included | B12: =Assumptions!$D$92 -> 0 | C12: =Assumptions!$D$93 -> 0 | D12: =Assumptions!$D$94 -> 0 | E12: =Assumptions!$D$95 -> 1
A14: LOW cost case
A15: Cost of included usage at 100% (£ / month) | B15: =Assumptions!$B$113*Unit_Costs!$Q$6+Assumptions!$C$113*Unit_Costs!$Q$7+Assumptions!$D$113*Unit_Costs!$Q$8+Assumptions!$E$113*Unit_Costs!$Q$9+Assumptions!$F$113*Unit_Costs!$Q$10+Assumptions!$G$113*Unit_Costs!$Q$11+Assumptions!$H$113*Unit_Costs!$Q$12+Assumptions!$I$113*Unit_Costs!$Q$13+Assumptions!$J$113*Unit_Costs!$Q$14+Assumptions!$K$113*Unit_Costs!$Q$15 -> 16.786213 | C15: =Assumptions!$B$114*Unit_Costs!$Q$6+Assumptions!$C$114*Unit_Costs!$Q$7+Assumptions!$D$114*Unit_Costs!$Q$8+Assumptions!$E$114*Unit_Costs!$Q$9+Assumptions!$F$114*Unit_Costs!$Q$10+Assumptions!$G$114*Unit_Costs!$Q$11+Assumptions!$H$114*Unit_Costs!$Q$12+Assumptions!$I$114*Unit_Costs!$Q$13+Assumptions!$J$114*Unit_Costs!$Q$14+Assumptions!$K$114*Unit_Costs!$Q$15 -> 63.138133 | D15: =Assumptions!$B$115*Unit_Costs!$Q$6+Assumptions!$C$115*Unit_Costs!$Q$7+Assumptions!$D$115*Unit_Costs!$Q$8+Assumptions!$E$115*Unit_Costs!$Q$9+Assumptions!$F$115*Unit_Costs!$Q$10+Assumptions!$G$115*Unit_Costs!$Q$11+Assumptions!$H$115*Unit_Costs!$Q$12+Assumptions!$I$115*Unit_Costs!$Q$13+Assumptions!$J$115*Unit_Costs!$Q$14+Assumptions!$K$115*Unit_Costs!$Q$15 -> 103.07194 | E15: =Assumptions!$B$116*Unit_Costs!$Q$6+Assumptions!$C$116*Unit_Costs!$Q$7+Assumptions!$D$116*Unit_Costs!$Q$8+Assumptions!$E$116*Unit_Costs!$Q$9+Assumptions!$F$116*Unit_Costs!$Q$10+Assumptions!$G$116*Unit_Costs!$Q$11+Assumptions!$H$116*Unit_Costs!$Q$12+Assumptions!$I$116*Unit_Costs!$Q$13+Assumptions!$J$116*Unit_Costs!$Q$14+Assumptions!$K$116*Unit_Costs!$Q$15 -> 427.31702
A16: Per-account fixed cost: hosting + SSO (£ / month) | B16: =Assumptions!$D$88*Unit_Costs!$Q$16+Assumptions!$D$92*Assumptions!$D$96*Assumptions!$D$6 -> 0.0604 | C16: =Assumptions!$D$89*Unit_Costs!$Q$16+Assumptions!$D$93*Assumptions!$D$96*Assumptions!$D$6 -> 0.302 | D16: =Assumptions!$D$90*Unit_Costs!$Q$16+Assumptions!$D$94*Assumptions!$D$96*Assumptions!$D$6 -> 0.906 | E16: =Assumptions!$D$91*Unit_Costs!$Q$16+Assumptions!$D$95*Assumptions!$D$96*Assumptions!$D$6 -> 97.395
A17: Payment fees at list price (£ / month) | B17: =B5*Assumptions!$D$97+Assumptions!$D$101 -> 3.478 | C17: =C5*Assumptions!$D$98+Assumptions!$D$102 -> 11.178 | D17: =D5*Assumptions!$D$99+Assumptions!$D$103 -> 20.489 | E17: =E5*Assumptions!$D$100+Assumptions!$D$104 -> 59
A18: Gross margin at 100% of included usage | B18: =1-(B15+B16+B17)/B5 -> 0.8635932 | C18: =1-(C15+C16+C17)/C5 -> 0.85046466 | D18: =1-(D15+D16+D17)/D5 -> 0.91696669 | E18: =1-(E15+E16+E17)/E5 -> 0.8832576
A19: Gross margin at Base-scenario utilisation | B19: =1-(B15*Assumptions!$D$153+B16+B17)/B5 -> 0.9030239 | C19: =1-(C15*Assumptions!$D$153+C16+C17)/C5 -> 0.89474993 | D19: =1-(D15*Assumptions!$D$153+D16+D17)/D5 -> 0.94103285 | E19: =1-(E15*Assumptions!$D$153+E16+E17)/E5 -> 0.91316979
A20: Cost per credit (£) | B20: =IF(B6=0,0,B15/B6) -> 0.32281179 | C20: =IF(C6=0,0,C15/C6) -> 0.30950065 | D20: =IF(D6=0,0,D15/D6) -> 0.232144 | E20: =IF(E6=0,0,E15/E6) -> 0.22802402
A21: Overage gross margin | B21: =IF(B8=0,0,1-B20/B8-Assumptions!$D$97) -> 0.89729705 | C21: =IF(C8=0,0,1-C20/C8-Assumptions!$D$98) -> 0.88957124 | D21: =IF(D8=0,0,1-D20/D8-Assumptions!$D$99) -> 0.91161867 | E21: =IF(E8=0,0,1-E20/E8-Assumptions!$D$100) -> 0.89779039
A22: Setup fee gross margin (onboarding labour) | B22: =IF(B9=0,0,1-Assumptions!$D$105*Assumptions!$D$109/B9) -> 0 | C22: =IF(C9=0,0,1-Assumptions!$D$106*Assumptions!$D$109/C9) -> 0.79 | D22: =IF(D9=0,0,1-Assumptions!$D$107*Assumptions!$D$109/D9) -> 0.81333333 | E22: =IF(E9=0,0,1-Assumptions!$D$108*Assumptions!$D$109/E9) -> 0.86
A23: Human minutes per credit | B23: =IF(B6=0,0,(Assumptions!$B$113*Unit_Costs!$S$6+Assumptions!$C$113*Unit_Costs!$S$7+Assumptions!$D$113*Unit_Costs!$S$8+Assumptions!$E$113*Unit_Costs!$S$9+Assumptions!$F$113*Unit_Costs!$S$10+Assumptions!$G$113*Unit_Costs!$S$11+Assumptions!$H$113*Unit_Costs!$S$12+Assumptions!$I$113*Unit_Costs!$S$13+Assumptions!$J$113*Unit_Costs!$S$14+Assumptions!$K$113*Unit_Costs!$S$15)/B6) -> 0.96204453 | C23: =IF(C6=0,0,(Assumptions!$B$114*Unit_Costs!$S$6+Assumptions!$C$114*Unit_Costs!$S$7+Assumptions!$D$114*Unit_Costs!$S$8+Assumptions!$E$114*Unit_Costs!$S$9+Assumptions!$F$114*Unit_Costs!$S$10+Assumptions!$G$114*Unit_Costs!$S$11+Assumptions!$H$114*Unit_Costs!$S$12+Assumptions!$I$114*Unit_Costs!$S$13+Assumptions!$J$114*Unit_Costs!$S$14+Assumptions!$K$114*Unit_Costs!$S$15)/C6) -> 0.90557276 | D23: =IF(D6=0,0,(Assumptions!$B$115*Unit_Costs!$S$6+Assumptions!$C$115*Unit_Costs!$S$7+Assumptions!$D$115*Unit_Costs!$S$8+Assumptions!$E$115*Unit_Costs!$S$9+Assumptions!$F$115*Unit_Costs!$S$10+Assumptions!$G$115*Unit_Costs!$S$11+Assumptions!$H$115*Unit_Costs!$S$12+Assumptions!$I$115*Unit_Costs!$S$13+Assumptions!$J$115*Unit_Costs!$S$14+Assumptions!$K$115*Unit_Costs!$S$15)/D6) -> 0.63466098 | E23: =IF(E6=0,0,(Assumptions!$B$116*Unit_Costs!$S$6+Assumptions!$C$116*Unit_Costs!$S$7+Assumptions!$D$116*Unit_Costs!$S$8+Assumptions!$E$116*Unit_Costs!$S$9+Assumptions!$F$116*Unit_Costs!$S$10+Assumptions!$G$116*Unit_Costs!$S$11+Assumptions!$H$116*Unit_Costs!$S$12+Assumptions!$I$116*Unit_Costs!$S$13+Assumptions!$J$116*Unit_Costs!$S$14+Assumptions!$K$116*Unit_Costs!$S$15)/E6) -> 0.57335842
A24: BASE cost case
A25: Cost of included usage at 100% (£ / month) | B25: =Assumptions!$B$113*Unit_Costs!$Q$20+Assumptions!$C$113*Unit_Costs!$Q$21+Assumptions!$D$113*Unit_Costs!$Q$22+Assumptions!$E$113*Unit_Costs!$Q$23+Assumptions!$F$113*Unit_Costs!$Q$24+Assumptions!$G$113*Unit_Costs!$Q$25+Assumptions!$H$113*Unit_Costs!$Q$26+Assumptions!$I$113*Unit_Costs!$Q$27+Assumptions!$J$113*Unit_Costs!$Q$28+Assumptions!$K$113*Unit_Costs!$Q$29 -> 56.395732 | C25: =Assumptions!$B$114*Unit_Costs!$Q$20+Assumptions!$C$114*Unit_Costs!$Q$21+Assumptions!$D$114*Unit_Costs!$Q$22+Assumptions!$E$114*Unit_Costs!$Q$23+Assumptions!$F$114*Unit_Costs!$Q$24+Assumptions!$G$114*Unit_Costs!$Q$25+Assumptions!$H$114*Unit_Costs!$Q$26+Assumptions!$I$114*Unit_Costs!$Q$27+Assumptions!$J$114*Unit_Costs!$Q$28+Assumptions!$K$114*Unit_Costs!$Q$29 -> 205.4845 | D25: =Assumptions!$B$115*Unit_Costs!$Q$20+Assumptions!$C$115*Unit_Costs!$Q$21+Assumptions!$D$115*Unit_Costs!$Q$22+Assumptions!$E$115*Unit_Costs!$Q$23+Assumptions!$F$115*Unit_Costs!$Q$24+Assumptions!$G$115*Unit_Costs!$Q$25+Assumptions!$H$115*Unit_Costs!$Q$26+Assumptions!$I$115*Unit_Costs!$Q$27+Assumptions!$J$115*Unit_Costs!$Q$28+Assumptions!$K$115*Unit_Costs!$Q$29 -> 348.63013 | E25: =Assumptions!$B$116*Unit_Costs!$Q$20+Assumptions!$C$116*Unit_Costs!$Q$21+Assumptions!$D$116*Unit_Costs!$Q$22+Assumptions!$E$116*Unit_Costs!$Q$23+Assumptions!$F$116*Unit_Costs!$Q$24+Assumptions!$G$116*Unit_Costs!$Q$25+Assumptions!$H$116*Unit_Costs!$Q$26+Assumptions!$I$116*Unit_Costs!$Q$27+Assumptions!$J$116*Unit_Costs!$Q$28+Assumptions!$K$116*Unit_Costs!$Q$29 -> 1470.6892
A26: Per-account fixed cost: hosting + SSO (£ / month) | B26: =Assumptions!$D$88*Unit_Costs!$Q$30+Assumptions!$D$92*Assumptions!$D$96*Assumptions!$D$6 -> 2.84635 | C26: =Assumptions!$D$89*Unit_Costs!$Q$30+Assumptions!$D$93*Assumptions!$D$96*Assumptions!$D$6 -> 14.23175 | D26: =Assumptions!$D$90*Unit_Costs!$Q$30+Assumptions!$D$94*Assumptions!$D$96*Assumptions!$D$6 -> 42.69525 | E26: =Assumptions!$D$91*Unit_Costs!$Q$30+Assumptions!$D$95*Assumptions!$D$96*Assumptions!$D$6 -> 236.6925
A27: Payment fees at list price (£ / month) | B27: =B5*Assumptions!$D$97+Assumptions!$D$101 -> 3.478 | C27: =C5*Assumptions!$D$98+Assumptions!$D$102 -> 11.178 | D27: =D5*Assumptions!$D$99+Assumptions!$D$103 -> 20.489 | E27: =E5*Assumptions!$D$100+Assumptions!$D$104 -> 59
A28: Gross margin at 100% of included usage | B28: =1-(B25+B26+B27)/B5 -> 0.57905985 | C28: =1-(C25+C26+C27)/C5 -> 0.53728607 | D28: =1-(D25+D26+D27)/D5 -> 0.72527393 | E28: =1-(E25+E26+E27)/E5 -> 0.64672366
A29: Gross margin at Base-scenario utilisation | B29: =1-(B25*Assumptions!$D$153+B26+B27)/B5 -> 0.71153305 | C29: =1-(C25*Assumptions!$D$153+C26+C27)/C5 -> 0.68141348 | D29: =1-(D25*Assumptions!$D$153+D26+D27)/D5 -> 0.80667523 | E29: =1-(E25*Assumptions!$D$153+E26+E27)/E5 -> 0.7496719
A30: Cost per credit (£) | B30: =IF(B6=0,0,B25/B6) -> 1.0845333 | C30: =IF(C6=0,0,C25/C6) -> 1.007277 | D30: =IF(D6=0,0,D25/D6) -> 0.785203 | E30: =IF(E6=0,0,E25/E6) -> 0.78478614
A31: Overage gross margin | B31: =IF(B8=0,0,1-B30/B8-Assumptions!$D$97) -> 0.70686667 | C31: =IF(C8=0,0,1-C30/C8-Assumptions!$D$98) -> 0.69020658 | D31: =IF(D8=0,0,1-D30/D8-Assumptions!$D$99) -> 0.72726567 | E31: =IF(E8=0,0,1-E30/E8-Assumptions!$D$100) -> 0.67508554
A32: Setup fee gross margin (onboarding labour) | B32: =IF(B9=0,0,1-Assumptions!$D$105*Assumptions!$D$109/B9) -> 0 | C32: =IF(C9=0,0,1-Assumptions!$D$106*Assumptions!$D$109/C9) -> 0.79 | D32: =IF(D9=0,0,1-Assumptions!$D$107*Assumptions!$D$109/D9) -> 0.81333333 | E32: =IF(E9=0,0,1-Assumptions!$D$108*Assumptions!$D$109/E9) -> 0.86
A33: Human minutes per credit | B33: =IF(B6=0,0,(Assumptions!$B$113*Unit_Costs!$S$20+Assumptions!$C$113*Unit_Costs!$S$21+Assumptions!$D$113*Unit_Costs!$S$22+Assumptions!$E$113*Unit_Costs!$S$23+Assumptions!$F$113*Unit_Costs!$S$24+Assumptions!$G$113*Unit_Costs!$S$25+Assumptions!$H$113*Unit_Costs!$S$26+Assumptions!$I$113*Unit_Costs!$S$27+Assumptions!$J$113*Unit_Costs!$S$28+Assumptions!$K$113*Unit_Costs!$S$29)/B6) -> 2.030543 | C33: =IF(C6=0,0,(Assumptions!$B$114*Unit_Costs!$S$20+Assumptions!$C$114*Unit_Costs!$S$21+Assumptions!$D$114*Unit_Costs!$S$22+Assumptions!$E$114*Unit_Costs!$S$23+Assumptions!$F$114*Unit_Costs!$S$24+Assumptions!$G$114*Unit_Costs!$S$25+Assumptions!$H$114*Unit_Costs!$S$26+Assumptions!$I$114*Unit_Costs!$S$27+Assumptions!$J$114*Unit_Costs!$S$28+Assumptions!$K$114*Unit_Costs!$S$29)/C6) -> 1.8581315 | D33: =IF(D6=0,0,(Assumptions!$B$115*Unit_Costs!$S$20+Assumptions!$C$115*Unit_Costs!$S$21+Assumptions!$D$115*Unit_Costs!$S$22+Assumptions!$E$115*Unit_Costs!$S$23+Assumptions!$F$115*Unit_Costs!$S$24+Assumptions!$G$115*Unit_Costs!$S$25+Assumptions!$H$115*Unit_Costs!$S$26+Assumptions!$I$115*Unit_Costs!$S$27+Assumptions!$J$115*Unit_Costs!$S$28+Assumptions!$K$115*Unit_Costs!$S$29)/D6) -> 1.1409645 | E33: =IF(E6=0,0,(Assumptions!$B$116*Unit_Costs!$S$20+Assumptions!$C$116*Unit_Costs!$S$21+Assumptions!$D$116*Unit_Costs!$S$22+Assumptions!$E$116*Unit_Costs!$S$23+Assumptions!$F$116*Unit_Costs!$S$24+Assumptions!$G$116*Unit_Costs!$S$25+Assumptions!$H$116*Unit_Costs!$S$26+Assumptions!$I$116*Unit_Costs!$S$27+Assumptions!$J$116*Unit_Costs!$S$28+Assumptions!$K$116*Unit_Costs!$S$29)/E6) -> 1.0251114
A34: HIGH cost case
A35: Cost of included usage at 100% (£ / month) | B35: =Assumptions!$B$113*Unit_Costs!$Q$34+Assumptions!$C$113*Unit_Costs!$Q$35+Assumptions!$D$113*Unit_Costs!$Q$36+Assumptions!$E$113*Unit_Costs!$Q$37+Assumptions!$F$113*Unit_Costs!$Q$38+Assumptions!$G$113*Unit_Costs!$Q$39+Assumptions!$H$113*Unit_Costs!$Q$40+Assumptions!$I$113*Unit_Costs!$Q$41+Assumptions!$J$113*Unit_Costs!$Q$42+Assumptions!$K$113*Unit_Costs!$Q$43 -> 107.738 | C35: =Assumptions!$B$114*Unit_Costs!$Q$34+Assumptions!$C$114*Unit_Costs!$Q$35+Assumptions!$D$114*Unit_Costs!$Q$36+Assumptions!$E$114*Unit_Costs!$Q$37+Assumptions!$F$114*Unit_Costs!$Q$38+Assumptions!$G$114*Unit_Costs!$Q$39+Assumptions!$H$114*Unit_Costs!$Q$40+Assumptions!$I$114*Unit_Costs!$Q$41+Assumptions!$J$114*Unit_Costs!$Q$42+Assumptions!$K$114*Unit_Costs!$Q$43 -> 412.13378 | D35: =Assumptions!$B$115*Unit_Costs!$Q$34+Assumptions!$C$115*Unit_Costs!$Q$35+Assumptions!$D$115*Unit_Costs!$Q$36+Assumptions!$E$115*Unit_Costs!$Q$37+Assumptions!$F$115*Unit_Costs!$Q$38+Assumptions!$G$115*Unit_Costs!$Q$39+Assumptions!$H$115*Unit_Costs!$Q$40+Assumptions!$I$115*Unit_Costs!$Q$41+Assumptions!$J$115*Unit_Costs!$Q$42+Assumptions!$K$115*Unit_Costs!$Q$43 -> 771.55002 | E35: =Assumptions!$B$116*Unit_Costs!$Q$34+Assumptions!$C$116*Unit_Costs!$Q$35+Assumptions!$D$116*Unit_Costs!$Q$36+Assumptions!$E$116*Unit_Costs!$Q$37+Assumptions!$F$116*Unit_Costs!$Q$38+Assumptions!$G$116*Unit_Costs!$Q$39+Assumptions!$H$116*Unit_Costs!$Q$40+Assumptions!$I$116*Unit_Costs!$Q$41+Assumptions!$J$116*Unit_Costs!$Q$42+Assumptions!$K$116*Unit_Costs!$Q$43 -> 3271.8902
A36: Per-account fixed cost: hosting + SSO (£ / month) | B36: =Assumptions!$D$88*Unit_Costs!$Q$44+Assumptions!$D$92*Assumptions!$D$96*Assumptions!$D$6 -> 14.256665 | C36: =Assumptions!$D$89*Unit_Costs!$Q$44+Assumptions!$D$93*Assumptions!$D$96*Assumptions!$D$6 -> 71.283325 | D36: =Assumptions!$D$90*Unit_Costs!$Q$44+Assumptions!$D$94*Assumptions!$D$96*Assumptions!$D$6 -> 213.84998 | E36: =Assumptions!$D$91*Unit_Costs!$Q$44+Assumptions!$D$95*Assumptions!$D$96*Assumptions!$D$6 -> 807.20825
A37: Payment fees at list price (£ / month) | B37: =B5*Assumptions!$D$97+Assumptions!$D$101 -> 3.478 | C37: =C5*Assumptions!$D$98+Assumptions!$D$102 -> 11.178 | D37: =D5*Assumptions!$D$99+Assumptions!$D$103 -> 20.489 | E37: =E5*Assumptions!$D$100+Assumptions!$D$104 -> 59
A38: Gross margin at 100% of included usage | B38: =1-(B35+B36+B37)/B5 -> 0.1579016 | C38: =1-(C35+C36+C37)/C5 -> 0.008827446 | D38: =1-(D35+D36+D37)/D5 -> 0.32895998 | E38: =1-(E35+E36+E37)/E5 -> 0.1723803
A39: Gross margin at Base-scenario utilisation | B39: =1-(B35*Assumptions!$D$153+B36+B37)/B5 -> 0.41097743 | C39: =1-(C35*Assumptions!$D$153+C36+C37)/C5 -> 0.29789924 | D39: =1-(D35*Assumptions!$D$153+D36+D37)/D5 -> 0.50910841 | E39: =1-(E35*Assumptions!$D$153+E36+E37)/E5 -> 0.40141262
A40: Cost per credit (£) | B40: =IF(B6=0,0,B35/B6) -> 2.0718846 | C40: =IF(C6=0,0,C35/C6) -> 2.0202636 | D40: =IF(D6=0,0,D35/D6) -> 1.7377253 | E40: =IF(E6=0,0,E35/E6) -> 1.7459393
A41: Overage gross margin | B41: =IF(B8=0,0,1-B40/B8-Assumptions!$D$97) -> 0.46002886 | C41: =IF(C8=0,0,1-C40/C8-Assumptions!$D$98) -> 0.40078182 | D41: =IF(D8=0,0,1-D40/D8-Assumptions!$D$99) -> 0.40975824 | E41: =IF(E8=0,0,1-E40/E8-Assumptions!$D$100) -> 0.29062428
A42: Setup fee gross margin (onboarding labour) | B42: =IF(B9=0,0,1-Assumptions!$D$105*Assumptions!$D$109/B9) -> 0 | C42: =IF(C9=0,0,1-Assumptions!$D$106*Assumptions!$D$109/C9) -> 0.79 | D42: =IF(D9=0,0,1-Assumptions!$D$107*Assumptions!$D$109/D9) -> 0.81333333 | E42: =IF(E9=0,0,1-Assumptions!$D$108*Assumptions!$D$109/E9) -> 0.86
A43: Human minutes per credit | B43: =IF(B6=0,0,(Assumptions!$B$113*Unit_Costs!$S$34+Assumptions!$C$113*Unit_Costs!$S$35+Assumptions!$D$113*Unit_Costs!$S$36+Assumptions!$E$113*Unit_Costs!$S$37+Assumptions!$F$113*Unit_Costs!$S$38+Assumptions!$G$113*Unit_Costs!$S$39+Assumptions!$H$113*Unit_Costs!$S$40+Assumptions!$I$113*Unit_Costs!$S$41+Assumptions!$J$113*Unit_Costs!$S$42+Assumptions!$K$113*Unit_Costs!$S$43)/B6) -> 3.0480769 | C43: =IF(C6=0,0,(Assumptions!$B$114*Unit_Costs!$S$34+Assumptions!$C$114*Unit_Costs!$S$35+Assumptions!$D$114*Unit_Costs!$S$36+Assumptions!$E$114*Unit_Costs!$S$37+Assumptions!$F$114*Unit_Costs!$S$38+Assumptions!$G$114*Unit_Costs!$S$39+Assumptions!$H$114*Unit_Costs!$S$40+Assumptions!$I$114*Unit_Costs!$S$41+Assumptions!$J$114*Unit_Costs!$S$42+Assumptions!$K$114*Unit_Costs!$S$43)/C6) -> 2.7777778 | D43: =IF(D6=0,0,(Assumptions!$B$115*Unit_Costs!$S$34+Assumptions!$C$115*Unit_Costs!$S$35+Assumptions!$D$115*Unit_Costs!$S$36+Assumptions!$E$115*Unit_Costs!$S$37+Assumptions!$F$115*Unit_Costs!$S$38+Assumptions!$G$115*Unit_Costs!$S$39+Assumptions!$H$115*Unit_Costs!$S$40+Assumptions!$I$115*Unit_Costs!$S$41+Assumptions!$J$115*Unit_Costs!$S$42+Assumptions!$K$115*Unit_Costs!$S$43)/D6) -> 1.6546547 | E43: =IF(E6=0,0,(Assumptions!$B$116*Unit_Costs!$S$34+Assumptions!$C$116*Unit_Costs!$S$35+Assumptions!$D$116*Unit_Costs!$S$36+Assumptions!$E$116*Unit_Costs!$S$37+Assumptions!$F$116*Unit_Costs!$S$38+Assumptions!$G$116*Unit_Costs!$S$39+Assumptions!$H$116*Unit_Costs!$S$40+Assumptions!$I$116*Unit_Costs!$S$41+Assumptions!$J$116*Unit_Costs!$S$42+Assumptions!$K$116*Unit_Costs!$S$43)/E6) -> 1.5295269
A45: Per-development fee economics (extra development = 50-unit, 6 plan types)
A46: Fee charged (£) = plan types x £ per plan type | B46: =Assumptions!$D$48*Assumptions!$D$87 -> 2100
A47: Delivery cost (£), LOW case | B47: =Unit_Costs!$Q$14 -> 252.65042 | C47: =IF($B$46=0,0,1-B47/$B$46-Assumptions!$D$99) -> 0.86869028 | D47: ← gross margin
A48: Delivery cost (£), BASE case | B48: =Unit_Costs!$Q$28 -> 870.6056 | C48: =IF($B$46=0,0,1-B48/$B$46-Assumptions!$D$99) -> 0.5744259 | D48: ← gross margin
A49: Delivery cost (£), HIGH case | B49: =Unit_Costs!$Q$42 -> 1910.9102 | C49: =IF($B$46=0,0,1-B49/$B$46-Assumptions!$D$99) -> 0.079042761 | D49: ← gross margin
A51: B. Hypothesis price points evaluated against the tier usage mix (gross margin at 100% included usage / at Base utilisation)
A52: Hypothesis | B52: Price £/mo | C52: Usage mix | D52: GM @100% Base cost | E52: GM @100% High cost | F52: GM @util Base cost | G52: GM @util High cost
A53: Studio £149 | B53: =Assumptions!$D$73 -> 149 | C53: Studio | D53: =1-(B25+B26+B53*Assumptions!$D$97+Assumptions!$D$101)/B53 -> 0.57905985 | E53: =1-(B35+B36+B53*Assumptions!$D$97+Assumptions!$D$101)/B53 -> 0.1579016 | F53: =1-(B25*Assumptions!$D$153+B26+B53*Assumptions!$D$97+Assumptions!$D$101)/B53 -> 0.71153305 | G53: =1-(B35*Assumptions!$D$153+B36+B53*Assumptions!$D$97+Assumptions!$D$101)/B53 -> 0.41097743
A54: Agency £499 | B54: =Assumptions!$D$74 -> 499 | C54: Agency | D54: =1-(C25+C26+B54*Assumptions!$D$98+Assumptions!$D$102)/B54 -> 0.53728607 | E54: =1-(C35+C36+B54*Assumptions!$D$98+Assumptions!$D$102)/B54 -> 0.008827446 | F54: =1-(C25*Assumptions!$D$153+C26+B54*Assumptions!$D$98+Assumptions!$D$102)/B54 -> 0.68141348 | G54: =1-(C35*Assumptions!$D$153+C36+B54*Assumptions!$D$98+Assumptions!$D$102)/B54 -> 0.29789924
A55: Developer Pro £1,499 | B55: =Assumptions!$D$75 -> 1499 | C55: Developer Pro | D55: =1-(D25+D26+B55*Assumptions!$D$99+Assumptions!$D$103)/B55 -> 0.72527393 | E55: =1-(D35+D36+B55*Assumptions!$D$99+Assumptions!$D$103)/B55 -> 0.32895998 | F55: =1-(D25*Assumptions!$D$153+D26+B55*Assumptions!$D$99+Assumptions!$D$103)/B55 -> 0.80667523 | G55: =1-(D35*Assumptions!$D$153+D36+B55*Assumptions!$D$99+Assumptions!$D$103)/B55 -> 0.50910841
A56: Enterprise £3k | B56: =Assumptions!$D$77 -> 3000 | C56: Enterprise | D56: =1-(E25+E26+B56*Assumptions!$D$100+Assumptions!$D$104)/B56 -> 0.41853943 | E56: =1-(E35+E36+B56*Assumptions!$D$100+Assumptions!$D$104)/B56 -> -0.37203283 | F56: =1-(E25*Assumptions!$D$153+E26+B56*Assumptions!$D$100+Assumptions!$D$104)/B56 -> 0.59011984 | G56: =1-(E35*Assumptions!$D$153+E36+B56*Assumptions!$D$100+Assumptions!$D$104)/B56 -> 0.0096877
A57: Enterprise £5k | B57: =Assumptions!$D$76 -> 5000 | C57: Enterprise | D57: =1-(E25+E26+B57*Assumptions!$D$100+Assumptions!$D$104)/B57 -> 0.64672366 | E57: =1-(E35+E36+B57*Assumptions!$D$100+Assumptions!$D$104)/B57 -> 0.1723803 | F57: =1-(E25*Assumptions!$D$153+E26+B57*Assumptions!$D$100+Assumptions!$D$104)/B57 -> 0.7496719 | G57: =1-(E35*Assumptions!$D$153+E36+B57*Assumptions!$D$100+Assumptions!$D$104)/B57 -> 0.40141262
A58: Enterprise £10k | B58: =Assumptions!$D$78 -> 10000 | C58: Enterprise | D58: =1-(E25+E26+B58*Assumptions!$D$100+Assumptions!$D$104)/B58 -> 0.81786183 | E58: =1-(E35+E36+B58*Assumptions!$D$100+Assumptions!$D$104)/B58 -> 0.58069015 | F58: =1-(E25*Assumptions!$D$153+E26+B58*Assumptions!$D$100+Assumptions!$D$104)/B58 -> 0.86933595 | G58: =1-(E35*Assumptions!$D$153+E36+B58*Assumptions!$D$100+Assumptions!$D$104)/B58 -> 0.69520631
A60: C. Price required for target gross margin (price = (cost + fixed payment fee) / (1 − GM − payment %))
A61: Target gross margin → | B61: 0.6 | C61: 0.7 | D61: 0.8 | E61: 0.85 | F61: =B61 -> 0.6 | G61: =C61 -> 0.7 | H61: =D61 -> 0.8 | I61: =E61 -> 0.85
A62: Item | B62: Base cost £ | C62: Base cost £ | D62: Base cost £ | E62: Base cost £ | F62: High cost £ | G62: High cost £ | H62: High cost £ | I62: High cost £
A63: Subscription tiers at 100% of included usage (£ / month)
A64: Studio | B64: =(B$25+B$26+Assumptions!$D$101)/(1-B$61-Assumptions!$D$97) -> 157.25418 | C64: =(B$25+B$26+Assumptions!$D$101)/(1-C$61-Assumptions!$D$97) -> 213.82044 | D64: =(B$25+B$26+Assumptions!$D$101)/(1-D$61-Assumptions!$D$97) -> 333.94428 | E64: =(B$25+B$26+Assumptions!$D$101)/(1-E$61-Assumptions!$D$97) -> 464.39126 | F64: =(B$35+B$36+Assumptions!$D$101)/(1-F$61-Assumptions!$D$97) -> 323.2663 | G64: =(B$35+B$36+Assumptions!$D$101)/(1-G$61-Assumptions!$D$97) -> 439.54914 | H64: =(B$35+B$36+Assumptions!$D$101)/(1-H$61-Assumptions!$D$97) -> 686.48686 | I64: =(B$35+B$36+Assumptions!$D$101)/(1-I$61-Assumptions!$D$97) -> 954.64579
A65: Agency | B65: =(C$25+C$26+Assumptions!$D$102)/(1-B$61-Assumptions!$D$98) -> 581.78902 | C65: =(C$25+C$26+Assumptions!$D$102)/(1-C$61-Assumptions!$D$98) -> 791.06565 | D65: =(C$25+C$26+Assumptions!$D$102)/(1-D$61-Assumptions!$D$98) -> 1235.4846 | E65: =(C$25+C$26+Assumptions!$D$102)/(1-E$61-Assumptions!$D$98) -> 1718.0957 | F65: =(C$35+C$36+Assumptions!$D$102)/(1-F$61-Assumptions!$D$98) -> 1279.4103 | G65: =(C$35+C$36+Assumptions!$D$102)/(1-G$61-Assumptions!$D$98) -> 1739.6299 | H65: =(C$35+C$36+Assumptions!$D$102)/(1-H$61-Assumptions!$D$98) -> 2716.95 | I65: =(C$35+C$36+Assumptions!$D$102)/(1-I$61-Assumptions!$D$98) -> 3778.2586
A66: Developer Pro | B66: =(D$25+D$26+Assumptions!$D$103)/(1-B$61-Assumptions!$D$99) -> 1016.2606 | C66: =(D$25+D$26+Assumptions!$D$103)/(1-C$61-Assumptions!$D$99) -> 1367.9079 | D66: =(D$25+D$26+Assumptions!$D$103)/(1-D$61-Assumptions!$D$99) -> 2091.6687 | E66: =(D$25+D$26+Assumptions!$D$103)/(1-E$61-Assumptions!$D$99) -> 2844.0675 | F66: =(D$35+D$36+Assumptions!$D$103)/(1-F$61-Assumptions!$D$99) -> 2543.4447 | G66: =(D$35+D$36+Assumptions!$D$103)/(1-G$61-Assumptions!$D$99) -> 3423.5294 | H66: =(D$35+D$36+Assumptions!$D$103)/(1-H$61-Assumptions!$D$99) -> 5234.9206 | I66: =(D$35+D$36+Assumptions!$D$103)/(1-I$61-Assumptions!$D$99) -> 7117.9856
A67: Enterprise | B67: =(E$25+E$26+Assumptions!$D$104)/(1-B$61-Assumptions!$D$100) -> 4399.4389 | C67: =(E$25+E$26+Assumptions!$D$104)/(1-C$61-Assumptions!$D$100) -> 5921.7361 | D67: =(E$25+E$26+Assumptions!$D$104)/(1-D$61-Assumptions!$D$100) -> 9054.9297 | E67: =(E$25+E$26+Assumptions!$D$104)/(1-E$61-Assumptions!$D$100) -> 12312.099 | F67: =(E$35+E$36+Assumptions!$D$104)/(1-F$61-Assumptions!$D$100) -> 10496.397 | G67: =(E$35+E$36+Assumptions!$D$104)/(1-G$61-Assumptions!$D$100) -> 14128.368 | H67: =(E$35+E$36+Assumptions!$D$104)/(1-H$61-Assumptions!$D$100) -> 21603.696 | I67: =(E$35+E$36+Assumptions!$D$104)/(1-I$61-Assumptions!$D$100) -> 29374.809
A68: One-off deliverables / per-development pricing (£ each, card payment)
A69: Single room image | B69: =(Unit_Costs!$Q$20+Assumptions!$D$101)/(1-B$61-Assumptions!$D$97) -> 14.785238 | C69: =(Unit_Costs!$Q$20+Assumptions!$D$101)/(1-C$61-Assumptions!$D$97) -> 20.103669 | D69: =(Unit_Costs!$Q$20+Assumptions!$D$101)/(1-D$61-Assumptions!$D$97) -> 31.397865 | E69: =(Unit_Costs!$Q$20+Assumptions!$D$101)/(1-E$61-Assumptions!$D$97) -> 43.662655 | F69: =(Unit_Costs!$Q$34+Assumptions!$D$101)/(1-F$61-Assumptions!$D$97) -> 29.126556 | G69: =(Unit_Costs!$Q$34+Assumptions!$D$101)/(1-G$61-Assumptions!$D$97) -> 39.603735 | H69: =(Unit_Costs!$Q$34+Assumptions!$D$101)/(1-H$61-Assumptions!$D$97) -> 61.853024 | I69: =(Unit_Costs!$Q$34+Assumptions!$D$101)/(1-I$61-Assumptions!$D$97) -> 86.014362
A70: 5 room images | B70: =(Unit_Costs!$Q$21+Assumptions!$D$101)/(1-B$61-Assumptions!$D$97) -> 29.26594 | C70: =(Unit_Costs!$Q$21+Assumptions!$D$101)/(1-C$61-Assumptions!$D$97) -> 39.793257 | D70: =(Unit_Costs!$Q$21+Assumptions!$D$101)/(1-D$61-Assumptions!$D$97) -> 62.14902 | E70: =(Unit_Costs!$Q$21+Assumptions!$D$101)/(1-E$61-Assumptions!$D$97) -> 86.42598 | F70: =(Unit_Costs!$Q$35+Assumptions!$D$101)/(1-F$61-Assumptions!$D$97) -> 55.72111 | G70: =(Unit_Costs!$Q$35+Assumptions!$D$101)/(1-G$61-Assumptions!$D$97) -> 75.764674 | H70: =(Unit_Costs!$Q$35+Assumptions!$D$101)/(1-H$61-Assumptions!$D$97) -> 118.3291 | I70: =(Unit_Costs!$Q$35+Assumptions!$D$101)/(1-I$61-Assumptions!$D$97) -> 164.5514
A71: 2-bed flat (8 images + plan) | B71: =(Unit_Costs!$Q$22+Assumptions!$D$101)/(1-B$61-Assumptions!$D$97) -> 43.433058 | C71: =(Unit_Costs!$Q$22+Assumptions!$D$101)/(1-C$61-Assumptions!$D$97) -> 59.056461 | D71: =(Unit_Costs!$Q$22+Assumptions!$D$101)/(1-D$61-Assumptions!$D$97) -> 92.234248 | E71: =(Unit_Costs!$Q$22+Assumptions!$D$101)/(1-E$61-Assumptions!$D$97) -> 128.26325 | F71: =(Unit_Costs!$Q$36+Assumptions!$D$101)/(1-F$61-Assumptions!$D$97) -> 82.148773 | G71: =(Unit_Costs!$Q$36+Assumptions!$D$101)/(1-G$61-Assumptions!$D$97) -> 111.69869 | H71: =(Unit_Costs!$Q$36+Assumptions!$D$101)/(1-H$61-Assumptions!$D$97) -> 174.45076 | I71: =(Unit_Costs!$Q$36+Assumptions!$D$101)/(1-I$61-Assumptions!$D$97) -> 242.59559
A72: 4-bed house (19 images, 2 floors) | B72: =(Unit_Costs!$Q$23+Assumptions!$D$101)/(1-B$61-Assumptions!$D$97) -> 92.564063 | C72: =(Unit_Costs!$Q$23+Assumptions!$D$101)/(1-C$61-Assumptions!$D$97) -> 125.86049 | D72: =(Unit_Costs!$Q$23+Assumptions!$D$101)/(1-D$61-Assumptions!$D$97) -> 196.56863 | E72: =(Unit_Costs!$Q$23+Assumptions!$D$101)/(1-E$61-Assumptions!$D$97) -> 273.35325 | F72: =(Unit_Costs!$Q$37+Assumptions!$D$101)/(1-F$61-Assumptions!$D$97) -> 175.33313 | G72: =(Unit_Costs!$Q$37+Assumptions!$D$101)/(1-G$61-Assumptions!$D$97) -> 238.4026 | H72: =(Unit_Costs!$Q$37+Assumptions!$D$101)/(1-H$61-Assumptions!$D$97) -> 372.33664 | I72: =(Unit_Costs!$Q$37+Assumptions!$D$101)/(1-I$61-Assumptions!$D$97) -> 517.78064
A73: Interactive 3D property (WebGL tour, 1st month hosting) | B73: =(Unit_Costs!$Q$24+Assumptions!$D$101)/(1-B$61-Assumptions!$D$97) -> 45.296081 | C73: =(Unit_Costs!$Q$24+Assumptions!$D$101)/(1-C$61-Assumptions!$D$97) -> 61.589635 | D73: =(Unit_Costs!$Q$24+Assumptions!$D$101)/(1-D$61-Assumptions!$D$97) -> 96.190554 | E73: =(Unit_Costs!$Q$24+Assumptions!$D$101)/(1-E$61-Assumptions!$D$97) -> 133.76499 | F73: =(Unit_Costs!$Q$38+Assumptions!$D$101)/(1-F$61-Assumptions!$D$97) -> 109.13126 | G73: =(Unit_Costs!$Q$38+Assumptions!$D$101)/(1-G$61-Assumptions!$D$97) -> 148.3871 | H73: =(Unit_Costs!$Q$38+Assumptions!$D$101)/(1-H$61-Assumptions!$D$97) -> 231.75065 | I73: =(Unit_Costs!$Q$38+Assumptions!$D$101)/(1-I$61-Assumptions!$D$97) -> 322.27824
A74: 30s walkthrough video | B74: =(Unit_Costs!$Q$25+Assumptions!$D$101)/(1-B$61-Assumptions!$D$97) -> 43.370788 | C74: =(Unit_Costs!$Q$25+Assumptions!$D$101)/(1-C$61-Assumptions!$D$97) -> 58.971791 | D74: =(Unit_Costs!$Q$25+Assumptions!$D$101)/(1-D$61-Assumptions!$D$97) -> 92.10201 | E74: =(Unit_Costs!$Q$25+Assumptions!$D$101)/(1-E$61-Assumptions!$D$97) -> 128.07936 | F74: =(Unit_Costs!$Q$39+Assumptions!$D$101)/(1-F$61-Assumptions!$D$97) -> 98.143144 | G74: =(Unit_Costs!$Q$39+Assumptions!$D$101)/(1-G$61-Assumptions!$D$97) -> 133.44643 | H74: =(Unit_Costs!$Q$39+Assumptions!$D$101)/(1-H$61-Assumptions!$D$97) -> 208.41634 | I74: =(Unit_Costs!$Q$39+Assumptions!$D$101)/(1-I$61-Assumptions!$D$97) -> 289.82897
A75: 60s cinematic video | B75: =(Unit_Costs!$Q$26+Assumptions!$D$101)/(1-B$61-Assumptions!$D$97) -> 143.80012 | C75: =(Unit_Costs!$Q$26+Assumptions!$D$101)/(1-C$61-Assumptions!$D$97) -> 195.52678 | D75: =(Unit_Costs!$Q$26+Assumptions!$D$101)/(1-D$61-Assumptions!$D$97) -> 305.37329 | E75: =(Unit_Costs!$Q$26+Assumptions!$D$101)/(1-E$61-Assumptions!$D$97) -> 424.65973 | F75: =(Unit_Costs!$Q$40+Assumptions!$D$101)/(1-F$61-Assumptions!$D$97) -> 355.97165 | G75: =(Unit_Costs!$Q$40+Assumptions!$D$101)/(1-G$61-Assumptions!$D$97) -> 484.019 | H75: =(Unit_Costs!$Q$40+Assumptions!$D$101)/(1-H$61-Assumptions!$D$97) -> 755.93979 | I75: =(Unit_Costs!$Q$40+Assumptions!$D$101)/(1-I$61-Assumptions!$D$97) -> 1051.2288
A76: Developer marketing package (per house type) | B76: =(Unit_Costs!$Q$27+Assumptions!$D$101)/(1-B$61-Assumptions!$D$97) -> 302.49464 | C76: =(Unit_Costs!$Q$27+Assumptions!$D$101)/(1-C$61-Assumptions!$D$97) -> 411.30566 | D76: =(Unit_Costs!$Q$27+Assumptions!$D$101)/(1-D$61-Assumptions!$D$97) -> 642.37625 | E76: =(Unit_Costs!$Q$27+Assumptions!$D$101)/(1-E$61-Assumptions!$D$97) -> 893.30447 | F76: =(Unit_Costs!$Q$41+Assumptions!$D$101)/(1-F$61-Assumptions!$D$97) -> 683.39065 | G76: =(Unit_Costs!$Q$41+Assumptions!$D$101)/(1-G$61-Assumptions!$D$97) -> 929.21462 | H76: =(Unit_Costs!$Q$41+Assumptions!$D$101)/(1-H$61-Assumptions!$D$97) -> 1451.2453 | I76: =(Unit_Costs!$Q$41+Assumptions!$D$101)/(1-I$61-Assumptions!$D$97) -> 2018.138
A77: 50-unit development (6 plan types) | B77: =(Unit_Costs!$Q$28+Assumptions!$D$101)/(1-B$61-Assumptions!$D$97) -> 2303.7185 | C77: =(Unit_Costs!$Q$28+Assumptions!$D$101)/(1-C$61-Assumptions!$D$97) -> 3132.3942 | D77: =(Unit_Costs!$Q$28+Assumptions!$D$101)/(1-D$61-Assumptions!$D$97) -> 4892.1663 | E77: =(Unit_Costs!$Q$28+Assumptions!$D$101)/(1-E$61-Assumptions!$D$97) -> 6803.1687 | F77: =(Unit_Costs!$Q$42+Assumptions!$D$101)/(1-F$61-Assumptions!$D$97) -> 5055.8471 | G77: =(Unit_Costs!$Q$42+Assumptions!$D$101)/(1-G$61-Assumptions!$D$97) -> 6874.4971 | H77: =(Unit_Costs!$Q$42+Assumptions!$D$101)/(1-H$61-Assumptions!$D$97) -> 10736.574 | I77: =(Unit_Costs!$Q$42+Assumptions!$D$101)/(1-I$61-Assumptions!$D$97) -> 14930.548
A78: 200-unit development (15 plan types) | B78: =(Unit_Costs!$Q$29+Assumptions!$D$101)/(1-B$61-Assumptions!$D$97) -> 6333.9522 | C78: =(Unit_Costs!$Q$29+Assumptions!$D$101)/(1-C$61-Assumptions!$D$97) -> 8612.3523 | D78: =(Unit_Costs!$Q$29+Assumptions!$D$101)/(1-D$61-Assumptions!$D$97) -> 13450.752 | E78: =(Unit_Costs!$Q$29+Assumptions!$D$101)/(1-E$61-Assumptions!$D$97) -> 18704.953 | F78: =(Unit_Costs!$Q$43+Assumptions!$D$101)/(1-F$61-Assumptions!$D$97) -> 13789.407 | G78: =(Unit_Costs!$Q$43+Assumptions!$D$101)/(1-G$61-Assumptions!$D$97) -> 18749.625 | H78: =(Unit_Costs!$Q$43+Assumptions!$D$101)/(1-H$61-Assumptions!$D$97) -> 29283.122 | I78: =(Unit_Costs!$Q$43+Assumptions!$D$101)/(1-I$61-Assumptions!$D$97) -> 40721.842
A80: Recommendation (see financial_model_summary.md): keep the £149 / £499 / £1,499 / £5k+ anchors but sell CREDITS, not 'unlimited'. Every geometry-true output needs a human 2D confirm per plan, so a single-image order is labour-dominated: charge per plan conversion inside the credit price.
A81: Overages are priced above the effective included-credit price; setup fees cover onboarding labour; developments beyond the first are billed per plan type, because delivery cost scales with plan types, not units.
A82: Pixel streaming is the margin risk for interactive tours: default to WebGL/three.js viewers (pricing_inputs §6) and charge for streamed tours separately.

Sheet Model_Bear
A1: Model Bear scenario — monthly model, 36 months (£). All cells are formulas driven by Assumptions column C.
A3: Month | B3: Unit | C3: 1 | D3: 2 | E3: 3 | F3: 4 | G3: 5 | H3: 6 | I3: 7 | J3: 8 | K3: 9 | L3: 10 | M3: 11 | N3: 12 | O3: 13 | P3: 14 | Q3: 15 | R3: 16 | S3: 17 | T3: 18 | U3: 19 | V3: 20 | W3: 21 | X3: 22 | Y3: 23 | Z3: 24 | AA3: 25 | AB3: 26 | AC3: 27 | AD3: 28 | AE3: 29 | AF3: 30 | AG3: 31 | AH3: 32 | AI3: 33 | AJ3: 34 | AK3: 35 | AL3: 36
A4: Year | C4: ="Y"&ROUNDUP(C$3/12,0) -> Y1 | D4: ="Y"&ROUNDUP(D$3/12,0) -> Y1 | E4: ="Y"&ROUNDUP(E$3/12,0) -> Y1 | F4: ="Y"&ROUNDUP(F$3/12,0) -> Y1 | G4: ="Y"&ROUNDUP(G$3/12,0) -> Y1 | H4: ="Y"&ROUNDUP(H$3/12,0) -> Y1 | I4: ="Y"&ROUNDUP(I$3/12,0) -> Y1 | J4: ="Y"&ROUNDUP(J$3/12,0) -> Y1 | ... AL4: ="Y"&ROUNDUP(AL$3/12,0) -> Y3
A6: Headcount (step functions; triggers evaluated on previous month)
A7: Customer support / QA lead #1 (1 = hired) | B7: flag | C7: =0 -> 0 | D7: =MAX(C7,IF(IF(Assumptions!$B$187="Customers",C36,C43)>=Assumptions!$C$187,1,0)) -> 0 | E7: =MAX(D7,IF(IF(Assumptions!$B$187="Customers",D36,D43)>=Assumptions!$C$187,1,0)) -> 0 | F7: =MAX(E7,IF(IF(Assumptions!$B$187="Customers",E36,E43)>=Assumptions!$C$187,1,0)) -> 0 | G7: =MAX(F7,IF(IF(Assumptions!$B$187="Customers",F36,F43)>=Assumptions!$C$187,1,0)) -> 0 | H7: =MAX(G7,IF(IF(Assumptions!$B$187="Customers",G36,G43)>=Assumptions!$C$187,1,0)) -> 0 | I7: =MAX(H7,IF(IF(Assumptions!$B$187="Customers",H36,H43)>=Assumptions!$C$187,1,0)) -> 0 | J7: =MAX(I7,IF(IF(Assumptions!$B$187="Customers",I36,I43)>=Assumptions!$C$187,1,0)) -> 0 | K7: =MAX(J7,IF(IF(Assumptions!$B$187="Customers",J36,J43)>=Assumptions!$C$187,1,0)) -> 0 | ... AL7: =MAX(AK7,IF(IF(Assumptions!$B$187="Customers",AK36,AK43)>=Assumptions!$C$187,1,0)) -> 1
A8: Senior engineer #1 (1 = hired) | B8: flag | C8: =0 -> 0 | D8: =MAX(C8,IF(IF(Assumptions!$B$188="Customers",C36,C43)>=Assumptions!$C$188,1,0)) -> 0 | E8: =MAX(D8,IF(IF(Assumptions!$B$188="Customers",D36,D43)>=Assumptions!$C$188,1,0)) -> 0 | F8: =MAX(E8,IF(IF(Assumptions!$B$188="Customers",E36,E43)>=Assumptions!$C$188,1,0)) -> 0 | G8: =MAX(F8,IF(IF(Assumptions!$B$188="Customers",F36,F43)>=Assumptions!$C$188,1,0)) -> 0 | H8: =MAX(G8,IF(IF(Assumptions!$B$188="Customers",G36,G43)>=Assumptions!$C$188,1,0)) -> 0 | I8: =MAX(H8,IF(IF(Assumptions!$B$188="Customers",H36,H43)>=Assumptions!$C$188,1,0)) -> 0 | J8: =MAX(I8,IF(IF(Assumptions!$B$188="Customers",I36,I43)>=Assumptions!$C$188,1,0)) -> 0 | K8: =MAX(J8,IF(IF(Assumptions!$B$188="Customers",J36,J43)>=Assumptions!$C$188,1,0)) -> 0 | ... AL8: =MAX(AK8,IF(IF(Assumptions!$B$188="Customers",AK36,AK43)>=Assumptions!$C$188,1,0)) -> 1
A9: Account executive #1 (developers) (1 = hired) | B9: flag | C9: =0 -> 0 | D9: =MAX(C9,IF(IF(Assumptions!$B$189="Customers",C36,C43)>=Assumptions!$C$189,1,0)) -> 0 | E9: =MAX(D9,IF(IF(Assumptions!$B$189="Customers",D36,D43)>=Assumptions!$C$189,1,0)) -> 0 | F9: =MAX(E9,IF(IF(Assumptions!$B$189="Customers",E36,E43)>=Assumptions!$C$189,1,0)) -> 0 | G9: =MAX(F9,IF(IF(Assumptions!$B$189="Customers",F36,F43)>=Assumptions!$C$189,1,0)) -> 0 | H9: =MAX(G9,IF(IF(Assumptions!$B$189="Customers",G36,G43)>=Assumptions!$C$189,1,0)) -> 0 | I9: =MAX(H9,IF(IF(Assumptions!$B$189="Customers",H36,H43)>=Assumptions!$C$189,1,0)) -> 0 | J9: =MAX(I9,IF(IF(Assumptions!$B$189="Customers",I36,I43)>=Assumptions!$C$189,1,0)) -> 0 | K9: =MAX(J9,IF(IF(Assumptions!$B$189="Customers",J36,J43)>=Assumptions!$C$189,1,0)) -> 0 | ... AL9: =MAX(AK9,IF(IF(Assumptions!$B$189="Customers",AK36,AK43)>=Assumptions!$C$189,1,0)) -> 0
A10: Founder salary uplift to market (1 = hired) | B10: flag | C10: =0 -> 0 | D10: =MAX(C10,IF(IF(Assumptions!$B$190="Customers",C36,C43)>=Assumptions!$C$190,1,0)) -> 0 | E10: =MAX(D10,IF(IF(Assumptions!$B$190="Customers",D36,D43)>=Assumptions!$C$190,1,0)) -> 0 | F10: =MAX(E10,IF(IF(Assumptions!$B$190="Customers",E36,E43)>=Assumptions!$C$190,1,0)) -> 0 | G10: =MAX(F10,IF(IF(Assumptions!$B$190="Customers",F36,F43)>=Assumptions!$C$190,1,0)) -> 0 | H10: =MAX(G10,IF(IF(Assumptions!$B$190="Customers",G36,G43)>=Assumptions!$C$190,1,0)) -> 0 | I10: =MAX(H10,IF(IF(Assumptions!$B$190="Customers",H36,H43)>=Assumptions!$C$190,1,0)) -> 0 | J10: =MAX(I10,IF(IF(Assumptions!$B$190="Customers",I36,I43)>=Assumptions!$C$190,1,0)) -> 0 | K10: =MAX(J10,IF(IF(Assumptions!$B$190="Customers",J36,J43)>=Assumptions!$C$190,1,0)) -> 0 | ... AL10: =MAX(AK10,IF(IF(Assumptions!$B$190="Customers",AK36,AK43)>=Assumptions!$C$190,1,0)) -> 0
A11: Senior engineer #2 (1 = hired) | B11: flag | C11: =0 -> 0 | D11: =MAX(C11,IF(IF(Assumptions!$B$191="Customers",C36,C43)>=Assumptions!$C$191,1,0)) -> 0 | E11: =MAX(D11,IF(IF(Assumptions!$B$191="Customers",D36,D43)>=Assumptions!$C$191,1,0)) -> 0 | F11: =MAX(E11,IF(IF(Assumptions!$B$191="Customers",E36,E43)>=Assumptions!$C$191,1,0)) -> 0 | G11: =MAX(F11,IF(IF(Assumptions!$B$191="Customers",F36,F43)>=Assumptions!$C$191,1,0)) -> 0 | H11: =MAX(G11,IF(IF(Assumptions!$B$191="Customers",G36,G43)>=Assumptions!$C$191,1,0)) -> 0 | I11: =MAX(H11,IF(IF(Assumptions!$B$191="Customers",H36,H43)>=Assumptions!$C$191,1,0)) -> 0 | J11: =MAX(I11,IF(IF(Assumptions!$B$191="Customers",I36,I43)>=Assumptions!$C$191,1,0)) -> 0 | K11: =MAX(J11,IF(IF(Assumptions!$B$191="Customers",J36,J43)>=Assumptions!$C$191,1,0)) -> 0 | ... AL11: =MAX(AK11,IF(IF(Assumptions!$B$191="Customers",AK36,AK43)>=Assumptions!$C$191,1,0)) -> 0
A12: Customer success #2 (1 = hired) | B12: flag | C12: =0 -> 0 | D12: =MAX(C12,IF(IF(Assumptions!$B$192="Customers",C36,C43)>=Assumptions!$C$192,1,0)) -> 0 | E12: =MAX(D12,IF(IF(Assumptions!$B$192="Customers",D36,D43)>=Assumptions!$C$192,1,0)) -> 0 | F12: =MAX(E12,IF(IF(Assumptions!$B$192="Customers",E36,E43)>=Assumptions!$C$192,1,0)) -> 0 | G12: =MAX(F12,IF(IF(Assumptions!$B$192="Customers",F36,F43)>=Assumptions!$C$192,1,0)) -> 0 | H12: =MAX(G12,IF(IF(Assumptions!$B$192="Customers",G36,G43)>=Assumptions!$C$192,1,0)) -> 0 | I12: =MAX(H12,IF(IF(Assumptions!$B$192="Customers",H36,H43)>=Assumptions!$C$192,1,0)) -> 0 | J12: =MAX(I12,IF(IF(Assumptions!$B$192="Customers",I36,I43)>=Assumptions!$C$192,1,0)) -> 0 | K12: =MAX(J12,IF(IF(Assumptions!$B$192="Customers",J36,J43)>=Assumptions!$C$192,1,0)) -> 0 | ... AL12: =MAX(AK12,IF(IF(Assumptions!$B$192="Customers",AK36,AK43)>=Assumptions!$C$192,1,0)) -> 0
A13: Marketing manager (1 = hired) | B13: flag | C13: =0 -> 0 | D13: =MAX(C13,IF(IF(Assumptions!$B$193="Customers",C36,C43)>=Assumptions!$C$193,1,0)) -> 0 | E13: =MAX(D13,IF(IF(Assumptions!$B$193="Customers",D36,D43)>=Assumptions!$C$193,1,0)) -> 0 | F13: =MAX(E13,IF(IF(Assumptions!$B$193="Customers",E36,E43)>=Assumptions!$C$193,1,0)) -> 0 | G13: =MAX(F13,IF(IF(Assumptions!$B$193="Customers",F36,F43)>=Assumptions!$C$193,1,0)) -> 0 | H13: =MAX(G13,IF(IF(Assumptions!$B$193="Customers",G36,G43)>=Assumptions!$C$193,1,0)) -> 0 | I13: =MAX(H13,IF(IF(Assumptions!$B$193="Customers",H36,H43)>=Assumptions!$C$193,1,0)) -> 0 | J13: =MAX(I13,IF(IF(Assumptions!$B$193="Customers",I36,I43)>=Assumptions!$C$193,1,0)) -> 0 | K13: =MAX(J13,IF(IF(Assumptions!$B$193="Customers",J36,J43)>=Assumptions!$C$193,1,0)) -> 0 | ... AL13: =MAX(AK13,IF(IF(Assumptions!$B$193="Customers",AK36,AK43)>=Assumptions!$C$193,1,0)) -> 0
A14: Account executive #2 (1 = hired) | B14: flag | C14: =0 -> 0 | D14: =MAX(C14,IF(IF(Assumptions!$B$194="Customers",C36,C43)>=Assumptions!$C$194,1,0)) -> 0 | E14: =MAX(D14,IF(IF(Assumptions!$B$194="Customers",D36,D43)>=Assumptions!$C$194,1,0)) -> 0 | F14: =MAX(E14,IF(IF(Assumptions!$B$194="Customers",E36,E43)>=Assumptions!$C$194,1,0)) -> 0 | G14: =MAX(F14,IF(IF(Assumptions!$B$194="Customers",F36,F43)>=Assumptions!$C$194,1,0)) -> 0 | H14: =MAX(G14,IF(IF(Assumptions!$B$194="Customers",G36,G43)>=Assumptions!$C$194,1,0)) -> 0 | I14: =MAX(H14,IF(IF(Assumptions!$B$194="Customers",H36,H43)>=Assumptions!$C$194,1,0)) -> 0 | J14: =MAX(I14,IF(IF(Assumptions!$B$194="Customers",I36,I43)>=Assumptions!$C$194,1,0)) -> 0 | K14: =MAX(J14,IF(IF(Assumptions!$B$194="Customers",J36,J43)>=Assumptions!$C$194,1,0)) -> 0 | ... AL14: =MAX(AK14,IF(IF(Assumptions!$B$194="Customers",AK36,AK43)>=Assumptions!$C$194,1,0)) -> 0
A15: Graphics / 3D engineer #3 (1 = hired) | B15: flag | C15: =0 -> 0 | D15: =MAX(C15,IF(IF(Assumptions!$B$195="Customers",C36,C43)>=Assumptions!$C$195,1,0)) -> 0 | E15: =MAX(D15,IF(IF(Assumptions!$B$195="Customers",D36,D43)>=Assumptions!$C$195,1,0)) -> 0 | F15: =MAX(E15,IF(IF(Assumptions!$B$195="Customers",E36,E43)>=Assumptions!$C$195,1,0)) -> 0 | G15: =MAX(F15,IF(IF(Assumptions!$B$195="Customers",F36,F43)>=Assumptions!$C$195,1,0)) -> 0 | H15: =MAX(G15,IF(IF(Assumptions!$B$195="Customers",G36,G43)>=Assumptions!$C$195,1,0)) -> 0 | I15: =MAX(H15,IF(IF(Assumptions!$B$195="Customers",H36,H43)>=Assumptions!$C$195,1,0)) -> 0 | J15: =MAX(I15,IF(IF(Assumptions!$B$195="Customers",I36,I43)>=Assumptions!$C$195,1,0)) -> 0 | K15: =MAX(J15,IF(IF(Assumptions!$B$195="Customers",J36,J43)>=Assumptions!$C$195,1,0)) -> 0 | ... AL15: =MAX(AK15,IF(IF(Assumptions!$B$195="Customers",AK36,AK43)>=Assumptions!$C$195,1,0)) -> 0
A16: Customer success #3 (1 = hired) | B16: flag | C16: =0 -> 0 | D16: =MAX(C16,IF(IF(Assumptions!$B$196="Customers",C36,C43)>=Assumptions!$C$196,1,0)) -> 0 | E16: =MAX(D16,IF(IF(Assumptions!$B$196="Customers",D36,D43)>=Assumptions!$C$196,1,0)) -> 0 | F16: =MAX(E16,IF(IF(Assumptions!$B$196="Customers",E36,E43)>=Assumptions!$C$196,1,0)) -> 0 | G16: =MAX(F16,IF(IF(Assumptions!$B$196="Customers",F36,F43)>=Assumptions!$C$196,1,0)) -> 0 | H16: =MAX(G16,IF(IF(Assumptions!$B$196="Customers",G36,G43)>=Assumptions!$C$196,1,0)) -> 0 | I16: =MAX(H16,IF(IF(Assumptions!$B$196="Customers",H36,H43)>=Assumptions!$C$196,1,0)) -> 0 | J16: =MAX(I16,IF(IF(Assumptions!$B$196="Customers",I36,I43)>=Assumptions!$C$196,1,0)) -> 0 | K16: =MAX(J16,IF(IF(Assumptions!$B$196="Customers",J36,J43)>=Assumptions!$C$196,1,0)) -> 0 | ... AL16: =MAX(AK16,IF(IF(Assumptions!$B$196="Customers",AK36,AK43)>=Assumptions!$C$196,1,0)) -> 0
A17: Total headcount incl. founder | B17: FTE | C17: =1+C7+C8+C9+C11+C12+C13+C14+C15+C16 -> 1 | D17: =1+D7+D8+D9+D11+D12+D13+D14+D15+D16 -> 1 | E17: =1+E7+E8+E9+E11+E12+E13+E14+E15+E16 -> 1 | F17: =1+F7+F8+F9+F11+F12+F13+F14+F15+F16 -> 1 | G17: =1+G7+G8+G9+G11+G12+G13+G14+G15+G16 -> 1 | H17: =1+H7+H8+H9+H11+H12+H13+H14+H15+H16 -> 1 | I17: =1+I7+I8+I9+I11+I12+I13+I14+I15+I16 -> 1 | J17: =1+J7+J8+J9+J11+J12+J13+J14+J15+J16 -> 1 | ... AL17: =1+AL7+AL8+AL9+AL11+AL12+AL13+AL14+AL15+AL16 -> 3
A18: Account executives in seat | B18: FTE | C18: =C9+C14 -> 0 | D18: =D9+D14 -> 0 | E18: =E9+E14 -> 0 | F18: =F9+F14 -> 0 | G18: =G9+G14 -> 0 | H18: =H9+H14 -> 0 | I18: =I9+I14 -> 0 | J18: =J9+J14 -> 0 | ... AL18: =AL9+AL14 -> 0
A19: Productive AEs (in seat ≥ ramp months) | B19: FTE | C19: =IF(C$3>Assumptions!$C$140,OFFSET(C18,0,-Assumptions!$C$140),0) -> 0 | D19: =IF(D$3>Assumptions!$C$140,OFFSET(D18,0,-Assumptions!$C$140),0) -> 0 | E19: =IF(E$3>Assumptions!$C$140,OFFSET(E18,0,-Assumptions!$C$140),0) -> 0 | F19: =IF(F$3>Assumptions!$C$140,OFFSET(F18,0,-Assumptions!$C$140),0) -> 0 | G19: =IF(G$3>Assumptions!$C$140,OFFSET(G18,0,-Assumptions!$C$140),0) -> 0 | H19: =IF(H$3>Assumptions!$C$140,OFFSET(H18,0,-Assumptions!$C$140),0) -> 0 | I19: =IF(I$3>Assumptions!$C$140,OFFSET(I18,0,-Assumptions!$C$140),0) -> 0 | J19: =IF(J$3>Assumptions!$C$140,OFFSET(J18,0,-Assumptions!$C$140),0) -> 0 | ... AL19: =IF(AL$3>Assumptions!$C$140,OFFSET(AL18,0,-Assumptions!$C$140),0) -> 0
A21: Customers
A22: New customers — Studio | B22: logos | C22: =IF(C$3<Assumptions!$C$122,0,MIN(Assumptions!$C$134,Assumptions!$C$126+Assumptions!$C$130*(C$3-Assumptions!$C$122))) -> 0 | D22: =IF(D$3<Assumptions!$C$122,0,MIN(Assumptions!$C$134,Assumptions!$C$126+Assumptions!$C$130*(D$3-Assumptions!$C$122))) -> 0 | E22: =IF(E$3<Assumptions!$C$122,0,MIN(Assumptions!$C$134,Assumptions!$C$126+Assumptions!$C$130*(E$3-Assumptions!$C$122))) -> 0 | F22: =IF(F$3<Assumptions!$C$122,0,MIN(Assumptions!$C$134,Assumptions!$C$126+Assumptions!$C$130*(F$3-Assumptions!$C$122))) -> 0 | G22: =IF(G$3<Assumptions!$C$122,0,MIN(Assumptions!$C$134,Assumptions!$C$126+Assumptions!$C$130*(G$3-Assumptions!$C$122))) -> 0 | H22: =IF(H$3<Assumptions!$C$122,0,MIN(Assumptions!$C$134,Assumptions!$C$126+Assumptions!$C$130*(H$3-Assumptions!$C$122))) -> 0 | I22: =IF(I$3<Assumptions!$C$122,0,MIN(Assumptions!$C$134,Assumptions!$C$126+Assumptions!$C$130*(I$3-Assumptions!$C$122))) -> 0 | J22: =IF(J$3<Assumptions!$C$122,0,MIN(Assumptions!$C$134,Assumptions!$C$126+Assumptions!$C$130*(J$3-Assumptions!$C$122))) -> 0 | ... AL22: =IF(AL$3<Assumptions!$C$122,0,MIN(Assumptions!$C$134,Assumptions!$C$126+Assumptions!$C$130*(AL$3-Assumptions!$C$122))) -> 4.04
A23: New customers — Agency | B23: logos | C23: =IF(C$3<Assumptions!$C$123,0,MIN(Assumptions!$C$135,Assumptions!$C$127+Assumptions!$C$131*(C$3-Assumptions!$C$123))) -> 0 | D23: =IF(D$3<Assumptions!$C$123,0,MIN(Assumptions!$C$135,Assumptions!$C$127+Assumptions!$C$131*(D$3-Assumptions!$C$123))) -> 0 | E23: =IF(E$3<Assumptions!$C$123,0,MIN(Assumptions!$C$135,Assumptions!$C$127+Assumptions!$C$131*(E$3-Assumptions!$C$123))) -> 0 | F23: =IF(F$3<Assumptions!$C$123,0,MIN(Assumptions!$C$135,Assumptions!$C$127+Assumptions!$C$131*(F$3-Assumptions!$C$123))) -> 0 | G23: =IF(G$3<Assumptions!$C$123,0,MIN(Assumptions!$C$135,Assumptions!$C$127+Assumptions!$C$131*(G$3-Assumptions!$C$123))) -> 0 | H23: =IF(H$3<Assumptions!$C$123,0,MIN(Assumptions!$C$135,Assumptions!$C$127+Assumptions!$C$131*(H$3-Assumptions!$C$123))) -> 0 | I23: =IF(I$3<Assumptions!$C$123,0,MIN(Assumptions!$C$135,Assumptions!$C$127+Assumptions!$C$131*(I$3-Assumptions!$C$123))) -> 0 | J23: =IF(J$3<Assumptions!$C$123,0,MIN(Assumptions!$C$135,Assumptions!$C$127+Assumptions!$C$131*(J$3-Assumptions!$C$123))) -> 0 | ... AL23: =IF(AL$3<Assumptions!$C$123,0,MIN(Assumptions!$C$135,Assumptions!$C$127+Assumptions!$C$131*(AL$3-Assumptions!$C$123))) -> 1.24
A24: New customers — Developer Pro | B24: logos | C24: =IF(C$3<Assumptions!$C$124,0,MIN(Assumptions!$C$136,Assumptions!$C$128+Assumptions!$C$132*(C$3-Assumptions!$C$124)))+IF(C$3<Assumptions!$C$124,0,C$19*Assumptions!$C$138) -> 0 | D24: =IF(D$3<Assumptions!$C$124,0,MIN(Assumptions!$C$136,Assumptions!$C$128+Assumptions!$C$132*(D$3-Assumptions!$C$124)))+IF(D$3<Assumptions!$C$124,0,D$19*Assumptions!$C$138) -> 0 | E24: =IF(E$3<Assumptions!$C$124,0,MIN(Assumptions!$C$136,Assumptions!$C$128+Assumptions!$C$132*(E$3-Assumptions!$C$124)))+IF(E$3<Assumptions!$C$124,0,E$19*Assumptions!$C$138) -> 0 | F24: =IF(F$3<Assumptions!$C$124,0,MIN(Assumptions!$C$136,Assumptions!$C$128+Assumptions!$C$132*(F$3-Assumptions!$C$124)))+IF(F$3<Assumptions!$C$124,0,F$19*Assumptions!$C$138) -> 0 | G24: =IF(G$3<Assumptions!$C$124,0,MIN(Assumptions!$C$136,Assumptions!$C$128+Assumptions!$C$132*(G$3-Assumptions!$C$124)))+IF(G$3<Assumptions!$C$124,0,G$19*Assumptions!$C$138) -> 0 | H24: =IF(H$3<Assumptions!$C$124,0,MIN(Assumptions!$C$136,Assumptions!$C$128+Assumptions!$C$132*(H$3-Assumptions!$C$124)))+IF(H$3<Assumptions!$C$124,0,H$19*Assumptions!$C$138) -> 0 | I24: =IF(I$3<Assumptions!$C$124,0,MIN(Assumptions!$C$136,Assumptions!$C$128+Assumptions!$C$132*(I$3-Assumptions!$C$124)))+IF(I$3<Assumptions!$C$124,0,I$19*Assumptions!$C$138) -> 0 | J24: =IF(J$3<Assumptions!$C$124,0,MIN(Assumptions!$C$136,Assumptions!$C$128+Assumptions!$C$132*(J$3-Assumptions!$C$124)))+IF(J$3<Assumptions!$C$124,0,J$19*Assumptions!$C$138) -> 0 | ... AL24: =IF(AL$3<Assumptions!$C$124,0,MIN(Assumptions!$C$136,Assumptions!$C$128+Assumptions!$C$132*(AL$3-Assumptions!$C$124)))+IF(AL$3<Assumptions!$C$124,0,AL$19*Assumptions!$C$138) -> 0.46
A25: New customers — Enterprise | B25: logos | C25: =IF(C$3<Assumptions!$C$125,0,MIN(Assumptions!$C$137,Assumptions!$C$129+Assumptions!$C$133*(C$3-Assumptions!$C$125)))+IF(C$3<Assumptions!$C$125,0,C$19*Assumptions!$C$139) -> 0 | D25: =IF(D$3<Assumptions!$C$125,0,MIN(Assumptions!$C$137,Assumptions!$C$129+Assumptions!$C$133*(D$3-Assumptions!$C$125)))+IF(D$3<Assumptions!$C$125,0,D$19*Assumptions!$C$139) -> 0 | E25: =IF(E$3<Assumptions!$C$125,0,MIN(Assumptions!$C$137,Assumptions!$C$129+Assumptions!$C$133*(E$3-Assumptions!$C$125)))+IF(E$3<Assumptions!$C$125,0,E$19*Assumptions!$C$139) -> 0 | F25: =IF(F$3<Assumptions!$C$125,0,MIN(Assumptions!$C$137,Assumptions!$C$129+Assumptions!$C$133*(F$3-Assumptions!$C$125)))+IF(F$3<Assumptions!$C$125,0,F$19*Assumptions!$C$139) -> 0 | G25: =IF(G$3<Assumptions!$C$125,0,MIN(Assumptions!$C$137,Assumptions!$C$129+Assumptions!$C$133*(G$3-Assumptions!$C$125)))+IF(G$3<Assumptions!$C$125,0,G$19*Assumptions!$C$139) -> 0 | H25: =IF(H$3<Assumptions!$C$125,0,MIN(Assumptions!$C$137,Assumptions!$C$129+Assumptions!$C$133*(H$3-Assumptions!$C$125)))+IF(H$3<Assumptions!$C$125,0,H$19*Assumptions!$C$139) -> 0 | I25: =IF(I$3<Assumptions!$C$125,0,MIN(Assumptions!$C$137,Assumptions!$C$129+Assumptions!$C$133*(I$3-Assumptions!$C$125)))+IF(I$3<Assumptions!$C$125,0,I$19*Assumptions!$C$139) -> 0 | J25: =IF(J$3<Assumptions!$C$125,0,MIN(Assumptions!$C$137,Assumptions!$C$129+Assumptions!$C$133*(J$3-Assumptions!$C$125)))+IF(J$3<Assumptions!$C$125,0,J$19*Assumptions!$C$139) -> 0 | ... AL25: =IF(AL$3<Assumptions!$C$125,0,MIN(Assumptions!$C$137,Assumptions!$C$129+Assumptions!$C$133*(AL$3-Assumptions!$C$125)))+IF(AL$3<Assumptions!$C$125,0,AL$19*Assumptions!$C$139) -> 0.122
A26: Churned customers — Studio | B26: logos | C26: =0 -> 0 | D26: =C30*Assumptions!$C$141 -> 0 | E26: =D30*Assumptions!$C$141 -> 0 | F26: =E30*Assumptions!$C$141 -> 0 | G26: =F30*Assumptions!$C$141 -> 0 | H26: =G30*Assumptions!$C$141 -> 0 | I26: =H30*Assumptions!$C$141 -> 0 | J26: =I30*Assumptions!$C$141 -> 0 | K26: =J30*Assumptions!$C$141 -> 0 | ... AL26: =AK30*Assumptions!$C$141 -> 1.9117987
A27: Churned customers — Agency | B27: logos | C27: =0 -> 0 | D27: =C31*Assumptions!$C$142 -> 0 | E27: =D31*Assumptions!$C$142 -> 0 | F27: =E31*Assumptions!$C$142 -> 0 | G27: =F31*Assumptions!$C$142 -> 0 | H27: =G31*Assumptions!$C$142 -> 0 | I27: =H31*Assumptions!$C$142 -> 0 | J27: =I31*Assumptions!$C$142 -> 0 | K27: =J31*Assumptions!$C$142 -> 0 | ... AL27: =AK31*Assumptions!$C$142 -> 0.47052715
A28: Churned customers — Developer Pro | B28: logos | C28: =0 -> 0 | D28: =C32*Assumptions!$C$143 -> 0 | E28: =D32*Assumptions!$C$143 -> 0 | F28: =E32*Assumptions!$C$143 -> 0 | G28: =F32*Assumptions!$C$143 -> 0 | H28: =G32*Assumptions!$C$143 -> 0 | I28: =H32*Assumptions!$C$143 -> 0 | J28: =I32*Assumptions!$C$143 -> 0 | K28: =J32*Assumptions!$C$143 -> 0 | ... AL28: =AK32*Assumptions!$C$143 -> 0.086198527
A29: Churned customers — Enterprise | B29: logos | C29: =0 -> 0 | D29: =C33*Assumptions!$C$144 -> 0 | E29: =D33*Assumptions!$C$144 -> 0 | F29: =E33*Assumptions!$C$144 -> 0 | G29: =F33*Assumptions!$C$144 -> 0 | H29: =G33*Assumptions!$C$144 -> 0 | I29: =H33*Assumptions!$C$144 -> 0 | J29: =I33*Assumptions!$C$144 -> 0 | K29: =J33*Assumptions!$C$144 -> 0 | ... AL29: =AK33*Assumptions!$C$144 -> 0.014079817
A30: Customers (end of month) — Studio | B30: logos | C30: =C22-C26 -> 0 | D30: =C30+D22-D26 -> 0 | E30: =D30+E22-E26 -> 0 | F30: =E30+F22-F26 -> 0 | G30: =F30+G22-G26 -> 0 | H30: =G30+H22-H26 -> 0 | I30: =H30+I22-I26 -> 0 | J30: =I30+J22-J26 -> 0 | K30: =J30+K22-K26 -> 0.8 | ... AL30: =AK30+AL22-AL26 -> 44.612618
A31: Customers (end of month) — Agency | B31: logos | C31: =C23-C27 -> 0 | D31: =C31+D23-D27 -> 0 | E31: =D31+E23-E27 -> 0 | F31: =E31+F23-F27 -> 0 | G31: =F31+G23-G27 -> 0 | H31: =G31+H23-H27 -> 0 | I31: =H31+I23-I27 -> 0 | J31: =I31+J23-J27 -> 0 | K31: =J31+K23-K27 -> 0 | ... AL31: =AK31+AL23-AL27 -> 14.213106
A32: Customers (end of month) — Developer Pro | B32: logos | C32: =C24-C28 -> 0 | D32: =C32+D24-D28 -> 0 | E32: =D32+E24-E28 -> 0 | F32: =E32+F24-F28 -> 0 | G32: =F32+G24-G28 -> 0 | H32: =G32+H24-H28 -> 0 | I32: =H32+I24-I28 -> 0 | J32: =I32+J24-J28 -> 0 | K32: =J32+K24-K28 -> 0 | ... AL32: =AK32+AL24-AL28 -> 6.1203699
A33: Customers (end of month) — Enterprise | B33: logos | C33: =C25-C29 -> 0 | D33: =C33+D25-D29 -> 0 | E33: =D33+E25-E29 -> 0 | F33: =E33+F25-F29 -> 0 | G33: =F33+G25-G29 -> 0 | H33: =G33+H25-H29 -> 0 | I33: =H33+I25-I29 -> 0 | J33: =I33+J25-J29 -> 0 | K33: =J33+K25-K29 -> 0 | ... AL33: =AK33+AL25-AL29 -> 1.5159018
A34: Total new customers | B34: logos | C34: =C22+C23+C24+C25 -> 0 | D34: =D22+D23+D24+D25 -> 0 | E34: =E22+E23+E24+E25 -> 0 | F34: =F22+F23+F24+F25 -> 0 | G34: =G22+G23+G24+G25 -> 0 | H34: =H22+H23+H24+H25 -> 0 | I34: =I22+I23+I24+I25 -> 0 | J34: =J22+J23+J24+J25 -> 0 | ... AL34: =AL22+AL23+AL24+AL25 -> 5.862
A35: Total churned customers | B35: logos | C35: =C26+C27+C28+C29 -> 0 | D35: =D26+D27+D28+D29 -> 0 | E35: =E26+E27+E28+E29 -> 0 | F35: =F26+F27+F28+F29 -> 0 | G35: =G26+G27+G28+G29 -> 0 | H35: =H26+H27+H28+H29 -> 0 | I35: =I26+I27+I28+I29 -> 0 | J35: =J26+J27+J28+J29 -> 0 | ... AL35: =AL26+AL27+AL28+AL29 -> 2.4826042
A36: Total paying customers | B36: logos | C36: =C30+C31+C32+C33 -> 0 | D36: =D30+D31+D32+D33 -> 0 | E36: =E30+E31+E32+E33 -> 0 | F36: =F30+F31+F32+F33 -> 0 | G36: =G30+G31+G32+G33 -> 0 | H36: =H30+H31+H32+H33 -> 0 | I36: =I30+I31+I32+I33 -> 0 | J36: =J30+J31+J32+J33 -> 0 | ... AL36: =AL30+AL31+AL32+AL33 -> 66.461995
A38: Revenue
A39: Subscription MRR — Studio | B39: £ | C39: =C22*Assumptions!$D$73*Assumptions!$C$149 -> 0 | D39: =C39*(1-Assumptions!$C$141)*(1+Assumptions!$C$145)+D22*Assumptions!$D$73*Assumptions!$C$149 -> 0 | E39: =D39*(1-Assumptions!$C$141)*(1+Assumptions!$C$145)+E22*Assumptions!$D$73*Assumptions!$C$149 -> 0 | F39: =E39*(1-Assumptions!$C$141)*(1+Assumptions!$C$145)+F22*Assumptions!$D$73*Assumptions!$C$149 -> 0 | G39: =F39*(1-Assumptions!$C$141)*(1+Assumptions!$C$145)+G22*Assumptions!$D$73*Assumptions!$C$149 -> 0 | H39: =G39*(1-Assumptions!$C$141)*(1+Assumptions!$C$145)+H22*Assumptions!$D$73*Assumptions!$C$149 -> 0 | I39: =H39*(1-Assumptions!$C$141)*(1+Assumptions!$C$145)+I22*Assumptions!$D$73*Assumptions!$C$149 -> 0 | J39: =I39*(1-Assumptions!$C$141)*(1+Assumptions!$C$145)+J22*Assumptions!$D$73*Assumptions!$C$149 -> 0 | K39: =J39*(1-Assumptions!$C$141)*(1+Assumptions!$C$145)+K22*Assumptions!$D$73*Assumptions!$C$149 -> 101.32 | ... AL39: =AK39*(1-Assumptions!$C$141)*(1+Assumptions!$C$145)+AL22*Assumptions!$D$73*Assumptions!$C$149 -> 5695.5066
A40: Subscription MRR — Agency | B40: £ | C40: =C23*Assumptions!$D$74*Assumptions!$C$150 -> 0 | D40: =C40*(1-Assumptions!$C$142)*(1+Assumptions!$C$146)+D23*Assumptions!$D$74*Assumptions!$C$150 -> 0 | E40: =D40*(1-Assumptions!$C$142)*(1+Assumptions!$C$146)+E23*Assumptions!$D$74*Assumptions!$C$150 -> 0 | F40: =E40*(1-Assumptions!$C$142)*(1+Assumptions!$C$146)+F23*Assumptions!$D$74*Assumptions!$C$150 -> 0 | G40: =F40*(1-Assumptions!$C$142)*(1+Assumptions!$C$146)+G23*Assumptions!$D$74*Assumptions!$C$150 -> 0 | H40: =G40*(1-Assumptions!$C$142)*(1+Assumptions!$C$146)+H23*Assumptions!$D$74*Assumptions!$C$150 -> 0 | I40: =H40*(1-Assumptions!$C$142)*(1+Assumptions!$C$146)+I23*Assumptions!$D$74*Assumptions!$C$150 -> 0 | J40: =I40*(1-Assumptions!$C$142)*(1+Assumptions!$C$146)+J23*Assumptions!$D$74*Assumptions!$C$150 -> 0 | K40: =J40*(1-Assumptions!$C$142)*(1+Assumptions!$C$146)+K23*Assumptions!$D$74*Assumptions!$C$150 -> 0 | ... AL40: =AK40*(1-Assumptions!$C$142)*(1+Assumptions!$C$146)+AL23*Assumptions!$D$74*Assumptions!$C$150 -> 5812.4545
A41: Subscription MRR — Developer Pro | B41: £ | C41: =C24*Assumptions!$D$75*Assumptions!$C$151 -> 0 | D41: =C41*(1-Assumptions!$C$143)*(1+Assumptions!$C$147)+D24*Assumptions!$D$75*Assumptions!$C$151 -> 0 | E41: =D41*(1-Assumptions!$C$143)*(1+Assumptions!$C$147)+E24*Assumptions!$D$75*Assumptions!$C$151 -> 0 | F41: =E41*(1-Assumptions!$C$143)*(1+Assumptions!$C$147)+F24*Assumptions!$D$75*Assumptions!$C$151 -> 0 | G41: =F41*(1-Assumptions!$C$143)*(1+Assumptions!$C$147)+G24*Assumptions!$D$75*Assumptions!$C$151 -> 0 | H41: =G41*(1-Assumptions!$C$143)*(1+Assumptions!$C$147)+H24*Assumptions!$D$75*Assumptions!$C$151 -> 0 | I41: =H41*(1-Assumptions!$C$143)*(1+Assumptions!$C$147)+I24*Assumptions!$D$75*Assumptions!$C$151 -> 0 | J41: =I41*(1-Assumptions!$C$143)*(1+Assumptions!$C$147)+J24*Assumptions!$D$75*Assumptions!$C$151 -> 0 | K41: =J41*(1-Assumptions!$C$143)*(1+Assumptions!$C$147)+K24*Assumptions!$D$75*Assumptions!$C$151 -> 0 | ... AL41: =AK41*(1-Assumptions!$C$143)*(1+Assumptions!$C$147)+AL24*Assumptions!$D$75*Assumptions!$C$151 -> 8072.1237
A42: Subscription MRR — Enterprise | B42: £ | C42: =C25*Assumptions!$D$76*Assumptions!$C$152 -> 0 | D42: =C42*(1-Assumptions!$C$144)*(1+Assumptions!$C$148)+D25*Assumptions!$D$76*Assumptions!$C$152 -> 0 | E42: =D42*(1-Assumptions!$C$144)*(1+Assumptions!$C$148)+E25*Assumptions!$D$76*Assumptions!$C$152 -> 0 | F42: =E42*(1-Assumptions!$C$144)*(1+Assumptions!$C$148)+F25*Assumptions!$D$76*Assumptions!$C$152 -> 0 | G42: =F42*(1-Assumptions!$C$144)*(1+Assumptions!$C$148)+G25*Assumptions!$D$76*Assumptions!$C$152 -> 0 | H42: =G42*(1-Assumptions!$C$144)*(1+Assumptions!$C$148)+H25*Assumptions!$D$76*Assumptions!$C$152 -> 0 | I42: =H42*(1-Assumptions!$C$144)*(1+Assumptions!$C$148)+I25*Assumptions!$D$76*Assumptions!$C$152 -> 0 | J42: =I42*(1-Assumptions!$C$144)*(1+Assumptions!$C$148)+J25*Assumptions!$D$76*Assumptions!$C$152 -> 0 | K42: =J42*(1-Assumptions!$C$144)*(1+Assumptions!$C$148)+K25*Assumptions!$D$76*Assumptions!$C$152 -> 0 | ... AL42: =AK42*(1-Assumptions!$C$144)*(1+Assumptions!$C$148)+AL25*Assumptions!$D$76*Assumptions!$C$152 -> 5504.9721
A43: Subscription MRR (total) — milestone metric | B43: £ | C43: =C39+C40+C41+C42 -> 0 | D43: =D39+D40+D41+D42 -> 0 | E43: =E39+E40+E41+E42 -> 0 | F43: =F39+F40+F41+F42 -> 0 | G43: =G39+G40+G41+G42 -> 0 | H43: =H39+H40+H41+H42 -> 0 | I43: =I39+I40+I41+I42 -> 0 | J43: =J39+J40+J41+J42 -> 0 | ... AL43: =AL39+AL40+AL41+AL42 -> 25085.057
A44: ARR (subscription MRR x 12) | B44: £ | C44: =C43*12 -> 0 | D44: =D43*12 -> 0 | E44: =E43*12 -> 0 | F44: =F43*12 -> 0 | G44: =G43*12 -> 0 | H44: =H43*12 -> 0 | I44: =I43*12 -> 0 | J44: =J43*12 -> 0 | ... AL44: =AL43*12 -> 301020.68
A45: ARPA — Studio | B45: £ / month | C45: =IF(C30<0.0001,0,C39/C30) -> 0 | D45: =IF(D30<0.0001,0,D39/D30) -> 0 | E45: =IF(E30<0.0001,0,E39/E30) -> 0 | F45: =IF(F30<0.0001,0,F39/F30) -> 0 | G45: =IF(G30<0.0001,0,G39/G30) -> 0 | H45: =IF(H30<0.0001,0,H39/H30) -> 0 | I45: =IF(I30<0.0001,0,I39/I30) -> 0 | J45: =IF(J30<0.0001,0,J39/J30) -> 0 | ... AL45: =IF(AL30<0.0001,0,AL39/AL30) -> 127.66582
A46: ARPA — Agency | B46: £ / month | C46: =IF(C31<0.0001,0,C40/C31) -> 0 | D46: =IF(D31<0.0001,0,D40/D31) -> 0 | E46: =IF(E31<0.0001,0,E40/E31) -> 0 | F46: =IF(F31<0.0001,0,F40/F31) -> 0 | G46: =IF(G31<0.0001,0,G40/G31) -> 0 | H46: =IF(H31<0.0001,0,H40/H31) -> 0 | I46: =IF(I31<0.0001,0,I40/I31) -> 0 | J46: =IF(J31<0.0001,0,J40/J31) -> 0 | ... AL46: =IF(AL31<0.0001,0,AL40/AL31) -> 408.95035
A47: ARPA — Developer Pro | B47: £ / month | C47: =IF(C32<0.0001,0,C41/C32) -> 0 | D47: =IF(D32<0.0001,0,D41/D32) -> 0 | E47: =IF(E32<0.0001,0,E41/E32) -> 0 | F47: =IF(F32<0.0001,0,F41/F32) -> 0 | G47: =IF(G32<0.0001,0,G41/G32) -> 0 | H47: =IF(H32<0.0001,0,H41/H32) -> 0 | I47: =IF(I32<0.0001,0,I41/I32) -> 0 | J47: =IF(J32<0.0001,0,J41/J32) -> 0 | ... AL47: =IF(AL32<0.0001,0,AL41/AL32) -> 1318.8947
A48: ARPA — Enterprise | B48: £ / month | C48: =IF(C33<0.0001,0,C42/C33) -> 0 | D48: =IF(D33<0.0001,0,D42/D33) -> 0 | E48: =IF(E33<0.0001,0,E42/E33) -> 0 | F48: =IF(F33<0.0001,0,F42/F33) -> 0 | G48: =IF(G33<0.0001,0,G42/G33) -> 0 | H48: =IF(H33<0.0001,0,H42/H33) -> 0 | I48: =IF(I33<0.0001,0,I42/I33) -> 0 | J48: =IF(J33<0.0001,0,J42/J33) -> 0 | ... AL48: =IF(AL33<0.0001,0,AL42/AL33) -> 3631.4833
A49: ARPA — blended | B49: £ / month | C49: =IF(C36<0.0001,0,C43/C36) -> 0 | D49: =IF(D36<0.0001,0,D43/D36) -> 0 | E49: =IF(E36<0.0001,0,E43/E36) -> 0 | F49: =IF(F36<0.0001,0,F43/F36) -> 0 | G49: =IF(G36<0.0001,0,G43/G36) -> 0 | H49: =IF(H36<0.0001,0,H43/H36) -> 0 | I49: =IF(I36<0.0001,0,I43/I36) -> 0 | J49: =IF(J36<0.0001,0,J43/J36) -> 0 | ... AL49: =IF(AL36<0.0001,0,AL43/AL36) -> 377.43461
A50: Overage revenue — Studio | B50: £ | C50: =C30*Pricing!$B$6*Assumptions!$C$154*Assumptions!$D$79 -> 0 | D50: =D30*Pricing!$B$6*Assumptions!$C$154*Assumptions!$D$79 -> 0 | E50: =E30*Pricing!$B$6*Assumptions!$C$154*Assumptions!$D$79 -> 0 | F50: =F30*Pricing!$B$6*Assumptions!$C$154*Assumptions!$D$79 -> 0 | G50: =G30*Pricing!$B$6*Assumptions!$C$154*Assumptions!$D$79 -> 0 | H50: =H30*Pricing!$B$6*Assumptions!$C$154*Assumptions!$D$79 -> 0 | I50: =I30*Pricing!$B$6*Assumptions!$C$154*Assumptions!$D$79 -> 0 | J50: =J30*Pricing!$B$6*Assumptions!$C$154*Assumptions!$D$79 -> 0 | ... AL50: =AL30*Pricing!$B$6*Assumptions!$C$154*Assumptions!$D$79 -> 185.58849
A51: Overage revenue — Agency | B51: £ | C51: =C31*Pricing!$C$6*Assumptions!$C$154*Assumptions!$D$80 -> 0 | D51: =D31*Pricing!$C$6*Assumptions!$C$154*Assumptions!$D$80 -> 0 | E51: =E31*Pricing!$C$6*Assumptions!$C$154*Assumptions!$D$80 -> 0 | F51: =F31*Pricing!$C$6*Assumptions!$C$154*Assumptions!$D$80 -> 0 | G51: =G31*Pricing!$C$6*Assumptions!$C$154*Assumptions!$D$80 -> 0 | H51: =H31*Pricing!$C$6*Assumptions!$C$154*Assumptions!$D$80 -> 0 | I51: =I31*Pricing!$C$6*Assumptions!$C$154*Assumptions!$D$80 -> 0 | J51: =J31*Pricing!$C$6*Assumptions!$C$154*Assumptions!$D$80 -> 0 | ... AL51: =AL31*Pricing!$C$6*Assumptions!$C$154*Assumptions!$D$80 -> 202.96315
A52: Overage revenue — Developer Pro | B52: £ | C52: =C32*Pricing!$D$6*Assumptions!$C$154*Assumptions!$D$81 -> 0 | D52: =D32*Pricing!$D$6*Assumptions!$C$154*Assumptions!$D$81 -> 0 | E52: =E32*Pricing!$D$6*Assumptions!$C$154*Assumptions!$D$81 -> 0 | F52: =F32*Pricing!$D$6*Assumptions!$C$154*Assumptions!$D$81 -> 0 | G52: =G32*Pricing!$D$6*Assumptions!$C$154*Assumptions!$D$81 -> 0 | H52: =H32*Pricing!$D$6*Assumptions!$C$154*Assumptions!$D$81 -> 0 | I52: =I32*Pricing!$D$6*Assumptions!$C$154*Assumptions!$D$81 -> 0 | J52: =J32*Pricing!$D$6*Assumptions!$C$154*Assumptions!$D$81 -> 0 | ... AL52: =AL32*Pricing!$D$6*Assumptions!$C$154*Assumptions!$D$81 -> 163.04665
A53: Overage revenue — Enterprise | B53: £ | C53: =C33*Pricing!$E$6*Assumptions!$C$154*Assumptions!$D$82 -> 0 | D53: =D33*Pricing!$E$6*Assumptions!$C$154*Assumptions!$D$82 -> 0 | E53: =E33*Pricing!$E$6*Assumptions!$C$154*Assumptions!$D$82 -> 0 | F53: =F33*Pricing!$E$6*Assumptions!$C$154*Assumptions!$D$82 -> 0 | G53: =G33*Pricing!$E$6*Assumptions!$C$154*Assumptions!$D$82 -> 0 | H53: =H33*Pricing!$E$6*Assumptions!$C$154*Assumptions!$D$82 -> 0 | I53: =I33*Pricing!$E$6*Assumptions!$C$154*Assumptions!$D$82 -> 0 | J53: =J33*Pricing!$E$6*Assumptions!$C$154*Assumptions!$D$82 -> 0 | ... AL53: =AL33*Pricing!$E$6*Assumptions!$C$154*Assumptions!$D$82 -> 142.04
A54: Setup fees — Studio | B54: £ | C54: =C22*Assumptions!$D$83*Assumptions!$C$155 -> 0 | D54: =D22*Assumptions!$D$83*Assumptions!$C$155 -> 0 | E54: =E22*Assumptions!$D$83*Assumptions!$C$155 -> 0 | F54: =F22*Assumptions!$D$83*Assumptions!$C$155 -> 0 | G54: =G22*Assumptions!$D$83*Assumptions!$C$155 -> 0 | H54: =H22*Assumptions!$D$83*Assumptions!$C$155 -> 0 | I54: =I22*Assumptions!$D$83*Assumptions!$C$155 -> 0 | J54: =J22*Assumptions!$D$83*Assumptions!$C$155 -> 0 | ... AL54: =AL22*Assumptions!$D$83*Assumptions!$C$155 -> 0
A55: Setup fees — Agency | B55: £ | C55: =C23*Assumptions!$D$84*Assumptions!$C$155 -> 0 | D55: =D23*Assumptions!$D$84*Assumptions!$C$155 -> 0 | E55: =E23*Assumptions!$D$84*Assumptions!$C$155 -> 0 | F55: =F23*Assumptions!$D$84*Assumptions!$C$155 -> 0 | G55: =G23*Assumptions!$D$84*Assumptions!$C$155 -> 0 | H55: =H23*Assumptions!$D$84*Assumptions!$C$155 -> 0 | I55: =I23*Assumptions!$D$84*Assumptions!$C$155 -> 0 | J55: =J23*Assumptions!$D$84*Assumptions!$C$155 -> 0 | ... AL55: =AL23*Assumptions!$D$84*Assumptions!$C$155 -> 310
A56: Setup fees — Developer Pro | B56: £ | C56: =C24*Assumptions!$D$85*Assumptions!$C$155 -> 0 | D56: =D24*Assumptions!$D$85*Assumptions!$C$155 -> 0 | E56: =E24*Assumptions!$D$85*Assumptions!$C$155 -> 0 | F56: =F24*Assumptions!$D$85*Assumptions!$C$155 -> 0 | G56: =G24*Assumptions!$D$85*Assumptions!$C$155 -> 0 | H56: =H24*Assumptions!$D$85*Assumptions!$C$155 -> 0 | I56: =I24*Assumptions!$D$85*Assumptions!$C$155 -> 0 | J56: =J24*Assumptions!$D$85*Assumptions!$C$155 -> 0 | ... AL56: =AL24*Assumptions!$D$85*Assumptions!$C$155 -> 345
A57: Setup fees — Enterprise | B57: £ | C57: =C25*Assumptions!$D$86*Assumptions!$C$155 -> 0 | D57: =D25*Assumptions!$D$86*Assumptions!$C$155 -> 0 | E57: =E25*Assumptions!$D$86*Assumptions!$C$155 -> 0 | F57: =F25*Assumptions!$D$86*Assumptions!$C$155 -> 0 | G57: =G25*Assumptions!$D$86*Assumptions!$C$155 -> 0 | H57: =H25*Assumptions!$D$86*Assumptions!$C$155 -> 0 | I57: =I25*Assumptions!$D$86*Assumptions!$C$155 -> 0 | J57: =J25*Assumptions!$D$86*Assumptions!$C$155 -> 0 | ... AL57: =AL25*Assumptions!$D$86*Assumptions!$C$155 -> 457.5
A58: Additional developments launched (Developer Pro) | B58: developments | C58: =C32*Assumptions!$C$156/12 -> 0 | D58: =D32*Assumptions!$C$156/12 -> 0 | E58: =E32*Assumptions!$C$156/12 -> 0 | F58: =F32*Assumptions!$C$156/12 -> 0 | G58: =G32*Assumptions!$C$156/12 -> 0 | H58: =H32*Assumptions!$C$156/12 -> 0 | I58: =I32*Assumptions!$C$156/12 -> 0 | J58: =J32*Assumptions!$C$156/12 -> 0 | ... AL58: =AL32*Assumptions!$C$156/12 -> 0.25501541
A59: Per-development fees | B59: £ | C59: =C58*Assumptions!$D$48*Assumptions!$D$87 -> 0 | D59: =D58*Assumptions!$D$48*Assumptions!$D$87 -> 0 | E59: =E58*Assumptions!$D$48*Assumptions!$D$87 -> 0 | F59: =F58*Assumptions!$D$48*Assumptions!$D$87 -> 0 | G59: =G58*Assumptions!$D$48*Assumptions!$D$87 -> 0 | H59: =H58*Assumptions!$D$48*Assumptions!$D$87 -> 0 | I59: =I58*Assumptions!$D$48*Assumptions!$D$87 -> 0 | J59: =J58*Assumptions!$D$48*Assumptions!$D$87 -> 0 | ... AL59: =AL58*Assumptions!$D$48*Assumptions!$D$87 -> 535.53237
A60: Revenue — subscription | B60: £ | C60: =C43 -> 0 | D60: =D43 -> 0 | E60: =E43 -> 0 | F60: =F43 -> 0 | G60: =G43 -> 0 | H60: =H43 -> 0 | I60: =I43 -> 0 | J60: =J43 -> 0 | ... AL60: =AL43 -> 25085.057
A61: Revenue — overage | B61: £ | C61: =C50+C51+C52+C53 -> 0 | D61: =D50+D51+D52+D53 -> 0 | E61: =E50+E51+E52+E53 -> 0 | F61: =F50+F51+F52+F53 -> 0 | G61: =G50+G51+G52+G53 -> 0 | H61: =H50+H51+H52+H53 -> 0 | I61: =I50+I51+I52+I53 -> 0 | J61: =J50+J51+J52+J53 -> 0 | ... AL61: =AL50+AL51+AL52+AL53 -> 693.63829
A62: Revenue — setup + per-development fees | B62: £ | C62: =C54+C55+C56+C57+C59 -> 0 | D62: =D54+D55+D56+D57+D59 -> 0 | E62: =E54+E55+E56+E57+E59 -> 0 | F62: =F54+F55+F56+F57+F59 -> 0 | G62: =G54+G55+G56+G57+G59 -> 0 | H62: =H54+H55+H56+H57+H59 -> 0 | I62: =I54+I55+I56+I57+I59 -> 0 | J62: =J54+J55+J56+J57+J59 -> 0 | ... AL62: =AL54+AL55+AL56+AL57+AL59 -> 1648.0324
A63: Total revenue | B63: £ | C63: =C60+C61+C62 -> 0 | D63: =D60+D61+D62 -> 0 | E63: =E60+E61+E62 -> 0 | F63: =F60+F61+F62 -> 0 | G63: =G60+G61+G62 -> 0 | H63: =H60+H61+H62 -> 0 | I63: =I60+I61+I62 -> 0 | J63: =J60+J61+J62 -> 0 | ... AL63: =AL60+AL61+AL62 -> 27426.728
A65: Cost of goods sold
A66: Generation + human QA on included usage — Studio | B66: £ | C66: =C30*Pricing!$B$6*Assumptions!$C$153*CHOOSE(Assumptions!$C$121,Pricing!$B$20,Pricing!$B$30,Pricing!$B$40) -> 0 | D66: =D30*Pricing!$B$6*Assumptions!$C$153*CHOOSE(Assumptions!$C$121,Pricing!$B$20,Pricing!$B$30,Pricing!$B$40) -> 0 | E66: =E30*Pricing!$B$6*Assumptions!$C$153*CHOOSE(Assumptions!$C$121,Pricing!$B$20,Pricing!$B$30,Pricing!$B$40) -> 0 | F66: =F30*Pricing!$B$6*Assumptions!$C$153*CHOOSE(Assumptions!$C$121,Pricing!$B$20,Pricing!$B$30,Pricing!$B$40) -> 0 | G66: =G30*Pricing!$B$6*Assumptions!$C$153*CHOOSE(Assumptions!$C$121,Pricing!$B$20,Pricing!$B$30,Pricing!$B$40) -> 0 | H66: =H30*Pricing!$B$6*Assumptions!$C$153*CHOOSE(Assumptions!$C$121,Pricing!$B$20,Pricing!$B$30,Pricing!$B$40) -> 0 | I66: =I30*Pricing!$B$6*Assumptions!$C$153*CHOOSE(Assumptions!$C$121,Pricing!$B$20,Pricing!$B$30,Pricing!$B$40) -> 0 | J66: =J30*Pricing!$B$6*Assumptions!$C$153*CHOOSE(Assumptions!$C$121,Pricing!$B$20,Pricing!$B$30,Pricing!$B$40) -> 0 | ... AL66: =AL30*Pricing!$B$6*Assumptions!$C$153*CHOOSE(Assumptions!$C$121,Pricing!$B$20,Pricing!$B$30,Pricing!$B$40) -> 3604.8555
A67: Generation + human QA on included usage — Agency | B67: £ | C67: =C31*Pricing!$C$6*Assumptions!$C$153*CHOOSE(Assumptions!$C$121,Pricing!$C$20,Pricing!$C$30,Pricing!$C$40) -> 0 | D67: =D31*Pricing!$C$6*Assumptions!$C$153*CHOOSE(Assumptions!$C$121,Pricing!$C$20,Pricing!$C$30,Pricing!$C$40) -> 0 | E67: =E31*Pricing!$C$6*Assumptions!$C$153*CHOOSE(Assumptions!$C$121,Pricing!$C$20,Pricing!$C$30,Pricing!$C$40) -> 0 | F67: =F31*Pricing!$C$6*Assumptions!$C$153*CHOOSE(Assumptions!$C$121,Pricing!$C$20,Pricing!$C$30,Pricing!$C$40) -> 0 | G67: =G31*Pricing!$C$6*Assumptions!$C$153*CHOOSE(Assumptions!$C$121,Pricing!$C$20,Pricing!$C$30,Pricing!$C$40) -> 0 | H67: =H31*Pricing!$C$6*Assumptions!$C$153*CHOOSE(Assumptions!$C$121,Pricing!$C$20,Pricing!$C$30,Pricing!$C$40) -> 0 | I67: =I31*Pricing!$C$6*Assumptions!$C$153*CHOOSE(Assumptions!$C$121,Pricing!$C$20,Pricing!$C$30,Pricing!$C$40) -> 0 | J67: =J31*Pricing!$C$6*Assumptions!$C$153*CHOOSE(Assumptions!$C$121,Pricing!$C$20,Pricing!$C$30,Pricing!$C$40) -> 0 | ... AL67: =AL31*Pricing!$C$6*Assumptions!$C$153*CHOOSE(Assumptions!$C$121,Pricing!$C$20,Pricing!$C$30,Pricing!$C$40) -> 4393.2757
A68: Generation + human QA on included usage — Developer Pro | B68: £ | C68: =C32*Pricing!$D$6*Assumptions!$C$153*CHOOSE(Assumptions!$C$121,Pricing!$D$20,Pricing!$D$30,Pricing!$D$40) -> 0 | D68: =D32*Pricing!$D$6*Assumptions!$C$153*CHOOSE(Assumptions!$C$121,Pricing!$D$20,Pricing!$D$30,Pricing!$D$40) -> 0 | E68: =E32*Pricing!$D$6*Assumptions!$C$153*CHOOSE(Assumptions!$C$121,Pricing!$D$20,Pricing!$D$30,Pricing!$D$40) -> 0 | F68: =F32*Pricing!$D$6*Assumptions!$C$153*CHOOSE(Assumptions!$C$121,Pricing!$D$20,Pricing!$D$30,Pricing!$D$40) -> 0 | G68: =G32*Pricing!$D$6*Assumptions!$C$153*CHOOSE(Assumptions!$C$121,Pricing!$D$20,Pricing!$D$30,Pricing!$D$40) -> 0 | H68: =H32*Pricing!$D$6*Assumptions!$C$153*CHOOSE(Assumptions!$C$121,Pricing!$D$20,Pricing!$D$30,Pricing!$D$40) -> 0 | I68: =I32*Pricing!$D$6*Assumptions!$C$153*CHOOSE(Assumptions!$C$121,Pricing!$D$20,Pricing!$D$30,Pricing!$D$40) -> 0 | J68: =J32*Pricing!$D$6*Assumptions!$C$153*CHOOSE(Assumptions!$C$121,Pricing!$D$20,Pricing!$D$30,Pricing!$D$40) -> 0 | ... AL68: =AL32*Pricing!$D$6*Assumptions!$C$153*CHOOSE(Assumptions!$C$121,Pricing!$D$20,Pricing!$D$30,Pricing!$D$40) -> 3541.6286
A69: Generation + human QA on included usage — Enterprise | B69: £ | C69: =C33*Pricing!$E$6*Assumptions!$C$153*CHOOSE(Assumptions!$C$121,Pricing!$E$20,Pricing!$E$30,Pricing!$E$40) -> 0 | D69: =D33*Pricing!$E$6*Assumptions!$C$153*CHOOSE(Assumptions!$C$121,Pricing!$E$20,Pricing!$E$30,Pricing!$E$40) -> 0 | E69: =E33*Pricing!$E$6*Assumptions!$C$153*CHOOSE(Assumptions!$C$121,Pricing!$E$20,Pricing!$E$30,Pricing!$E$40) -> 0 | F69: =F33*Pricing!$E$6*Assumptions!$C$153*CHOOSE(Assumptions!$C$121,Pricing!$E$20,Pricing!$E$30,Pricing!$E$40) -> 0 | G69: =G33*Pricing!$E$6*Assumptions!$C$153*CHOOSE(Assumptions!$C$121,Pricing!$E$20,Pricing!$E$30,Pricing!$E$40) -> 0 | H69: =H33*Pricing!$E$6*Assumptions!$C$153*CHOOSE(Assumptions!$C$121,Pricing!$E$20,Pricing!$E$30,Pricing!$E$40) -> 0 | I69: =I33*Pricing!$E$6*Assumptions!$C$153*CHOOSE(Assumptions!$C$121,Pricing!$E$20,Pricing!$E$30,Pricing!$E$40) -> 0 | J69: =J33*Pricing!$E$6*Assumptions!$C$153*CHOOSE(Assumptions!$C$121,Pricing!$E$20,Pricing!$E$30,Pricing!$E$40) -> 0 | ... AL69: =AL33*Pricing!$E$6*Assumptions!$C$153*CHOOSE(Assumptions!$C$121,Pricing!$E$20,Pricing!$E$30,Pricing!$E$40) -> 3719.8983
A70: Generation + human QA on overage usage | B70: £ | C70: =C30*Pricing!$B$6*Assumptions!$C$154*CHOOSE(Assumptions!$C$121,Pricing!$B$20,Pricing!$B$30,Pricing!$B$40)+C31*Pricing!$C$6*Assumptions!$C$154*CHOOSE(Assumptions!$C$121,Pricing!$C$20,Pricing!$C$30,Pricing!$C$40)+C32*Pricing!$D$6*Assumptions!$C$154*CHOOSE(Assumptions!$C$121,Pricing!$D$20,Pricing!$D$30,Pricing!$D$40)+C33*Pricing!$E$6*Assumptions!$C$154*CHOOSE(Assumptions!$C$121,Pricing!$E$20,Pricing!$E$30,Pricing!$E$40) -> 0 | D70: =D30*Pricing!$B$6*Assumptions!$C$154*CHOOSE(Assumptions!$C$121,Pricing!$B$20,Pricing!$B$30,Pricing!$B$40)+D31*Pricing!$C$6*Assumptions!$C$154*CHOOSE(Assumptions!$C$121,Pricing!$C$20,Pricing!$C$30,Pricing!$C$40)+D32*Pricing!$D$6*Assumptions!$C$154*CHOOSE(Assumptions!$C$121,Pricing!$D$20,Pricing!$D$30,Pricing!$D$40)+D33*Pricing!$E$6*Assumptions!$C$154*CHOOSE(Assumptions!$C$121,Pricing!$E$20,Pricing!$E$30,Pricing!$E$40) -> 0 | E70: =E30*Pricing!$B$6*Assumptions!$C$154*CHOOSE(Assumptions!$C$121,Pricing!$B$20,Pricing!$B$30,Pricing!$B$40)+E31*Pricing!$C$6*Assumptions!$C$154*CHOOSE(Assumptions!$C$121,Pricing!$C$20,Pricing!$C$30,Pricing!$C$40)+E32*Pricing!$D$6*Assumptions!$C$154*CHOOSE(Assumptions!$C$121,Pricing!$D$20,Pricing!$D$30,Pricing!$D$40)+E33*Pricing!$E$6*Assumptions!$C$154*CHOOSE(Assumptions!$C$121,Pricing!$E$20,Pricing!$E$30,Pricing!$E$40) -> 0 | F70: =F30*Pricing!$B$6*Assumptions!$C$154*CHOOSE(Assumptions!$C$121,Pricing!$B$20,Pricing!$B$30,Pricing!$B$40)+F31*Pricing!$C$6*Assumptions!$C$154*CHOOSE(Assumptions!$C$121,Pricing!$C$20,Pricing!$C$30,Pricing!$C$40)+F32*Pricing!$D$6*Assumptions!$C$154*CHOOSE(Assumptions!$C$121,Pricing!$D$20,Pricing!$D$30,Pricing!$D$40)+F33*Pricing!$E$6*Assumptions!$C$154*CHOOSE(Assumptions!$C$121,Pricing!$E$20,Pricing!$E$30,Pricing!$E$40) -> 0 | G70: =G30*Pricing!$B$6*Assumptions!$C$154*CHOOSE(Assumptions!$C$121,Pricing!$B$20,Pricing!$B$30,Pricing!$B$40)+G31*Pricing!$C$6*Assumptions!$C$154*CHOOSE(Assumptions!$C$121,Pricing!$C$20,Pricing!$C$30,Pricing!$C$40)+G32*Pricing!$D$6*Assumptions!$C$154*CHOOSE(Assumptions!$C$121,Pricing!$D$20,Pricing!$D$30,Pricing!$D$40)+G33*Pricing!$E$6*Assumptions!$C$154*CHOOSE(Assumptions!$C$121,Pricing!$E$20,Pricing!$E$30,Pricing!$E$40) -> 0 | H70: =H30*Pricing!$B$6*Assumptions!$C$154*CHOOSE(Assumptions!$C$121,Pricing!$B$20,Pricing!$B$30,Pricing!$B$40)+H31*Pricing!$C$6*Assumptions!$C$154*CHOOSE(Assumptions!$C$121,Pricing!$C$20,Pricing!$C$30,Pricing!$C$40)+H32*Pricing!$D$6*Assumptions!$C$154*CHOOSE(Assumptions!$C$121,Pricing!$D$20,Pricing!$D$30,Pricing!$D$40)+H33*Pricing!$E$6*Assumptions!$C$154*CHOOSE(Assumptions!$C$121,Pricing!$E$20,Pricing!$E$30,Pricing!$E$40) -> 0 | I70: =I30*Pricing!$B$6*Assumptions!$C$154*CHOOSE(Assumptions!$C$121,Pricing!$B$20,Pricing!$B$30,Pricing!$B$40)+I31*Pricing!$C$6*Assumptions!$C$154*CHOOSE(Assumptions!$C$121,Pricing!$C$20,Pricing!$C$30,Pricing!$C$40)+I32*Pricing!$D$6*Assumptions!$C$154*CHOOSE(Assumptions!$C$121,Pricing!$D$20,Pricing!$D$30,Pricing!$D$40)+I33*Pricing!$E$6*Assumptions!$C$154*CHOOSE(Assumptions!$C$121,Pricing!$E$20,Pricing!$E$30,Pricing!$E$40) -> 0 | J70: =J30*Pricing!$B$6*Assumptions!$C$154*CHOOSE(Assumptions!$C$121,Pricing!$B$20,Pricing!$B$30,Pricing!$B$40)+J31*Pricing!$C$6*Assumptions!$C$154*CHOOSE(Assumptions!$C$121,Pricing!$C$20,Pricing!$C$30,Pricing!$C$40)+J32*Pricing!$D$6*Assumptions!$C$154*CHOOSE(Assumptions!$C$121,Pricing!$D$20,Pricing!$D$30,Pricing!$D$40)+J33*Pricing!$E$6*Assumptions!$C$154*CHOOSE(Assumptions!$C$121,Pricing!$E$20,Pricing!$E$30,Pricing!$E$40) -> 0 | ... AL70: =AL30*Pricing!$B$6*Assumptions!$C$154*CHOOSE(Assumptions!$C$121,Pricing!$B$20,Pricing!$B$30,Pricing!$B$40)+AL31*Pricing!$C$6*Assumptions!$C$154*CHOOSE(Assumptions!$C$121,Pricing!$C$20,Pricing!$C$30,Pricing!$C$40)+AL32*Pricing!$D$6*Assumptions!$C$154*CHOOSE(Assumptions!$C$121,Pricing!$D$20,Pricing!$D$30,Pricing!$D$40)+AL33*Pricing!$E$6*Assumptions!$C$154*CHOOSE(Assumptions!$C$121,Pricing!$E$20,Pricing!$E$30,Pricing!$E$40) -> 406.92422
A71: Interactive hosting / streaming (per account) | B71: £ | C71: =C30*Assumptions!$D$88*CHOOSE(Assumptions!$C$121,Unit_Costs!$Q$16,Unit_Costs!$Q$30,Unit_Costs!$Q$44)+C31*Assumptions!$D$89*CHOOSE(Assumptions!$C$121,Unit_Costs!$Q$16,Unit_Costs!$Q$30,Unit_Costs!$Q$44)+C32*Assumptions!$D$90*CHOOSE(Assumptions!$C$121,Unit_Costs!$Q$16,Unit_Costs!$Q$30,Unit_Costs!$Q$44)+C33*Assumptions!$D$91*CHOOSE(Assumptions!$C$121,Unit_Costs!$Q$16,Unit_Costs!$Q$30,Unit_Costs!$Q$44) -> 0 | D71: =D30*Assumptions!$D$88*CHOOSE(Assumptions!$C$121,Unit_Costs!$Q$16,Unit_Costs!$Q$30,Unit_Costs!$Q$44)+D31*Assumptions!$D$89*CHOOSE(Assumptions!$C$121,Unit_Costs!$Q$16,Unit_Costs!$Q$30,Unit_Costs!$Q$44)+D32*Assumptions!$D$90*CHOOSE(Assumptions!$C$121,Unit_Costs!$Q$16,Unit_Costs!$Q$30,Unit_Costs!$Q$44)+D33*Assumptions!$D$91*CHOOSE(Assumptions!$C$121,Unit_Costs!$Q$16,Unit_Costs!$Q$30,Unit_Costs!$Q$44) -> 0 | E71: =E30*Assumptions!$D$88*CHOOSE(Assumptions!$C$121,Unit_Costs!$Q$16,Unit_Costs!$Q$30,Unit_Costs!$Q$44)+E31*Assumptions!$D$89*CHOOSE(Assumptions!$C$121,Unit_Costs!$Q$16,Unit_Costs!$Q$30,Unit_Costs!$Q$44)+E32*Assumptions!$D$90*CHOOSE(Assumptions!$C$121,Unit_Costs!$Q$16,Unit_Costs!$Q$30,Unit_Costs!$Q$44)+E33*Assumptions!$D$91*CHOOSE(Assumptions!$C$121,Unit_Costs!$Q$16,Unit_Costs!$Q$30,Unit_Costs!$Q$44) -> 0 | F71: =F30*Assumptions!$D$88*CHOOSE(Assumptions!$C$121,Unit_Costs!$Q$16,Unit_Costs!$Q$30,Unit_Costs!$Q$44)+F31*Assumptions!$D$89*CHOOSE(Assumptions!$C$121,Unit_Costs!$Q$16,Unit_Costs!$Q$30,Unit_Costs!$Q$44)+F32*Assumptions!$D$90*CHOOSE(Assumptions!$C$121,Unit_Costs!$Q$16,Unit_Costs!$Q$30,Unit_Costs!$Q$44)+F33*Assumptions!$D$91*CHOOSE(Assumptions!$C$121,Unit_Costs!$Q$16,Unit_Costs!$Q$30,Unit_Costs!$Q$44) -> 0 | G71: =G30*Assumptions!$D$88*CHOOSE(Assumptions!$C$121,Unit_Costs!$Q$16,Unit_Costs!$Q$30,Unit_Costs!$Q$44)+G31*Assumptions!$D$89*CHOOSE(Assumptions!$C$121,Unit_Costs!$Q$16,Unit_Costs!$Q$30,Unit_Costs!$Q$44)+G32*Assumptions!$D$90*CHOOSE(Assumptions!$C$121,Unit_Costs!$Q$16,Unit_Costs!$Q$30,Unit_Costs!$Q$44)+G33*Assumptions!$D$91*CHOOSE(Assumptions!$C$121,Unit_Costs!$Q$16,Unit_Costs!$Q$30,Unit_Costs!$Q$44) -> 0 | H71: =H30*Assumptions!$D$88*CHOOSE(Assumptions!$C$121,Unit_Costs!$Q$16,Unit_Costs!$Q$30,Unit_Costs!$Q$44)+H31*Assumptions!$D$89*CHOOSE(Assumptions!$C$121,Unit_Costs!$Q$16,Unit_Costs!$Q$30,Unit_Costs!$Q$44)+H32*Assumptions!$D$90*CHOOSE(Assumptions!$C$121,Unit_Costs!$Q$16,Unit_Costs!$Q$30,Unit_Costs!$Q$44)+H33*Assumptions!$D$91*CHOOSE(Assumptions!$C$121,Unit_Costs!$Q$16,Unit_Costs!$Q$30,Unit_Costs!$Q$44) -> 0 | I71: =I30*Assumptions!$D$88*CHOOSE(Assumptions!$C$121,Unit_Costs!$Q$16,Unit_Costs!$Q$30,Unit_Costs!$Q$44)+I31*Assumptions!$D$89*CHOOSE(Assumptions!$C$121,Unit_Costs!$Q$16,Unit_Costs!$Q$30,Unit_Costs!$Q$44)+I32*Assumptions!$D$90*CHOOSE(Assumptions!$C$121,Unit_Costs!$Q$16,Unit_Costs!$Q$30,Unit_Costs!$Q$44)+I33*Assumptions!$D$91*CHOOSE(Assumptions!$C$121,Unit_Costs!$Q$16,Unit_Costs!$Q$30,Unit_Costs!$Q$44) -> 0 | J71: =J30*Assumptions!$D$88*CHOOSE(Assumptions!$C$121,Unit_Costs!$Q$16,Unit_Costs!$Q$30,Unit_Costs!$Q$44)+J31*Assumptions!$D$89*CHOOSE(Assumptions!$C$121,Unit_Costs!$Q$16,Unit_Costs!$Q$30,Unit_Costs!$Q$44)+J32*Assumptions!$D$90*CHOOSE(Assumptions!$C$121,Unit_Costs!$Q$16,Unit_Costs!$Q$30,Unit_Costs!$Q$44)+J33*Assumptions!$D$91*CHOOSE(Assumptions!$C$121,Unit_Costs!$Q$16,Unit_Costs!$Q$30,Unit_Costs!$Q$44) -> 0 | ... AL71: =AL30*Assumptions!$D$88*CHOOSE(Assumptions!$C$121,Unit_Costs!$Q$16,Unit_Costs!$Q$30,Unit_Costs!$Q$44)+AL31*Assumptions!$D$89*CHOOSE(Assumptions!$C$121,Unit_Costs!$Q$16,Unit_Costs!$Q$30,Unit_Costs!$Q$44)+AL32*Assumptions!$D$90*CHOOSE(Assumptions!$C$121,Unit_Costs!$Q$16,Unit_Costs!$Q$30,Unit_Costs!$Q$44)+AL33*Assumptions!$D$91*CHOOSE(Assumptions!$C$121,Unit_Costs!$Q$16,Unit_Costs!$Q$30,Unit_Costs!$Q$44) -> 4038.6108
A72: SSO connections (WorkOS) | B72: £ | C72: =(C30*Assumptions!$D$92+C31*Assumptions!$D$93+C32*Assumptions!$D$94+C33*Assumptions!$D$95)*Assumptions!$D$96*Assumptions!$D$6 -> 0 | D72: =(D30*Assumptions!$D$92+D31*Assumptions!$D$93+D32*Assumptions!$D$94+D33*Assumptions!$D$95)*Assumptions!$D$96*Assumptions!$D$6 -> 0 | E72: =(E30*Assumptions!$D$92+E31*Assumptions!$D$93+E32*Assumptions!$D$94+E33*Assumptions!$D$95)*Assumptions!$D$96*Assumptions!$D$6 -> 0 | F72: =(F30*Assumptions!$D$92+F31*Assumptions!$D$93+F32*Assumptions!$D$94+F33*Assumptions!$D$95)*Assumptions!$D$96*Assumptions!$D$6 -> 0 | G72: =(G30*Assumptions!$D$92+G31*Assumptions!$D$93+G32*Assumptions!$D$94+G33*Assumptions!$D$95)*Assumptions!$D$96*Assumptions!$D$6 -> 0 | H72: =(H30*Assumptions!$D$92+H31*Assumptions!$D$93+H32*Assumptions!$D$94+H33*Assumptions!$D$95)*Assumptions!$D$96*Assumptions!$D$6 -> 0 | I72: =(I30*Assumptions!$D$92+I31*Assumptions!$D$93+I32*Assumptions!$D$94+I33*Assumptions!$D$95)*Assumptions!$D$96*Assumptions!$D$6 -> 0 | J72: =(J30*Assumptions!$D$92+J31*Assumptions!$D$93+J32*Assumptions!$D$94+J33*Assumptions!$D$95)*Assumptions!$D$96*Assumptions!$D$6 -> 0 | ... AL72: =(AL30*Assumptions!$D$92+AL31*Assumptions!$D$93+AL32*Assumptions!$D$94+AL33*Assumptions!$D$95)*Assumptions!$D$96*Assumptions!$D$6 -> 143.06324
A73: Onboarding labour (new customers) | B73: £ | C73: =(C22*Assumptions!$D$105+C23*Assumptions!$D$106+C24*Assumptions!$D$107+C25*Assumptions!$D$108)*Assumptions!$D$109 -> 0 | D73: =(D22*Assumptions!$D$105+D23*Assumptions!$D$106+D24*Assumptions!$D$107+D25*Assumptions!$D$108)*Assumptions!$D$109 -> 0 | E73: =(E22*Assumptions!$D$105+E23*Assumptions!$D$106+E24*Assumptions!$D$107+E25*Assumptions!$D$108)*Assumptions!$D$109 -> 0 | F73: =(F22*Assumptions!$D$105+F23*Assumptions!$D$106+F24*Assumptions!$D$107+F25*Assumptions!$D$108)*Assumptions!$D$109 -> 0 | G73: =(G22*Assumptions!$D$105+G23*Assumptions!$D$106+G24*Assumptions!$D$107+G25*Assumptions!$D$108)*Assumptions!$D$109 -> 0 | H73: =(H22*Assumptions!$D$105+H23*Assumptions!$D$106+H24*Assumptions!$D$107+H25*Assumptions!$D$108)*Assumptions!$D$109 -> 0 | I73: =(I22*Assumptions!$D$105+I23*Assumptions!$D$106+I24*Assumptions!$D$107+I25*Assumptions!$D$108)*Assumptions!$D$109 -> 0 | J73: =(J22*Assumptions!$D$105+J23*Assumptions!$D$106+J24*Assumptions!$D$107+J25*Assumptions!$D$108)*Assumptions!$D$109 -> 0 | ... AL73: =(AL22*Assumptions!$D$105+AL23*Assumptions!$D$106+AL24*Assumptions!$D$107+AL25*Assumptions!$D$108)*Assumptions!$D$109 -> 457.8
A74: Delivery of additional developments | B74: £ | C74: =C58*CHOOSE(Assumptions!$C$121,Unit_Costs!$Q$14,Unit_Costs!$Q$28,Unit_Costs!$Q$42) -> 0 | D74: =D58*CHOOSE(Assumptions!$C$121,Unit_Costs!$Q$14,Unit_Costs!$Q$28,Unit_Costs!$Q$42) -> 0 | E74: =E58*CHOOSE(Assumptions!$C$121,Unit_Costs!$Q$14,Unit_Costs!$Q$28,Unit_Costs!$Q$42) -> 0 | F74: =F58*CHOOSE(Assumptions!$C$121,Unit_Costs!$Q$14,Unit_Costs!$Q$28,Unit_Costs!$Q$42) -> 0 | G74: =G58*CHOOSE(Assumptions!$C$121,Unit_Costs!$Q$14,Unit_Costs!$Q$28,Unit_Costs!$Q$42) -> 0 | H74: =H58*CHOOSE(Assumptions!$C$121,Unit_Costs!$Q$14,Unit_Costs!$Q$28,Unit_Costs!$Q$42) -> 0 | I74: =I58*CHOOSE(Assumptions!$C$121,Unit_Costs!$Q$14,Unit_Costs!$Q$28,Unit_Costs!$Q$42) -> 0 | J74: =J58*CHOOSE(Assumptions!$C$121,Unit_Costs!$Q$14,Unit_Costs!$Q$28,Unit_Costs!$Q$42) -> 0 | ... AL74: =AL58*CHOOSE(Assumptions!$C$121,Unit_Costs!$Q$14,Unit_Costs!$Q$28,Unit_Costs!$Q$42) -> 487.31155
A75: Payment processing fees | B75: £ | C75: =(C39+C50+C54)*Assumptions!$D$97+C30*Assumptions!$D$101+(C40+C51+C55)*Assumptions!$D$98+C31*Assumptions!$D$102+(C41+C52+C56)*Assumptions!$D$99+C32*Assumptions!$D$103+(C42+C53+C57)*Assumptions!$D$100+C33*Assumptions!$D$104+C59*Assumptions!$D$99 -> 0 | D75: =(D39+D50+D54)*Assumptions!$D$97+D30*Assumptions!$D$101+(D40+D51+D55)*Assumptions!$D$98+D31*Assumptions!$D$102+(D41+D52+D56)*Assumptions!$D$99+D32*Assumptions!$D$103+(D42+D53+D57)*Assumptions!$D$100+D33*Assumptions!$D$104+D59*Assumptions!$D$99 -> 0 | E75: =(E39+E50+E54)*Assumptions!$D$97+E30*Assumptions!$D$101+(E40+E51+E55)*Assumptions!$D$98+E31*Assumptions!$D$102+(E41+E52+E56)*Assumptions!$D$99+E32*Assumptions!$D$103+(E42+E53+E57)*Assumptions!$D$100+E33*Assumptions!$D$104+E59*Assumptions!$D$99 -> 0 | F75: =(F39+F50+F54)*Assumptions!$D$97+F30*Assumptions!$D$101+(F40+F51+F55)*Assumptions!$D$98+F31*Assumptions!$D$102+(F41+F52+F56)*Assumptions!$D$99+F32*Assumptions!$D$103+(F42+F53+F57)*Assumptions!$D$100+F33*Assumptions!$D$104+F59*Assumptions!$D$99 -> 0 | G75: =(G39+G50+G54)*Assumptions!$D$97+G30*Assumptions!$D$101+(G40+G51+G55)*Assumptions!$D$98+G31*Assumptions!$D$102+(G41+G52+G56)*Assumptions!$D$99+G32*Assumptions!$D$103+(G42+G53+G57)*Assumptions!$D$100+G33*Assumptions!$D$104+G59*Assumptions!$D$99 -> 0 | H75: =(H39+H50+H54)*Assumptions!$D$97+H30*Assumptions!$D$101+(H40+H51+H55)*Assumptions!$D$98+H31*Assumptions!$D$102+(H41+H52+H56)*Assumptions!$D$99+H32*Assumptions!$D$103+(H42+H53+H57)*Assumptions!$D$100+H33*Assumptions!$D$104+H59*Assumptions!$D$99 -> 0 | I75: =(I39+I50+I54)*Assumptions!$D$97+I30*Assumptions!$D$101+(I40+I51+I55)*Assumptions!$D$98+I31*Assumptions!$D$102+(I41+I52+I56)*Assumptions!$D$99+I32*Assumptions!$D$103+(I42+I53+I57)*Assumptions!$D$100+I33*Assumptions!$D$104+I59*Assumptions!$D$99 -> 0 | J75: =(J39+J50+J54)*Assumptions!$D$97+J30*Assumptions!$D$101+(J40+J51+J55)*Assumptions!$D$98+J31*Assumptions!$D$102+(J41+J52+J56)*Assumptions!$D$99+J32*Assumptions!$D$103+(J42+J53+J57)*Assumptions!$D$100+J33*Assumptions!$D$104+J59*Assumptions!$D$99 -> 0 | ... AL75: =(AL39+AL50+AL54)*Assumptions!$D$97+AL30*Assumptions!$D$101+(AL40+AL51+AL55)*Assumptions!$D$98+AL31*Assumptions!$D$102+(AL41+AL52+AL56)*Assumptions!$D$99+AL32*Assumptions!$D$103+(AL42+AL53+AL57)*Assumptions!$D$100+AL33*Assumptions!$D$104+AL59*Assumptions!$D$99 -> 478.27588
A76: Platform infrastructure | B76: £ | C76: =Assumptions!$D$172+Assumptions!$D$173*C36 -> 300 | D76: =Assumptions!$D$172+Assumptions!$D$173*D36 -> 300 | E76: =Assumptions!$D$172+Assumptions!$D$173*E36 -> 300 | F76: =Assumptions!$D$172+Assumptions!$D$173*F36 -> 300 | G76: =Assumptions!$D$172+Assumptions!$D$173*G36 -> 300 | H76: =Assumptions!$D$172+Assumptions!$D$173*H36 -> 300 | I76: =Assumptions!$D$172+Assumptions!$D$173*I36 -> 300 | J76: =Assumptions!$D$172+Assumptions!$D$173*J36 -> 300 | ... AL76: =Assumptions!$D$172+Assumptions!$D$173*AL36 -> 399.69299
A77: ODA Drawings SDK licence (DWG) | B77: £ | C77: =IF(C$3=Assumptions!$D$176,Assumptions!$D$174,IF(AND(C$3>Assumptions!$D$176,MOD(C$3-Assumptions!$D$176,12)=0),Assumptions!$D$175,0))*Assumptions!$D$6 -> 0 | D77: =IF(D$3=Assumptions!$D$176,Assumptions!$D$174,IF(AND(D$3>Assumptions!$D$176,MOD(D$3-Assumptions!$D$176,12)=0),Assumptions!$D$175,0))*Assumptions!$D$6 -> 0 | E77: =IF(E$3=Assumptions!$D$176,Assumptions!$D$174,IF(AND(E$3>Assumptions!$D$176,MOD(E$3-Assumptions!$D$176,12)=0),Assumptions!$D$175,0))*Assumptions!$D$6 -> 0 | F77: =IF(F$3=Assumptions!$D$176,Assumptions!$D$174,IF(AND(F$3>Assumptions!$D$176,MOD(F$3-Assumptions!$D$176,12)=0),Assumptions!$D$175,0))*Assumptions!$D$6 -> 0 | G77: =IF(G$3=Assumptions!$D$176,Assumptions!$D$174,IF(AND(G$3>Assumptions!$D$176,MOD(G$3-Assumptions!$D$176,12)=0),Assumptions!$D$175,0))*Assumptions!$D$6 -> 0 | H77: =IF(H$3=Assumptions!$D$176,Assumptions!$D$174,IF(AND(H$3>Assumptions!$D$176,MOD(H$3-Assumptions!$D$176,12)=0),Assumptions!$D$175,0))*Assumptions!$D$6 -> 0 | I77: =IF(I$3=Assumptions!$D$176,Assumptions!$D$174,IF(AND(I$3>Assumptions!$D$176,MOD(I$3-Assumptions!$D$176,12)=0),Assumptions!$D$175,0))*Assumptions!$D$6 -> 0 | J77: =IF(J$3=Assumptions!$D$176,Assumptions!$D$174,IF(AND(J$3>Assumptions!$D$176,MOD(J$3-Assumptions!$D$176,12)=0),Assumptions!$D$175,0))*Assumptions!$D$6 -> 5662.5 | ... AL77: =IF(AL$3=Assumptions!$D$176,Assumptions!$D$174,IF(AND(AL$3>Assumptions!$D$176,MOD(AL$3-Assumptions!$D$176,12)=0),Assumptions!$D$175,0))*Assumptions!$D$6 -> 0
A78: Total COGS | B78: £ | C78: =SUM(C66:C77) -> 300 | D78: =SUM(D66:D77) -> 300 | E78: =SUM(E66:E77) -> 300 | F78: =SUM(F66:F77) -> 300 | G78: =SUM(G66:G77) -> 300 | H78: =SUM(H66:H77) -> 300 | I78: =SUM(I66:I77) -> 300 | J78: =SUM(J66:J77) -> 5962.5 | ... AL78: =SUM(AL66:AL77) -> 21671.337
A79: Gross profit | B79: £ | C79: =C63-C78 -> -300 | D79: =D63-D78 -> -300 | E79: =E63-E78 -> -300 | F79: =F63-F78 -> -300 | G79: =G63-G78 -> -300 | H79: =H63-H78 -> -300 | I79: =I63-I78 -> -300 | J79: =J63-J78 -> -5962.5 | ... AL79: =AL63-AL78 -> 5755.3908
A80: Gross margin | B80: % | C80: =IF(C63=0,0,C79/C63) -> 0 | D80: =IF(D63=0,0,D79/D63) -> 0 | E80: =IF(E63=0,0,E79/E63) -> 0 | F80: =IF(F63=0,0,F79/F63) -> 0 | G80: =IF(G63=0,0,G79/G63) -> 0 | H80: =IF(H63=0,0,H79/H63) -> 0 | I80: =IF(I63=0,0,I79/I63) -> 0 | J80: =IF(J63=0,0,J79/J63) -> 0 | ... AL80: =IF(AL63=0,0,AL79/AL63) -> 0.20984606
A82: Operating expenses
A83: Founder salary (incl. on-costs) | B83: £ | C83: =Assumptions!$D$161*(1+Assumptions!$D$162)/12 -> 3000 | D83: =Assumptions!$D$161*(1+Assumptions!$D$162)/12 -> 3000 | E83: =Assumptions!$D$161*(1+Assumptions!$D$162)/12 -> 3000 | F83: =Assumptions!$D$161*(1+Assumptions!$D$162)/12 -> 3000 | G83: =Assumptions!$D$161*(1+Assumptions!$D$162)/12 -> 3000 | H83: =Assumptions!$D$161*(1+Assumptions!$D$162)/12 -> 3000 | I83: =Assumptions!$D$161*(1+Assumptions!$D$162)/12 -> 3000 | J83: =Assumptions!$D$161*(1+Assumptions!$D$162)/12 -> 3000 | ... AL83: =Assumptions!$D$161*(1+Assumptions!$D$162)/12 -> 3000
A84: Customer support / QA lead #1 (incl. on-costs) | B84: £ | C84: =C7*Assumptions!$D$187*(1+Assumptions!$D$162)/12 -> 0 | D84: =D7*Assumptions!$D$187*(1+Assumptions!$D$162)/12 -> 0 | E84: =E7*Assumptions!$D$187*(1+Assumptions!$D$162)/12 -> 0 | F84: =F7*Assumptions!$D$187*(1+Assumptions!$D$162)/12 -> 0 | G84: =G7*Assumptions!$D$187*(1+Assumptions!$D$162)/12 -> 0 | H84: =H7*Assumptions!$D$187*(1+Assumptions!$D$162)/12 -> 0 | I84: =I7*Assumptions!$D$187*(1+Assumptions!$D$162)/12 -> 0 | J84: =J7*Assumptions!$D$187*(1+Assumptions!$D$162)/12 -> 0 | ... AL84: =AL7*Assumptions!$D$187*(1+Assumptions!$D$162)/12 -> 3200
A85: Senior engineer #1 (incl. on-costs) | B85: £ | C85: =C8*Assumptions!$D$188*(1+Assumptions!$D$162)/12 -> 0 | D85: =D8*Assumptions!$D$188*(1+Assumptions!$D$162)/12 -> 0 | E85: =E8*Assumptions!$D$188*(1+Assumptions!$D$162)/12 -> 0 | F85: =F8*Assumptions!$D$188*(1+Assumptions!$D$162)/12 -> 0 | G85: =G8*Assumptions!$D$188*(1+Assumptions!$D$162)/12 -> 0 | H85: =H8*Assumptions!$D$188*(1+Assumptions!$D$162)/12 -> 0 | I85: =I8*Assumptions!$D$188*(1+Assumptions!$D$162)/12 -> 0 | J85: =J8*Assumptions!$D$188*(1+Assumptions!$D$162)/12 -> 0 | ... AL85: =AL8*Assumptions!$D$188*(1+Assumptions!$D$162)/12 -> 8500
A86: Account executive #1 (developers) (incl. on-costs) | B86: £ | C86: =C9*Assumptions!$D$189*(1+Assumptions!$D$162)/12 -> 0 | D86: =D9*Assumptions!$D$189*(1+Assumptions!$D$162)/12 -> 0 | E86: =E9*Assumptions!$D$189*(1+Assumptions!$D$162)/12 -> 0 | F86: =F9*Assumptions!$D$189*(1+Assumptions!$D$162)/12 -> 0 | G86: =G9*Assumptions!$D$189*(1+Assumptions!$D$162)/12 -> 0 | H86: =H9*Assumptions!$D$189*(1+Assumptions!$D$162)/12 -> 0 | I86: =I9*Assumptions!$D$189*(1+Assumptions!$D$162)/12 -> 0 | J86: =J9*Assumptions!$D$189*(1+Assumptions!$D$162)/12 -> 0 | ... AL86: =AL9*Assumptions!$D$189*(1+Assumptions!$D$162)/12 -> 0
A87: Founder salary uplift to market (incl. on-costs) | B87: £ | C87: =C10*Assumptions!$D$190*(1+Assumptions!$D$162)/12 -> 0 | D87: =D10*Assumptions!$D$190*(1+Assumptions!$D$162)/12 -> 0 | E87: =E10*Assumptions!$D$190*(1+Assumptions!$D$162)/12 -> 0 | F87: =F10*Assumptions!$D$190*(1+Assumptions!$D$162)/12 -> 0 | G87: =G10*Assumptions!$D$190*(1+Assumptions!$D$162)/12 -> 0 | H87: =H10*Assumptions!$D$190*(1+Assumptions!$D$162)/12 -> 0 | I87: =I10*Assumptions!$D$190*(1+Assumptions!$D$162)/12 -> 0 | J87: =J10*Assumptions!$D$190*(1+Assumptions!$D$162)/12 -> 0 | ... AL87: =AL10*Assumptions!$D$190*(1+Assumptions!$D$162)/12 -> 0
A88: Senior engineer #2 (incl. on-costs) | B88: £ | C88: =C11*Assumptions!$D$191*(1+Assumptions!$D$162)/12 -> 0 | D88: =D11*Assumptions!$D$191*(1+Assumptions!$D$162)/12 -> 0 | E88: =E11*Assumptions!$D$191*(1+Assumptions!$D$162)/12 -> 0 | F88: =F11*Assumptions!$D$191*(1+Assumptions!$D$162)/12 -> 0 | G88: =G11*Assumptions!$D$191*(1+Assumptions!$D$162)/12 -> 0 | H88: =H11*Assumptions!$D$191*(1+Assumptions!$D$162)/12 -> 0 | I88: =I11*Assumptions!$D$191*(1+Assumptions!$D$162)/12 -> 0 | J88: =J11*Assumptions!$D$191*(1+Assumptions!$D$162)/12 -> 0 | ... AL88: =AL11*Assumptions!$D$191*(1+Assumptions!$D$162)/12 -> 0
A89: Customer success #2 (incl. on-costs) | B89: £ | C89: =C12*Assumptions!$D$192*(1+Assumptions!$D$162)/12 -> 0 | D89: =D12*Assumptions!$D$192*(1+Assumptions!$D$162)/12 -> 0 | E89: =E12*Assumptions!$D$192*(1+Assumptions!$D$162)/12 -> 0 | F89: =F12*Assumptions!$D$192*(1+Assumptions!$D$162)/12 -> 0 | G89: =G12*Assumptions!$D$192*(1+Assumptions!$D$162)/12 -> 0 | H89: =H12*Assumptions!$D$192*(1+Assumptions!$D$162)/12 -> 0 | I89: =I12*Assumptions!$D$192*(1+Assumptions!$D$162)/12 -> 0 | J89: =J12*Assumptions!$D$192*(1+Assumptions!$D$162)/12 -> 0 | ... AL89: =AL12*Assumptions!$D$192*(1+Assumptions!$D$162)/12 -> 0
A90: Marketing manager (incl. on-costs) | B90: £ | C90: =C13*Assumptions!$D$193*(1+Assumptions!$D$162)/12 -> 0 | D90: =D13*Assumptions!$D$193*(1+Assumptions!$D$162)/12 -> 0 | E90: =E13*Assumptions!$D$193*(1+Assumptions!$D$162)/12 -> 0 | F90: =F13*Assumptions!$D$193*(1+Assumptions!$D$162)/12 -> 0 | G90: =G13*Assumptions!$D$193*(1+Assumptions!$D$162)/12 -> 0 | H90: =H13*Assumptions!$D$193*(1+Assumptions!$D$162)/12 -> 0 | I90: =I13*Assumptions!$D$193*(1+Assumptions!$D$162)/12 -> 0 | J90: =J13*Assumptions!$D$193*(1+Assumptions!$D$162)/12 -> 0 | ... AL90: =AL13*Assumptions!$D$193*(1+Assumptions!$D$162)/12 -> 0
A91: Account executive #2 (incl. on-costs) | B91: £ | C91: =C14*Assumptions!$D$194*(1+Assumptions!$D$162)/12 -> 0 | D91: =D14*Assumptions!$D$194*(1+Assumptions!$D$162)/12 -> 0 | E91: =E14*Assumptions!$D$194*(1+Assumptions!$D$162)/12 -> 0 | F91: =F14*Assumptions!$D$194*(1+Assumptions!$D$162)/12 -> 0 | G91: =G14*Assumptions!$D$194*(1+Assumptions!$D$162)/12 -> 0 | H91: =H14*Assumptions!$D$194*(1+Assumptions!$D$162)/12 -> 0 | I91: =I14*Assumptions!$D$194*(1+Assumptions!$D$162)/12 -> 0 | J91: =J14*Assumptions!$D$194*(1+Assumptions!$D$162)/12 -> 0 | ... AL91: =AL14*Assumptions!$D$194*(1+Assumptions!$D$162)/12 -> 0
A92: Graphics / 3D engineer #3 (incl. on-costs) | B92: £ | C92: =C15*Assumptions!$D$195*(1+Assumptions!$D$162)/12 -> 0 | D92: =D15*Assumptions!$D$195*(1+Assumptions!$D$162)/12 -> 0 | E92: =E15*Assumptions!$D$195*(1+Assumptions!$D$162)/12 -> 0 | F92: =F15*Assumptions!$D$195*(1+Assumptions!$D$162)/12 -> 0 | G92: =G15*Assumptions!$D$195*(1+Assumptions!$D$162)/12 -> 0 | H92: =H15*Assumptions!$D$195*(1+Assumptions!$D$162)/12 -> 0 | I92: =I15*Assumptions!$D$195*(1+Assumptions!$D$162)/12 -> 0 | J92: =J15*Assumptions!$D$195*(1+Assumptions!$D$162)/12 -> 0 | ... AL92: =AL15*Assumptions!$D$195*(1+Assumptions!$D$162)/12 -> 0
A93: Customer success #3 (incl. on-costs) | B93: £ | C93: =C16*Assumptions!$D$196*(1+Assumptions!$D$162)/12 -> 0 | D93: =D16*Assumptions!$D$196*(1+Assumptions!$D$162)/12 -> 0 | E93: =E16*Assumptions!$D$196*(1+Assumptions!$D$162)/12 -> 0 | F93: =F16*Assumptions!$D$196*(1+Assumptions!$D$162)/12 -> 0 | G93: =G16*Assumptions!$D$196*(1+Assumptions!$D$162)/12 -> 0 | H93: =H16*Assumptions!$D$196*(1+Assumptions!$D$162)/12 -> 0 | I93: =I16*Assumptions!$D$196*(1+Assumptions!$D$162)/12 -> 0 | J93: =J16*Assumptions!$D$196*(1+Assumptions!$D$162)/12 -> 0 | ... AL93: =AL16*Assumptions!$D$196*(1+Assumptions!$D$162)/12 -> 0
A94: Recruitment fees (hire month) | B94: £ | C94: =C7*Assumptions!$D$187*Assumptions!$E$187+C8*Assumptions!$D$188*Assumptions!$E$188+C9*Assumptions!$D$189*Assumptions!$E$189+C10*Assumptions!$D$190*Assumptions!$E$190+C11*Assumptions!$D$191*Assumptions!$E$191+C12*Assumptions!$D$192*Assumptions!$E$192+C13*Assumptions!$D$193*Assumptions!$E$193+C14*Assumptions!$D$194*Assumptions!$E$194+C15*Assumptions!$D$195*Assumptions!$E$195+C16*Assumptions!$D$196*Assumptions!$E$196 -> 0 | D94: =(D7-C7)*Assumptions!$D$187*Assumptions!$E$187+(D8-C8)*Assumptions!$D$188*Assumptions!$E$188+(D9-C9)*Assumptions!$D$189*Assumptions!$E$189+(D10-C10)*Assumptions!$D$190*Assumptions!$E$190+(D11-C11)*Assumptions!$D$191*Assumptions!$E$191+(D12-C12)*Assumptions!$D$192*Assumptions!$E$192+(D13-C13)*Assumptions!$D$193*Assumptions!$E$193+(D14-C14)*Assumptions!$D$194*Assumptions!$E$194+(D15-C15)*Assumptions!$D$195*Assumptions!$E$195+(D16-C16)*Assumptions!$D$196*Assumptions!$E$196 -> 0 | E94: =(E7-D7)*Assumptions!$D$187*Assumptions!$E$187+(E8-D8)*Assumptions!$D$188*Assumptions!$E$188+(E9-D9)*Assumptions!$D$189*Assumptions!$E$189+(E10-D10)*Assumptions!$D$190*Assumptions!$E$190+(E11-D11)*Assumptions!$D$191*Assumptions!$E$191+(E12-D12)*Assumptions!$D$192*Assumptions!$E$192+(E13-D13)*Assumptions!$D$193*Assumptions!$E$193+(E14-D14)*Assumptions!$D$194*Assumptions!$E$194+(E15-D15)*Assumptions!$D$195*Assumptions!$E$195+(E16-D16)*Assumptions!$D$196*Assumptions!$E$196 -> 0 | F94: =(F7-E7)*Assumptions!$D$187*Assumptions!$E$187+(F8-E8)*Assumptions!$D$188*Assumptions!$E$188+(F9-E9)*Assumptions!$D$189*Assumptions!$E$189+(F10-E10)*Assumptions!$D$190*Assumptions!$E$190+(F11-E11)*Assumptions!$D$191*Assumptions!$E$191+(F12-E12)*Assumptions!$D$192*Assumptions!$E$192+(F13-E13)*Assumptions!$D$193*Assumptions!$E$193+(F14-E14)*Assumptions!$D$194*Assumptions!$E$194+(F15-E15)*Assumptions!$D$195*Assumptions!$E$195+(F16-E16)*Assumptions!$D$196*Assumptions!$E$196 -> 0 | G94: =(G7-F7)*Assumptions!$D$187*Assumptions!$E$187+(G8-F8)*Assumptions!$D$188*Assumptions!$E$188+(G9-F9)*Assumptions!$D$189*Assumptions!$E$189+(G10-F10)*Assumptions!$D$190*Assumptions!$E$190+(G11-F11)*Assumptions!$D$191*Assumptions!$E$191+(G12-F12)*Assumptions!$D$192*Assumptions!$E$192+(G13-F13)*Assumptions!$D$193*Assumptions!$E$193+(G14-F14)*Assumptions!$D$194*Assumptions!$E$194+(G15-F15)*Assumptions!$D$195*Assumptions!$E$195+(G16-F16)*Assumptions!$D$196*Assumptions!$E$196 -> 0 | H94: =(H7-G7)*Assumptions!$D$187*Assumptions!$E$187+(H8-G8)*Assumptions!$D$188*Assumptions!$E$188+(H9-G9)*Assumptions!$D$189*Assumptions!$E$189+(H10-G10)*Assumptions!$D$190*Assumptions!$E$190+(H11-G11)*Assumptions!$D$191*Assumptions!$E$191+(H12-G12)*Assumptions!$D$192*Assumptions!$E$192+(H13-G13)*Assumptions!$D$193*Assumptions!$E$193+(H14-G14)*Assumptions!$D$194*Assumptions!$E$194+(H15-G15)*Assumptions!$D$195*Assumptions!$E$195+(H16-G16)*Assumptions!$D$196*Assumptions!$E$196 -> 0 | I94: =(I7-H7)*Assumptions!$D$187*Assumptions!$E$187+(I8-H8)*Assumptions!$D$188*Assumptions!$E$188+(I9-H9)*Assumptions!$D$189*Assumptions!$E$189+(I10-H10)*Assumptions!$D$190*Assumptions!$E$190+(I11-H11)*Assumptions!$D$191*Assumptions!$E$191+(I12-H12)*Assumptions!$D$192*Assumptions!$E$192+(I13-H13)*Assumptions!$D$193*Assumptions!$E$193+(I14-H14)*Assumptions!$D$194*Assumptions!$E$194+(I15-H15)*Assumptions!$D$195*Assumptions!$E$195+(I16-H16)*Assumptions!$D$196*Assumptions!$E$196 -> 0 | J94: =(J7-I7)*Assumptions!$D$187*Assumptions!$E$187+(J8-I8)*Assumptions!$D$188*Assumptions!$E$188+(J9-I9)*Assumptions!$D$189*Assumptions!$E$189+(J10-I10)*Assumptions!$D$190*Assumptions!$E$190+(J11-I11)*Assumptions!$D$191*Assumptions!$E$191+(J12-I12)*Assumptions!$D$192*Assumptions!$E$192+(J13-I13)*Assumptions!$D$193*Assumptions!$E$193+(J14-I14)*Assumptions!$D$194*Assumptions!$E$194+(J15-I15)*Assumptions!$D$195*Assumptions!$E$195+(J16-I16)*Assumptions!$D$196*Assumptions!$E$196 -> 0 | K94: =(K7-J7)*Assumptions!$D$187*Assumptions!$E$187+(K8-J8)*Assumptions!$D$188*Assumptions!$E$188+(K9-J9)*Assumptions!$D$189*Assumptions!$E$189+(K10-J10)*Assumptions!$D$190*Assumptions!$E$190+(K11-J11)*Assumptions!$D$191*Assumptions!$E$191+(K12-J12)*Assumptions!$D$192*Assumptions!$E$192+(K13-J13)*Assumptions!$D$193*Assumptions!$E$193+(K14-J14)*Assumptions!$D$194*Assumptions!$E$194+(K15-J15)*Assumptions!$D$195*Assumptions!$E$195+(K16-J16)*Assumptions!$D$196*Assumptions!$E$196 -> 0 | ... AL94: =(AL7-AK7)*Assumptions!$D$187*Assumptions!$E$187+(AL8-AK8)*Assumptions!$D$188*Assumptions!$E$188+(AL9-AK9)*Assumptions!$D$189*Assumptions!$E$189+(AL10-AK10)*Assumptions!$D$190*Assumptions!$E$190+(AL11-AK11)*Assumptions!$D$191*Assumptions!$E$191+(AL12-AK12)*Assumptions!$D$192*Assumptions!$E$192+(AL13-AK13)*Assumptions!$D$193*Assumptions!$E$193+(AL14-AK14)*Assumptions!$D$194*Assumptions!$E$194+(AL15-AK15)*Assumptions!$D$195*Assumptions!$E$195+(AL16-AK16)*Assumptions!$D$196*Assumptions!$E$196 -> 0
A95: Contract engineering (until Engineer #1) | B95: £ | C95: =IF(C8=0,Assumptions!$D$163,0) -> 2000 | D95: =IF(D8=0,Assumptions!$D$163,0) -> 2000 | E95: =IF(E8=0,Assumptions!$D$163,0) -> 2000 | F95: =IF(F8=0,Assumptions!$D$163,0) -> 2000 | G95: =IF(G8=0,Assumptions!$D$163,0) -> 2000 | H95: =IF(H8=0,Assumptions!$D$163,0) -> 2000 | I95: =IF(I8=0,Assumptions!$D$163,0) -> 2000 | J95: =IF(J8=0,Assumptions!$D$163,0) -> 2000 | ... AL95: =IF(AL8=0,Assumptions!$D$163,0) -> 0
A96: Marketing programmes + events | B96: £ | C96: =Assumptions!$D$164+Assumptions!$D$165/12 -> 2250 | D96: =Assumptions!$D$164+Assumptions!$D$165/12 -> 2250 | E96: =Assumptions!$D$164+Assumptions!$D$165/12 -> 2250 | F96: =Assumptions!$D$164+Assumptions!$D$165/12 -> 2250 | G96: =Assumptions!$D$164+Assumptions!$D$165/12 -> 2250 | H96: =Assumptions!$D$164+Assumptions!$D$165/12 -> 2250 | I96: =Assumptions!$D$164+Assumptions!$D$165/12 -> 2250 | J96: =Assumptions!$D$164+Assumptions!$D$165/12 -> 2250 | ... AL96: =Assumptions!$D$164+Assumptions!$D$165/12 -> 2250
A97: Channel & data subscriptions (Reapit network, Barbour ABI) | B97: £ | C97: =Assumptions!$D$166/12+IF(C$3>=Assumptions!$C$124,Assumptions!$D$167/12,0) -> 125 | D97: =Assumptions!$D$166/12+IF(D$3>=Assumptions!$C$124,Assumptions!$D$167/12,0) -> 125 | E97: =Assumptions!$D$166/12+IF(E$3>=Assumptions!$C$124,Assumptions!$D$167/12,0) -> 125 | F97: =Assumptions!$D$166/12+IF(F$3>=Assumptions!$C$124,Assumptions!$D$167/12,0) -> 125 | G97: =Assumptions!$D$166/12+IF(G$3>=Assumptions!$C$124,Assumptions!$D$167/12,0) -> 125 | H97: =Assumptions!$D$166/12+IF(H$3>=Assumptions!$C$124,Assumptions!$D$167/12,0) -> 125 | I97: =Assumptions!$D$166/12+IF(I$3>=Assumptions!$C$124,Assumptions!$D$167/12,0) -> 125 | J97: =Assumptions!$D$166/12+IF(J$3>=Assumptions!$C$124,Assumptions!$D$167/12,0) -> 125 | ... AL97: =Assumptions!$D$166/12+IF(AL$3>=Assumptions!$C$124,Assumptions!$D$167/12,0) -> 458.33333
A98: Variable marketing (% revenue) | B98: £ | C98: =C63*Assumptions!$D$168 -> 0 | D98: =D63*Assumptions!$D$168 -> 0 | E98: =E63*Assumptions!$D$168 -> 0 | F98: =F63*Assumptions!$D$168 -> 0 | G98: =G63*Assumptions!$D$168 -> 0 | H98: =H63*Assumptions!$D$168 -> 0 | I98: =I63*Assumptions!$D$168 -> 0 | J98: =J63*Assumptions!$D$168 -> 0 | ... AL98: =AL63*Assumptions!$D$168 -> 1371.3364
A99: Sales commission (Developer Pro + Enterprise new ACV) | B99: £ | C99: =IF(C18>0,(C24*Assumptions!$D$75*Assumptions!$C$151+C25*Assumptions!$D$76*Assumptions!$C$152)*12*Assumptions!$D$169,0) -> 0 | D99: =IF(D18>0,(D24*Assumptions!$D$75*Assumptions!$C$151+D25*Assumptions!$D$76*Assumptions!$C$152)*12*Assumptions!$D$169,0) -> 0 | E99: =IF(E18>0,(E24*Assumptions!$D$75*Assumptions!$C$151+E25*Assumptions!$D$76*Assumptions!$C$152)*12*Assumptions!$D$169,0) -> 0 | F99: =IF(F18>0,(F24*Assumptions!$D$75*Assumptions!$C$151+F25*Assumptions!$D$76*Assumptions!$C$152)*12*Assumptions!$D$169,0) -> 0 | G99: =IF(G18>0,(G24*Assumptions!$D$75*Assumptions!$C$151+G25*Assumptions!$D$76*Assumptions!$C$152)*12*Assumptions!$D$169,0) -> 0 | H99: =IF(H18>0,(H24*Assumptions!$D$75*Assumptions!$C$151+H25*Assumptions!$D$76*Assumptions!$C$152)*12*Assumptions!$D$169,0) -> 0 | I99: =IF(I18>0,(I24*Assumptions!$D$75*Assumptions!$C$151+I25*Assumptions!$D$76*Assumptions!$C$152)*12*Assumptions!$D$169,0) -> 0 | J99: =IF(J18>0,(J24*Assumptions!$D$75*Assumptions!$C$151+J25*Assumptions!$D$76*Assumptions!$C$152)*12*Assumptions!$D$169,0) -> 0 | ... AL99: =IF(AL18>0,(AL24*Assumptions!$D$75*Assumptions!$C$151+AL25*Assumptions!$D$76*Assumptions!$C$152)*12*Assumptions!$D$169,0) -> 0
A100: Software & tools | B100: £ | C100: =Assumptions!$D$170+Assumptions!$D$171*C17 -> 440 | D100: =Assumptions!$D$170+Assumptions!$D$171*D17 -> 440 | E100: =Assumptions!$D$170+Assumptions!$D$171*E17 -> 440 | F100: =Assumptions!$D$170+Assumptions!$D$171*F17 -> 440 | G100: =Assumptions!$D$170+Assumptions!$D$171*G17 -> 440 | H100: =Assumptions!$D$170+Assumptions!$D$171*H17 -> 440 | I100: =Assumptions!$D$170+Assumptions!$D$171*I17 -> 440 | J100: =Assumptions!$D$170+Assumptions!$D$171*J17 -> 440 | ... AL100: =Assumptions!$D$170+Assumptions!$D$171*AL17 -> 520
A101: ISO 27001 programme + compliance platform | B101: £ | C101: =IF(C$3<Assumptions!$C$157,0,IF(C$3<Assumptions!$C$157+12,Assumptions!$D$177/12,Assumptions!$D$178/12)) -> 0 | D101: =IF(D$3<Assumptions!$C$157,0,IF(D$3<Assumptions!$C$157+12,Assumptions!$D$177/12,Assumptions!$D$178/12)) -> 0 | E101: =IF(E$3<Assumptions!$C$157,0,IF(E$3<Assumptions!$C$157+12,Assumptions!$D$177/12,Assumptions!$D$178/12)) -> 0 | F101: =IF(F$3<Assumptions!$C$157,0,IF(F$3<Assumptions!$C$157+12,Assumptions!$D$177/12,Assumptions!$D$178/12)) -> 0 | G101: =IF(G$3<Assumptions!$C$157,0,IF(G$3<Assumptions!$C$157+12,Assumptions!$D$177/12,Assumptions!$D$178/12)) -> 0 | H101: =IF(H$3<Assumptions!$C$157,0,IF(H$3<Assumptions!$C$157+12,Assumptions!$D$177/12,Assumptions!$D$178/12)) -> 0 | I101: =IF(I$3<Assumptions!$C$157,0,IF(I$3<Assumptions!$C$157+12,Assumptions!$D$177/12,Assumptions!$D$178/12)) -> 0 | J101: =IF(J$3<Assumptions!$C$157,0,IF(J$3<Assumptions!$C$157+12,Assumptions!$D$177/12,Assumptions!$D$178/12)) -> 0 | ... AL101: =IF(AL$3<Assumptions!$C$157,0,IF(AL$3<Assumptions!$C$157+12,Assumptions!$D$177/12,Assumptions!$D$178/12)) -> 833.33333
A102: Insurance (cyber, PI, public liability) | B102: £ | C102: =Assumptions!$D$179/12 -> 333.33333 | D102: =Assumptions!$D$179/12 -> 333.33333 | E102: =Assumptions!$D$179/12 -> 333.33333 | F102: =Assumptions!$D$179/12 -> 333.33333 | G102: =Assumptions!$D$179/12 -> 333.33333 | H102: =Assumptions!$D$179/12 -> 333.33333 | I102: =Assumptions!$D$179/12 -> 333.33333 | J102: =Assumptions!$D$179/12 -> 333.33333 | ... AL102: =Assumptions!$D$179/12 -> 333.33333
A103: Legal, accounting, admin | B103: £ | C103: =Assumptions!$D$180+IF(C$3=1,Assumptions!$D$181,0) -> 5400 | D103: =Assumptions!$D$180+IF(D$3=1,Assumptions!$D$181,0) -> 400 | E103: =Assumptions!$D$180+IF(E$3=1,Assumptions!$D$181,0) -> 400 | F103: =Assumptions!$D$180+IF(F$3=1,Assumptions!$D$181,0) -> 400 | G103: =Assumptions!$D$180+IF(G$3=1,Assumptions!$D$181,0) -> 400 | H103: =Assumptions!$D$180+IF(H$3=1,Assumptions!$D$181,0) -> 400 | I103: =Assumptions!$D$180+IF(I$3=1,Assumptions!$D$181,0) -> 400 | J103: =Assumptions!$D$180+IF(J$3=1,Assumptions!$D$181,0) -> 400 | ... AL103: =Assumptions!$D$180+IF(AL$3=1,Assumptions!$D$181,0) -> 400
A104: Total operating expenses | B104: £ | C104: =SUM(C83:C103) -> 13548.333 | D104: =SUM(D83:D103) -> 8548.3333 | E104: =SUM(E83:E103) -> 8548.3333 | F104: =SUM(F83:F103) -> 8548.3333 | G104: =SUM(G83:G103) -> 8548.3333 | H104: =SUM(H83:H103) -> 8548.3333 | I104: =SUM(I83:I103) -> 8548.3333 | J104: =SUM(J83:J103) -> 8548.3333 | ... AL104: =SUM(AL83:AL103) -> 20866.336
A105: memo: engineering (eng hires + contract) | B105: £ | C105: =C85+C88+C92+C95 -> 2000 | D105: =D85+D88+D92+D95 -> 2000 | E105: =E85+E88+E92+E95 -> 2000 | F105: =F85+F88+F92+F95 -> 2000 | G105: =G85+G88+G92+G95 -> 2000 | H105: =H85+H88+H92+H95 -> 2000 | I105: =I85+I88+I92+I95 -> 2000 | J105: =J85+J88+J92+J95 -> 2000 | ... AL105: =AL85+AL88+AL92+AL95 -> 8500
A106: memo: sales & marketing (AEs, marketing hire, programmes, commission) | B106: £ | C106: =C86+C91+C90+C96+C97+C98+C99 -> 2375 | D106: =D86+D91+D90+D96+D97+D98+D99 -> 2375 | E106: =E86+E91+E90+E96+E97+E98+E99 -> 2375 | F106: =F86+F91+F90+F96+F97+F98+F99 -> 2375 | G106: =G86+G91+G90+G96+G97+G98+G99 -> 2375 | H106: =H86+H91+H90+H96+H97+H98+H99 -> 2375 | I106: =I86+I91+I90+I96+I97+I98+I99 -> 2375 | J106: =J86+J91+J90+J96+J97+J98+J99 -> 2375 | ... AL106: =AL86+AL91+AL90+AL96+AL97+AL98+AL99 -> 4079.6697
...

Sheet Model_Base
A1: Model Base scenario — monthly model, 36 months (£). All cells are formulas driven by Assumptions column D.
A3: Month | B3: Unit | C3: 1 | D3: 2 | E3: 3 | F3: 4 | G3: 5 | H3: 6 | I3: 7 | J3: 8 | K3: 9 | L3: 10 | M3: 11 | N3: 12 | O3: 13 | P3: 14 | Q3: 15 | R3: 16 | S3: 17 | T3: 18 | U3: 19 | V3: 20 | W3: 21 | X3: 22 | Y3: 23 | Z3: 24 | AA3: 25 | AB3: 26 | AC3: 27 | AD3: 28 | AE3: 29 | AF3: 30 | AG3: 31 | AH3: 32 | AI3: 33 | AJ3: 34 | AK3: 35 | AL3: 36
A4: Year | C4: ="Y"&ROUNDUP(C$3/12,0) -> Y1 | D4: ="Y"&ROUNDUP(D$3/12,0) -> Y1 | E4: ="Y"&ROUNDUP(E$3/12,0) -> Y1 | F4: ="Y"&ROUNDUP(F$3/12,0) -> Y1 | G4: ="Y"&ROUNDUP(G$3/12,0) -> Y1 | H4: ="Y"&ROUNDUP(H$3/12,0) -> Y1 | I4: ="Y"&ROUNDUP(I$3/12,0) -> Y1 | J4: ="Y"&ROUNDUP(J$3/12,0) -> Y1 | ... AL4: ="Y"&ROUNDUP(AL$3/12,0) -> Y3
A6: Headcount (step functions; triggers evaluated on previous month)
A7: Customer support / QA lead #1 (1 = hired) | B7: flag | C7: =0 -> 0 | D7: =MAX(C7,IF(IF(Assumptions!$B$187="Customers",C36,C43)>=Assumptions!$C$187,1,0)) -> 0 | E7: =MAX(D7,IF(IF(Assumptions!$B$187="Customers",D36,D43)>=Assumptions!$C$187,1,0)) -> 0 | F7: =MAX(E7,IF(IF(Assumptions!$B$187="Customers",E36,E43)>=Assumptions!$C$187,1,0)) -> 0 | G7: =MAX(F7,IF(IF(Assumptions!$B$187="Customers",F36,F43)>=Assumptions!$C$187,1,0)) -> 0 | H7: =MAX(G7,IF(IF(Assumptions!$B$187="Customers",G36,G43)>=Assumptions!$C$187,1,0)) -> 0 | I7: =MAX(H7,IF(IF(Assumptions!$B$187="Customers",H36,H43)>=Assumptions!$C$187,1,0)) -> 0 | J7: =MAX(I7,IF(IF(Assumptions!$B$187="Customers",I36,I43)>=Assumptions!$C$187,1,0)) -> 0 | K7: =MAX(J7,IF(IF(Assumptions!$B$187="Customers",J36,J43)>=Assumptions!$C$187,1,0)) -> 0 | ... AL7: =MAX(AK7,IF(IF(Assumptions!$B$187="Customers",AK36,AK43)>=Assumptions!$C$187,1,0)) -> 1
A8: Senior engineer #1 (1 = hired) | B8: flag | C8: =0 -> 0 | D8: =MAX(C8,IF(IF(Assumptions!$B$188="Customers",C36,C43)>=Assumptions!$C$188,1,0)) -> 0 | E8: =MAX(D8,IF(IF(Assumptions!$B$188="Customers",D36,D43)>=Assumptions!$C$188,1,0)) -> 0 | F8: =MAX(E8,IF(IF(Assumptions!$B$188="Customers",E36,E43)>=Assumptions!$C$188,1,0)) -> 0 | G8: =MAX(F8,IF(IF(Assumptions!$B$188="Customers",F36,F43)>=Assumptions!$C$188,1,0)) -> 0 | H8: =MAX(G8,IF(IF(Assumptions!$B$188="Customers",G36,G43)>=Assumptions!$C$188,1,0)) -> 0 | I8: =MAX(H8,IF(IF(Assumptions!$B$188="Customers",H36,H43)>=Assumptions!$C$188,1,0)) -> 0 | J8: =MAX(I8,IF(IF(Assumptions!$B$188="Customers",I36,I43)>=Assumptions!$C$188,1,0)) -> 0 | K8: =MAX(J8,IF(IF(Assumptions!$B$188="Customers",J36,J43)>=Assumptions!$C$188,1,0)) -> 0 | ... AL8: =MAX(AK8,IF(IF(Assumptions!$B$188="Customers",AK36,AK43)>=Assumptions!$C$188,1,0)) -> 1
A9: Account executive #1 (developers) (1 = hired) | B9: flag | C9: =0 -> 0 | D9: =MAX(C9,IF(IF(Assumptions!$B$189="Customers",C36,C43)>=Assumptions!$C$189,1,0)) -> 0 | E9: =MAX(D9,IF(IF(Assumptions!$B$189="Customers",D36,D43)>=Assumptions!$C$189,1,0)) -> 0 | F9: =MAX(E9,IF(IF(Assumptions!$B$189="Customers",E36,E43)>=Assumptions!$C$189,1,0)) -> 0 | G9: =MAX(F9,IF(IF(Assumptions!$B$189="Customers",F36,F43)>=Assumptions!$C$189,1,0)) -> 0 | H9: =MAX(G9,IF(IF(Assumptions!$B$189="Customers",G36,G43)>=Assumptions!$C$189,1,0)) -> 0 | I9: =MAX(H9,IF(IF(Assumptions!$B$189="Customers",H36,H43)>=Assumptions!$C$189,1,0)) -> 0 | J9: =MAX(I9,IF(IF(Assumptions!$B$189="Customers",I36,I43)>=Assumptions!$C$189,1,0)) -> 0 | K9: =MAX(J9,IF(IF(Assumptions!$B$189="Customers",J36,J43)>=Assumptions!$C$189,1,0)) -> 0 | ... AL9: =MAX(AK9,IF(IF(Assumptions!$B$189="Customers",AK36,AK43)>=Assumptions!$C$189,1,0)) -> 1
A10: Founder salary uplift to market (1 = hired) | B10: flag | C10: =0 -> 0 | D10: =MAX(C10,IF(IF(Assumptions!$B$190="Customers",C36,C43)>=Assumptions!$C$190,1,0)) -> 0 | E10: =MAX(D10,IF(IF(Assumptions!$B$190="Customers",D36,D43)>=Assumptions!$C$190,1,0)) -> 0 | F10: =MAX(E10,IF(IF(Assumptions!$B$190="Customers",E36,E43)>=Assumptions!$C$190,1,0)) -> 0 | G10: =MAX(F10,IF(IF(Assumptions!$B$190="Customers",F36,F43)>=Assumptions!$C$190,1,0)) -> 0 | H10: =MAX(G10,IF(IF(Assumptions!$B$190="Customers",G36,G43)>=Assumptions!$C$190,1,0)) -> 0 | I10: =MAX(H10,IF(IF(Assumptions!$B$190="Customers",H36,H43)>=Assumptions!$C$190,1,0)) -> 0 | J10: =MAX(I10,IF(IF(Assumptions!$B$190="Customers",I36,I43)>=Assumptions!$C$190,1,0)) -> 0 | K10: =MAX(J10,IF(IF(Assumptions!$B$190="Customers",J36,J43)>=Assumptions!$C$190,1,0)) -> 0 | ... AL10: =MAX(AK10,IF(IF(Assumptions!$B$190="Customers",AK36,AK43)>=Assumptions!$C$190,1,0)) -> 1
A11: Senior engineer #2 (1 = hired) | B11: flag | C11: =0 -> 0 | D11: =MAX(C11,IF(IF(Assumptions!$B$191="Customers",C36,C43)>=Assumptions!$C$191,1,0)) -> 0 | E11: =MAX(D11,IF(IF(Assumptions!$B$191="Customers",D36,D43)>=Assumptions!$C$191,1,0)) -> 0 | F11: =MAX(E11,IF(IF(Assumptions!$B$191="Customers",E36,E43)>=Assumptions!$C$191,1,0)) -> 0 | G11: =MAX(F11,IF(IF(Assumptions!$B$191="Customers",F36,F43)>=Assumptions!$C$191,1,0)) -> 0 | H11: =MAX(G11,IF(IF(Assumptions!$B$191="Customers",G36,G43)>=Assumptions!$C$191,1,0)) -> 0 | I11: =MAX(H11,IF(IF(Assumptions!$B$191="Customers",H36,H43)>=Assumptions!$C$191,1,0)) -> 0 | J11: =MAX(I11,IF(IF(Assumptions!$B$191="Customers",I36,I43)>=Assumptions!$C$191,1,0)) -> 0 | K11: =MAX(J11,IF(IF(Assumptions!$B$191="Customers",J36,J43)>=Assumptions!$C$191,1,0)) -> 0 | ... AL11: =MAX(AK11,IF(IF(Assumptions!$B$191="Customers",AK36,AK43)>=Assumptions!$C$191,1,0)) -> 1
A12: Customer success #2 (1 = hired) | B12: flag | C12: =0 -> 0 | D12: =MAX(C12,IF(IF(Assumptions!$B$192="Customers",C36,C43)>=Assumptions!$C$192,1,0)) -> 0 | E12: =MAX(D12,IF(IF(Assumptions!$B$192="Customers",D36,D43)>=Assumptions!$C$192,1,0)) -> 0 | F12: =MAX(E12,IF(IF(Assumptions!$B$192="Customers",E36,E43)>=Assumptions!$C$192,1,0)) -> 0 | G12: =MAX(F12,IF(IF(Assumptions!$B$192="Customers",F36,F43)>=Assumptions!$C$192,1,0)) -> 0 | H12: =MAX(G12,IF(IF(Assumptions!$B$192="Customers",G36,G43)>=Assumptions!$C$192,1,0)) -> 0 | I12: =MAX(H12,IF(IF(Assumptions!$B$192="Customers",H36,H43)>=Assumptions!$C$192,1,0)) -> 0 | J12: =MAX(I12,IF(IF(Assumptions!$B$192="Customers",I36,I43)>=Assumptions!$C$192,1,0)) -> 0 | K12: =MAX(J12,IF(IF(Assumptions!$B$192="Customers",J36,J43)>=Assumptions!$C$192,1,0)) -> 0 | ... AL12: =MAX(AK12,IF(IF(Assumptions!$B$192="Customers",AK36,AK43)>=Assumptions!$C$192,1,0)) -> 1
A13: Marketing manager (1 = hired) | B13: flag | C13: =0 -> 0 | D13: =MAX(C13,IF(IF(Assumptions!$B$193="Customers",C36,C43)>=Assumptions!$C$193,1,0)) -> 0 | E13: =MAX(D13,IF(IF(Assumptions!$B$193="Customers",D36,D43)>=Assumptions!$C$193,1,0)) -> 0 | F13: =MAX(E13,IF(IF(Assumptions!$B$193="Customers",E36,E43)>=Assumptions!$C$193,1,0)) -> 0 | G13: =MAX(F13,IF(IF(Assumptions!$B$193="Customers",F36,F43)>=Assumptions!$C$193,1,0)) -> 0 | H13: =MAX(G13,IF(IF(Assumptions!$B$193="Customers",G36,G43)>=Assumptions!$C$193,1,0)) -> 0 | I13: =MAX(H13,IF(IF(Assumptions!$B$193="Customers",H36,H43)>=Assumptions!$C$193,1,0)) -> 0 | J13: =MAX(I13,IF(IF(Assumptions!$B$193="Customers",I36,I43)>=Assumptions!$C$193,1,0)) -> 0 | K13: =MAX(J13,IF(IF(Assumptions!$B$193="Customers",J36,J43)>=Assumptions!$C$193,1,0)) -> 0 | ... AL13: =MAX(AK13,IF(IF(Assumptions!$B$193="Customers",AK36,AK43)>=Assumptions!$C$193,1,0)) -> 1
A14: Account executive #2 (1 = hired) | B14: flag | C14: =0 -> 0 | D14: =MAX(C14,IF(IF(Assumptions!$B$194="Customers",C36,C43)>=Assumptions!$C$194,1,0)) -> 0 | E14: =MAX(D14,IF(IF(Assumptions!$B$194="Customers",D36,D43)>=Assumptions!$C$194,1,0)) -> 0 | F14: =MAX(E14,IF(IF(Assumptions!$B$194="Customers",E36,E43)>=Assumptions!$C$194,1,0)) -> 0 | G14: =MAX(F14,IF(IF(Assumptions!$B$194="Customers",F36,F43)>=Assumptions!$C$194,1,0)) -> 0 | H14: =MAX(G14,IF(IF(Assumptions!$B$194="Customers",G36,G43)>=Assumptions!$C$194,1,0)) -> 0 | I14: =MAX(H14,IF(IF(Assumptions!$B$194="Customers",H36,H43)>=Assumptions!$C$194,1,0)) -> 0 | J14: =MAX(I14,IF(IF(Assumptions!$B$194="Customers",I36,I43)>=Assumptions!$C$194,1,0)) -> 0 | K14: =MAX(J14,IF(IF(Assumptions!$B$194="Customers",J36,J43)>=Assumptions!$C$194,1,0)) -> 0 | ... AL14: =MAX(AK14,IF(IF(Assumptions!$B$194="Customers",AK36,AK43)>=Assumptions!$C$194,1,0)) -> 0
A15: Graphics / 3D engineer #3 (1 = hired) | B15: flag | C15: =0 -> 0 | D15: =MAX(C15,IF(IF(Assumptions!$B$195="Customers",C36,C43)>=Assumptions!$C$195,1,0)) -> 0 | E15: =MAX(D15,IF(IF(Assumptions!$B$195="Customers",D36,D43)>=Assumptions!$C$195,1,0)) -> 0 | F15: =MAX(E15,IF(IF(Assumptions!$B$195="Customers",E36,E43)>=Assumptions!$C$195,1,0)) -> 0 | G15: =MAX(F15,IF(IF(Assumptions!$B$195="Customers",F36,F43)>=Assumptions!$C$195,1,0)) -> 0 | H15: =MAX(G15,IF(IF(Assumptions!$B$195="Customers",G36,G43)>=Assumptions!$C$195,1,0)) -> 0 | I15: =MAX(H15,IF(IF(Assumptions!$B$195="Customers",H36,H43)>=Assumptions!$C$195,1,0)) -> 0 | J15: =MAX(I15,IF(IF(Assumptions!$B$195="Customers",I36,I43)>=Assumptions!$C$195,1,0)) -> 0 | K15: =MAX(J15,IF(IF(Assumptions!$B$195="Customers",J36,J43)>=Assumptions!$C$195,1,0)) -> 0 | ... AL15: =MAX(AK15,IF(IF(Assumptions!$B$195="Customers",AK36,AK43)>=Assumptions!$C$195,1,0)) -> 0
A16: Customer success #3 (1 = hired) | B16: flag | C16: =0 -> 0 | D16: =MAX(C16,IF(IF(Assumptions!$B$196="Customers",C36,C43)>=Assumptions!$C$196,1,0)) -> 0 | E16: =MAX(D16,IF(IF(Assumptions!$B$196="Customers",D36,D43)>=Assumptions!$C$196,1,0)) -> 0 | F16: =MAX(E16,IF(IF(Assumptions!$B$196="Customers",E36,E43)>=Assumptions!$C$196,1,0)) -> 0 | G16: =MAX(F16,IF(IF(Assumptions!$B$196="Customers",F36,F43)>=Assumptions!$C$196,1,0)) -> 0 | H16: =MAX(G16,IF(IF(Assumptions!$B$196="Customers",G36,G43)>=Assumptions!$C$196,1,0)) -> 0 | I16: =MAX(H16,IF(IF(Assumptions!$B$196="Customers",H36,H43)>=Assumptions!$C$196,1,0)) -> 0 | J16: =MAX(I16,IF(IF(Assumptions!$B$196="Customers",I36,I43)>=Assumptions!$C$196,1,0)) -> 0 | K16: =MAX(J16,IF(IF(Assumptions!$B$196="Customers",J36,J43)>=Assumptions!$C$196,1,0)) -> 0 | ... AL16: =MAX(AK16,IF(IF(Assumptions!$B$196="Customers",AK36,AK43)>=Assumptions!$C$196,1,0)) -> 0
A17: Total headcount incl. founder | B17: FTE | C17: =1+C7+C8+C9+C11+C12+C13+C14+C15+C16 -> 1 | D17: =1+D7+D8+D9+D11+D12+D13+D14+D15+D16 -> 1 | E17: =1+E7+E8+E9+E11+E12+E13+E14+E15+E16 -> 1 | F17: =1+F7+F8+F9+F11+F12+F13+F14+F15+F16 -> 1 | G17: =1+G7+G8+G9+G11+G12+G13+G14+G15+G16 -> 1 | H17: =1+H7+H8+H9+H11+H12+H13+H14+H15+H16 -> 1 | I17: =1+I7+I8+I9+I11+I12+I13+I14+I15+I16 -> 1 | J17: =1+J7+J8+J9+J11+J12+J13+J14+J15+J16 -> 1 | ... AL17: =1+AL7+AL8+AL9+AL11+AL12+AL13+AL14+AL15+AL16 -> 7
A18: Account executives in seat | B18: FTE | C18: =C9+C14 -> 0 | D18: =D9+D14 -> 0 | E18: =E9+E14 -> 0 | F18: =F9+F14 -> 0 | G18: =G9+G14 -> 0 | H18: =H9+H14 -> 0 | I18: =I9+I14 -> 0 | J18: =J9+J14 -> 0 | ... AL18: =AL9+AL14 -> 1
A19: Productive AEs (in seat ≥ ramp months) | B19: FTE | C19: =IF(C$3>Assumptions!$D$140,OFFSET(C18,0,-Assumptions!$D$140),0) -> 0 | D19: =IF(D$3>Assumptions!$D$140,OFFSET(D18,0,-Assumptions!$D$140),0) -> 0 | E19: =IF(E$3>Assumptions!$D$140,OFFSET(E18,0,-Assumptions!$D$140),0) -> 0 | F19: =IF(F$3>Assumptions!$D$140,OFFSET(F18,0,-Assumptions!$D$140),0) -> 0 | G19: =IF(G$3>Assumptions!$D$140,OFFSET(G18,0,-Assumptions!$D$140),0) -> 0 | H19: =IF(H$3>Assumptions!$D$140,OFFSET(H18,0,-Assumptions!$D$140),0) -> 0 | I19: =IF(I$3>Assumptions!$D$140,OFFSET(I18,0,-Assumptions!$D$140),0) -> 0 | J19: =IF(J$3>Assumptions!$D$140,OFFSET(J18,0,-Assumptions!$D$140),0) -> 0 | ... AL19: =IF(AL$3>Assumptions!$D$140,OFFSET(AL18,0,-Assumptions!$D$140),0) -> 1
A21: Customers
A22: New customers — Studio | B22: logos | C22: =IF(C$3<Assumptions!$D$122,0,MIN(Assumptions!$D$134,Assumptions!$D$126+Assumptions!$D$130*(C$3-Assumptions!$D$122))) -> 0 | D22: =IF(D$3<Assumptions!$D$122,0,MIN(Assumptions!$D$134,Assumptions!$D$126+Assumptions!$D$130*(D$3-Assumptions!$D$122))) -> 0 | E22: =IF(E$3<Assumptions!$D$122,0,MIN(Assumptions!$D$134,Assumptions!$D$126+Assumptions!$D$130*(E$3-Assumptions!$D$122))) -> 0 | F22: =IF(F$3<Assumptions!$D$122,0,MIN(Assumptions!$D$134,Assumptions!$D$126+Assumptions!$D$130*(F$3-Assumptions!$D$122))) -> 0 | G22: =IF(G$3<Assumptions!$D$122,0,MIN(Assumptions!$D$134,Assumptions!$D$126+Assumptions!$D$130*(G$3-Assumptions!$D$122))) -> 0 | H22: =IF(H$3<Assumptions!$D$122,0,MIN(Assumptions!$D$134,Assumptions!$D$126+Assumptions!$D$130*(H$3-Assumptions!$D$122))) -> 1.5 | I22: =IF(I$3<Assumptions!$D$122,0,MIN(Assumptions!$D$134,Assumptions!$D$126+Assumptions!$D$130*(I$3-Assumptions!$D$122))) -> 1.75 | J22: =IF(J$3<Assumptions!$D$122,0,MIN(Assumptions!$D$134,Assumptions!$D$126+Assumptions!$D$130*(J$3-Assumptions!$D$122))) -> 2 | ... AL22: =IF(AL$3<Assumptions!$D$122,0,MIN(Assumptions!$D$134,Assumptions!$D$126+Assumptions!$D$130*(AL$3-Assumptions!$D$122))) -> 9
A23: New customers — Agency | B23: logos | C23: =IF(C$3<Assumptions!$D$123,0,MIN(Assumptions!$D$135,Assumptions!$D$127+Assumptions!$D$131*(C$3-Assumptions!$D$123))) -> 0 | D23: =IF(D$3<Assumptions!$D$123,0,MIN(Assumptions!$D$135,Assumptions!$D$127+Assumptions!$D$131*(D$3-Assumptions!$D$123))) -> 0 | E23: =IF(E$3<Assumptions!$D$123,0,MIN(Assumptions!$D$135,Assumptions!$D$127+Assumptions!$D$131*(E$3-Assumptions!$D$123))) -> 0 | F23: =IF(F$3<Assumptions!$D$123,0,MIN(Assumptions!$D$135,Assumptions!$D$127+Assumptions!$D$131*(F$3-Assumptions!$D$123))) -> 0 | G23: =IF(G$3<Assumptions!$D$123,0,MIN(Assumptions!$D$135,Assumptions!$D$127+Assumptions!$D$131*(G$3-Assumptions!$D$123))) -> 0 | H23: =IF(H$3<Assumptions!$D$123,0,MIN(Assumptions!$D$135,Assumptions!$D$127+Assumptions!$D$131*(H$3-Assumptions!$D$123))) -> 0 | I23: =IF(I$3<Assumptions!$D$123,0,MIN(Assumptions!$D$135,Assumptions!$D$127+Assumptions!$D$131*(I$3-Assumptions!$D$123))) -> 0.3 | J23: =IF(J$3<Assumptions!$D$123,0,MIN(Assumptions!$D$135,Assumptions!$D$127+Assumptions!$D$131*(J$3-Assumptions!$D$123))) -> 0.38 | ... AL23: =IF(AL$3<Assumptions!$D$123,0,MIN(Assumptions!$D$135,Assumptions!$D$127+Assumptions!$D$131*(AL$3-Assumptions!$D$123))) -> 2.62
